Workbook

Sheet Articles
A1: No | B1: Date | C1: Year | D1: Title | E1: Keyword group (Tamil) | F1: Keyword group (English) | G1: Matched terms | H1: Places mentioned | I1: Source | J1: Source country | K1: Language | L1: URL | M1: Archive copy | N1: Snippet | O1: Match basis | P1: Found via | Q1: Found on
A2: 1 | B2: 2026-10-29 | C2: 2026 | D2: பாண்டியர் கால கல்வெட்டு புதுக்கோட்டையில் கண்டெடுப்பு | E2: கல்வெட்டு | F2: Inscription / Epigraphy | G2: கல்வெட்டு | I2: dinamalar.com | J2: India | K2: Tamil | L2: https://www.dinamalar.com/templenews/165979 | N2: பாண்டியர் கால கல்வெட்டு புதுக்கோட்டையில் கண்டெடுப்பு புதுக்கோட்டை: புதுக்கோட்டை மாவட்டம், பொதுஒக்கூர் என்ற ஊரில், வரலாற்று ஆய்வாளர் காளிதாஸ் குழுவினர், கள ஆய்வு மேற்கொண்டனர். அப்போது, பிள்ளையார் கோவில் திடலுக்கு அருகே கல்வெட்டு ஒன்று, மண்ணில் புதையுண்டு கிடப்பதை கண்டெடுத்தனர். இது குறித்து, காளிதாஸ்… | O2: full-text | P2: gnews | Q2: 2026-10-30
A3: 2 | B3: 2026-10-28 | C3: 2026 | D3: கீழடி அருங்காட்சியகத்தில் ஆய்வு | E3: தொல்லியல் | F3: Archaeology / Excavation | G3: தொல்லியல், தொல்லியல் துறை, அகழாய்வு, கீழடி | I3: dinamalar.com | J3: India | K3: Tamil | L3: https://www.dinamalar.com/news/tamil-nadu-district-news-sivagangai/exploration-at-the-keezhadi-museum/4361468 | N3: உள்ளடக்கத்திற்கு செல்ல ADDED : அக் 28, 2026 07:11 PM அ நிறம் | அளவு கீழடி: தமிழக தொல்லியல் துறை கமிஷனராக சங்கர் செப்டம்பரில் நியமிக்கப்பட்டார். இதனையடுத்து கீழடி தொல் பொருள் மற்றும் திறந்த வெளி அருங்காட்சியகம், 11ம் கட்ட அகழாய்வு நடைபெறும் இடங்கள் ஆகியவற்றை ஆய்வு செய்தார். அருங்காட்சியகத்தில் கூடுதல… | O3: full-text | P3: gnews | Q3: 2026-10-29
A4: 3 | B4: 2026-10-28 | C4: 2026 | D4: பாண்டியர் கால கல்வெட்டு புதுக்கோட்டையில் கண்டெடுப்பு | E4: கல்வெட்டு | F4: Inscription / Epigraphy | G4: கல்வெட்டு | I4: dinamalar.com | J4: India | K4: Tamil | L4: https://www.dinamalar.com/news/tamil-nadu-district-news-pudukottai/pandyan-period-inscription-discovered-in-pudukkottai/4360672 | N4: உள்ளடக்கத்திற்கு செல்ல பாண்டியர் கால கல்வெட்டு புதுக்கோட்டையில் கண்டெடுப்பு UPDATED : அக் 27, 2026 07:10 PM ADDED : அக் 27, 2026 07:00 PM புதுக்கோட்டை: புதுக்கோட்டை மாவட்டம், பொதுஒக்கூர் என்ற ஊரில், வரலாற்று ஆய்வாளர் காளிதாஸ் குழுவினர், கள ஆய்வு மேற்கொண்டனர். அப்போது, பிள்ளையார் கோவில் திடலுக்கு அரு… | O4: full-text | P4: gnews | Q4: 2026-10-28
A5: 4 | B5: 2026-10-28 | C5: 2026 | D5: பாண்டியர் கால கல்வெட்டு புதுக்கோட்டையில் கண்டெடுப்பு | E5: கல்வெட்டு | F5: Inscription / Epigraphy | G5: கல்வெட்டு | H5: Kerala | I5: temple.dinamalar.com | J5: India | K5: Tamil | L5: https://temple.dinamalar.com/news_detail.php?id=165979 | N5: | | | | முதல் பக்கம் » இன்றைய செய்திகள் | | | பாண்டியர் கால கல்வெட்டு புதுக்கோட்டையில் கண்டெடுப்பு பதிவு செய்த நாள் 28 அக் 2026 11:10 புதுக்கோட்டை: புதுக்கோட்டை மாவட்டம், பொதுஒக்கூர் என்ற ஊரில், வரலாற்று ஆய்வாளர் காளிதாஸ் குழுவினர், கள ஆய்வு மேற்கொண்டனர். அப்போது, பிள்ளையார் கோவில் திடலுக்கு அருகே க… | O5: full-text | P5: gnews | Q5: 2026-10-29
A6: 5 | B6: 2026-10-27 | C6: 2026 | D6: 10ம் நுாற்றாண்டு கல்வெட்டு அகத்தீஸ்வரர் கோவிலில் கண்டுபிடிப்பு | E6: கல்வெட்டு, தொல்லியல் | F6: Inscription / Epigraphy, Archaeology / Excavation | G6: கல்வெட்டு, கல்வெட்டுகள், தொல்லியல் | I6: dinamalar.com | J6: India | K6: Tamil | L6: https://www.dinamalar.com/news/tamil-nadu-district-news-kancheepuram/10th-century-inscription-discovered-in-agadheshwara-temple/4359447 | N6: உள்ளடக்கத்திற்கு செல்ல 10ம் நுாற்றாண்டு கல்வெட்டு அகத்தீஸ்வரர் கோவிலில் கண்டுபிடிப்பு ADDED : அக் 26, 2026 04:26 PM வாலாஜாபாத்: வல்லப்பாக்கம் அகத்தீஸ்வரர் கோவிலில், 10ம் நுாற்றாண்டைச் சேர்ந்த கல்வெட்டு நேற்று (அக்.,25) கண்டுபிடிக்கபட்டு உள்ளது. இதுகுறித்து, வாலாஜாபாத் வட்டார வரலாற்று ஆய்வு மைய தலைவர… | O6: full-text | P6: gnews | Q6: 2026-10-27
A7: 6 | B7: 2026-10-27 | C7: 2026 | D7: தமிழ் ஆசிரியர்கள் பறக்கலாம்!: நம்பிக்கை அளிக்கிறார் பேரூர் ஆதினம் | E7: கல்வெட்டு, தொல்லியல் | F7: Inscription / Epigraphy, Archaeology / Excavation | G7: கல்வெட்டு, தொல்பொருள் | H7: Sri Lanka, Malaysia | I7: dinamalar.com | J7: India | K7: Tamil | L7: https://www.dinamalar.com/news_detail.asp?id=2268888 | N7: உள்ளடக்கத்திற்கு செல்ல தமிழ் ஆசிரியர்கள் 'பறக்கலாம்!': நம்பிக்கை அளிக்கிறார் பேரூர் ஆதினம் UPDATED : மே 04, 2019 02:00 AM ADDED : மே 04, 2019 01:13 AM 'தமிழ் படிச்சு என்னங்க ஆகப்போகுது...பேசாம பி.காம் சேர்த்து விட்டுருங்க...பேங்குலயாவது வேலை கிடைக்கும்'- இப்படி பெற்றோர்களை தவறாக வழிநடத்தும் கல்வியாள… | O7: full-text | P7: gdelt | Q7: 2026-10-27
A8: 7 | B8: 2026-10-26 | C8: 2026 | D8: 13th Century Hero Stone Helps Understand Medieval History | E8: கல்வெட்டு, நடுகல், தொல்லியல் | F8: Inscription / Epigraphy, Hero stone / Memorial stone, Archaeology / Excavation | G8: inscription, inscriptions, inscribed, hero stone, hero stones, hero-stone, archaeological | H8: Tamil Nadu | I8: deccanchronicle.com | J8: India | K8: English/Other | L8: https://www.deccanchronicle.com/amp/southern-states/tamil-nadu/13th-century-hero-stone-helps-understand-medieval-history-1998923 | N8: 13th Century Hero Stone Helps Understand Medieval History In view of the relative rarity of inscriptions from the period of Vira Vishwanatha in Tamil Nadu, this discovery represents a significant documentary source for further research into the region’s medieval political history COIMBATORE: On the … | O8: full-text | P8: gnews | Q8: 2026-10-27
A9: 8 | B9: 2026-10-26 | C9: 2026 | D9: 13th Century Hero Stone Helps Understand Medieval History | E9: கல்வெட்டு, நடுகல், தொல்லியல் | F9: Inscription / Epigraphy, Hero stone / Memorial stone, Archaeology / Excavation | G9: inscription, inscriptions, inscribed, hero stone, hero stones, hero-stone, archaeological | H9: Tamil Nadu | I9: deccanchronicle.com | J9: India | K9: English/Other | L9: https://www.deccanchronicle.com/southern-states/tamil-nadu/13th-century-hero-stone-helps-understand-medieval-history-1998923 | N9: 13th Century Hero Stone Helps Understand Medieval History In view of the relative rarity of inscriptions from the period of Vira Vishwanatha in Tamil Nadu, this discovery represents a significant documentary source for further research into the region’s medieval political history COIMBATORE: On the … | O9: full-text | P9: gnews | Q9: 2026-10-27
A10: 9 | B10: 2026-10-26 | C10: 2026 | D10: 6th-Century Dharmapuri Hero Stone Sheds Light on Ancient Tamil Nadu | E10: கல்வெட்டு, நடுகல் | F10: Inscription / Epigraphy, Hero stone / Memorial stone | G10: inscriptions, hero stone, hero-stone | H10: Tamil Nadu | I10: deccanchronicle.com | J10: India | K10: English/Other | L10: https://www.deccanchronicle.com/through-the-lens/6th-century-dharmapuri-hero-stone-sheds-light-on-ancient-tamil-nadu-1998926 | N10: 6th-Century Dharmapuri Hero Stone Sheds Light on Ancient Tamil Nadu The newly-documented ‘hero stone inscriptions’ in Dharmapuri belt sheds light on the history of ancient Tamil Nadu as researchers from the Yaakkai Heritage Trust, based in Coimbatore, documented two hero stone inscriptions during fi… | O10: full-text | P10: gnews | Q10: 2026-10-27
A11: 10 | B11: 2026-10-26 | C11: 2026 | D11: Ancient terracotta lamp unearthed in Tamil Nadus Vembakottai | E11: தொல்லியல் | F11: Archaeology / Excavation | G11: archaeology, vembakottai | H11: Tamil Nadu | I11: news.webindia123.com | J11: Unknown | K11: English/Other | L11: https://news.webindia123.com/news/Articles/India/20220504/3937813.html | N11: Monday, October 26, 2026 News | | | Ancient terracotta lamp unearthed in Tamil Nadu's Vembakottai Chennai \| Wednesday, 2022 3:45:09 AM IST | | Excavations at Vembakottai in Virudhunagar district of Tamil Nadu have unearthed an ancient terracotta lamp, which according to archaeologists is an intrins… | O11: full-text | P11: gdelt | Q11: 2026-10-26
A12: 11 | B12: 2026-10-26 | C12: 2026 | D12: Dharmapuri Hero Stones Shed Light on Tamil Nadu’s History | E12: கல்வெட்டு, நடுகல், தொல்லியல் | F12: Inscription / Epigraphy, Hero stone / Memorial stone, Archaeology / Excavation | G12: inscription, inscriptions, epigraphist, vatteluttu, hero stone, hero stones, hero-stone, archaeological | H12: Tamil Nadu | I12: deccanchronicle.com | J12: India | K12: English/Other | L12: https://www.deccanchronicle.com/amp/southern-states/tamil-nadu/dharmapuri-hero-stones-shed-light-on-tamil-nadus-history-1998919 | N12: Dharmapuri Hero Stones Shed Light on Tamil Nadu’s History The newly-documented ‘hero stone inscriptions’ in Dharmapuri belt sheds light on the history of ancient Tamil Nadu as researchers from the Yaakkai Heritage Trust, based in Coimbatore, documented two hero stone inscriptions during field survey… | O12: full-text | P12: gnews | Q12: 2026-10-27
A13: 12 | B13: 2026-10-26 | C13: 2026 | D13: Dharmapuri Hero Stones Shed Light on Tamil Nadu’s History | E13: கல்வெட்டு, நடுகல், தொல்லியல் | F13: Inscription / Epigraphy, Hero stone / Memorial stone, Archaeology / Excavation | G13: inscription, inscriptions, epigraphist, vatteluttu, hero stone, hero stones, hero-stone, archaeological | H13: Tamil Nadu | I13: deccanchronicle.com | J13: India | K13: English/Other | L13: https://www.deccanchronicle.com/southern-states/tamil-nadu/dharmapuri-hero-stones-shed-light-on-tamil-nadus-history-1998919 | N13: Dharmapuri Hero Stones Shed Light on Tamil Nadu’s History The newly-documented ‘hero stone inscriptions’ in Dharmapuri belt sheds light on the history of ancient Tamil Nadu as researchers from the Yaakkai Heritage Trust, based in Coimbatore, documented two hero stone inscriptions during field survey… | O13: full-text | P13: gnews | Q13: 2026-10-27
A14: 13 | B14: 2026-10-26 | C14: 2026 | D14: நாயுடன் போருக்குச் சென்ற வீரன்... செஞ்சி அருகே 500 ஆண்டுகள் பழமையான நடுகல் கண்டுபிடிப்பு | E14: நடுகல் | F14: Hero stone / Memorial stone | G14: நடுகல் | I14: tamil.news18.com | J14: India | K14: Tamil | L14: https://tamil.news18.com/tamil-nadu/16th-century-hero-stone-discovered-near-gingee-in-villupuram-depicting-warrior-with-a-dog-pja-pdp-local18-2239455.html?utm_source=District%20Widget&utm_medium=Desktop&utm_campaign=tamil | N14: நாயுடன் போருக்குச் சென்ற வீரன்... செஞ்சி அருகே 500 ஆண்டுகள் பழமையான நடுகல் கண்டுபிடிப்பு - Reported by:Pooja S - Published by:pradeepa m Last Updated: இந்த நடுகல் கி.பி. 16-ஆம் நூற்றாண்டைச் சேர்ந்ததாகக் கருதப்படுகிறது. பிற்கால விஜயநகரப் பேரரசின் இறுதிக் காலத்துக்கும் தொடக்ககால நாயக்கர் ஆட்சிக் காலத்… | O14: full-text | P14: gnews | Q14: 2026-10-27
A15: 14 | B15: 2026-10-26 | C15: 2026 | D15: நாயுடன் போருக்குச் சென்ற வீரன்... செஞ்சி அருகே 500 ஆண்டுகள் பழமையான நடுகல் கண்டுபிடிப்பு | E15: நடுகல் | F15: Hero stone / Memorial stone | G15: நடுகல் | I15: tamil.news18.com | J15: India | K15: Tamil | L15: https://tamil.news18.com/tamil-nadu/16th-century-hero-stone-discovered-near-gingee-in-villupuram-depicting-warrior-with-a-dog-pja-pdp-local18-2239455.html | N15: நாயுடன் போருக்குச் சென்ற வீரன்... செஞ்சி அருகே 500 ஆண்டுகள் பழமையான நடுகல் கண்டுபிடிப்பு - Reported by:Pooja S - Published by:pradeepa m Last Updated: இந்த நடுகல் கி.பி. 16-ஆம் நூற்றாண்டைச் சேர்ந்ததாகக் கருதப்படுகிறது. பிற்கால விஜயநகரப் பேரரசின் இறுதிக் காலத்துக்கும் தொடக்ககால நாயக்கர் ஆட்சிக் காலத்… | O15: full-text | P15: gnews | Q15: 2026-10-27
A16: 15 | B16: 2026-10-25 | C16: 2026 | D16: ASI refutes Kanimozhi's claim over lack of facilities at Adichanallur heritage site | E16: தொல்லியல் | F16: Archaeology / Excavation | G16: archaeological, adichanallur | H16: Tamil Nadu | I16: aninews.in | J16: India | K16: English/Other | L16: https://www.aninews.in/news/national/general-news/asi-refutes-kanimozhis-claim-over-lack-of-facilities-at-adichanallur-heritage-site20210724135934/ | N16: New Delhi [India], July 24 (ANI): The Archaeological Survey of India (ASI) on Friday refuted DMK MP Kanimozhi's claim that there are no amenities like boundary walls, drinking water, toilets and solar lights around the Adichanallur heritage site in Tamil Nadu. "We Archaeological Survey of India is w… | O16: full-text | P16: gdelt | Q16: 2026-10-25
A17: 16 | B17: 2026-10-25 | C17: 2026 | D17: Assam: Thousands participate in Yoga Utsav in Sivasagar | E17: தொல்லியல் | F17: Archaeology / Excavation | G17: archaeological, adichanallur | H17: Tamil Nadu | I17: news.webindia123.com | J17: Unknown | K17: English/Other | L17: https://news.webindia123.com/news/Articles/India/20220502/3937227.html | N17: Sunday, October 25, 2026 News | | | Assam: Thousands participate in 'Yoga Utsav' in Sivasagar General News \| May 2, 2022 3:53:32 PM IST | | Sivasagar (Assam) [India], May 2: The Ayush Ministry with active support from the Assam government on Monday organised a Yoga Utsav at the iconic holy site of … | O17: full-text | P17: gdelt | Q17: 2026-10-25
A18: 17 | B18: 2026-10-25 | C18: 2026 | D18: Budget 2020: Govt allocates Rs 2,500 cr for development of tourism sector | E18: தொல்லியல் | F18: Archaeology / Excavation | G18: archaeology, archeological, adichanallur | H18: Tamil Nadu | I18: aninews.in | J18: India | K18: English/Other | L18: https://www.aninews.in/news/national/general-news/budget-2020-govt-allocates-rs-2500-cr-for-development-of-tourism-sector20200201205416/ | N18: New Delhi [India], Feb 1 (ANI): To make India an attractive destination for both international and domestic tourists, Finance Minister Nirmala Sitharaman on Saturday proposed to allocate Rs 2,500 crores in the Budget for FY2020-21 for the tourism sector. Besides tourism, Sitharaman also proposed to … | O18: full-text | P18: gdelt | Q18: 2026-10-25
A19: 18 | B19: 2026-10-25 | C19: 2026 | D19: FM Sitharaman proposes Rs 2,500 crore for tourism in 2020-21, eight new museums | E19: தொல்லியல் | F19: Archaeology / Excavation | G19: archeological, adichanallur | H19: Tamil Nadu | I19: aninews.in | J19: India | K19: English/Other | L19: https://www.aninews.in/news/national/general-news/fm-sitharaman-proposes-rs-2500-crore-for-tourism-in-2020-21-eight-new-museums20200201150419/ | N19: New Delhi [India], Feb 1 (ANI): Finance Minister Nirmala Sithraman on Saturday proposed to allocate Rs 2,500 crore in 2020-21 for the tourism sector and construction of eight new museums, which includes building infrastructure around 5 iconic sites. "To make India an attractive destination for both … | O19: full-text | P19: gdelt | Q19: 2026-10-25
A20: 19 | B20: 2026-10-25 | C20: 2026 | D20: Ministry of Ayush to celebrate Yoga Utsav to mark 50 days countdown to International Day of Yoga 2022 | E20: தொல்லியல் | F20: Archaeology / Excavation | G20: archaeological, adichanallur | H20: Tamil Nadu | I20: news.webindia123.com | J20: Unknown | K20: English/Other | L20: https://news.webindia123.com/news/Articles/Business/20220501/3937022.html | N20: Sunday, October 25, 2026 News | | | Ministry of Ayush to celebrate Yoga Utsav to mark 50 days countdown to International Day of Yoga 2022 New Delhi \| May 1, 2022 10:24:01 PM IST | | The Ministry of Ayush in collaboration with state Government of Assam is organizing a grand event at Rang Ghar Ground… | O20: full-text | P20: gdelt | Q20: 2026-10-25
A21: 20 | B21: 2026-10-25 | C21: 2026 | D21: NTK proposes new Tamil Nadu government emblem featuring Thiruvalluvar at election manifesto release program | E21: தொல்லியல் | F21: Archaeology / Excavation | G21: keeladi, adichanallur | H21: Tamil Nadu | I21: aninews.in | J21: India | K21: English/Other | L21: https://aninews.in/news/national/general-news/ntk-proposes-new-tamil-nadu-government-emblem-featuring-thiruvalluvar-at-election-manifesto-release-program20260319132156/ | N21: Chennai (Tamil Nadu) [India], March 19 (ANI): The Naam Tamilar Katchi (NTK) has proposed the new Tamil Nadu government emblem if the party comes to power in the state at the NTK Election Manifesto release program on Thursday in Chennai. According to the party, the redesigned emblem would prominently… | O21: full-text | P21: gdelt | Q21: 2026-10-25
A22: 21 | B22: 2026-10-25 | C22: 2026 | D22: Tamil Nadu floods: 35 deaths reported, focus now on restoring basic services, says chief secretary | E22: தொல்லியல் | F22: Archaeology / Excavation | G22: excavation site, adichanallur | H22: Tamil Nadu | I22: news.webindia123.com | J22: Unknown | K22: English/Other | L22: https://news.webindia123.com/news/Articles/India/20231223/4151975.html | N22: Sunday, October 25, 2026 News | | | Tamil Nadu floods: 35 deaths reported, focus now on restoring basic services, says chief secretary Thoothukudi (Tamil Nadu) \| December 23, 2023 10:21:28 PM IST | | Tamil Nadu Chief Secretary Shiv Das Meena said on Saturday that the rescue operation in the flood-a… | O22: full-text | P22: gdelt | Q22: 2026-10-25
A23: 22 | B23: 2026-10-25 | C23: 2026 | D23: Tamil Nadu: AIADMK, NDA allies hold massive protest against DMK in Dindigul | E23: தொல்லியல் | F23: Archaeology / Excavation | G23: archaeological, keezhadi, adichanallur | H23: Tamil Nadu | I23: aninews.in | J23: India | K23: English/Other | L23: https://aninews.in/news/national/politics/tamil-nadu-aiadmk-nda-allies-hold-massive-protest-against-dmk-in-dindigul20260318041556/ | N23: Dindigul (Tamil Nadu) [India], March 18 (ANI): The All India Anna Dravida Munnetra Kazhagam (AIADMK) and its National Democratic Alliance (NDA) partners staged a joint protest at the Dindigul Clock Tower area to condemn the policies of the state government led by Dravida Munnetra Kazhagam (DMK). AIA… | O23: full-text | P23: gdelt | Q23: 2026-10-25
A24: 23 | B24: 2026-10-25 | C24: 2026 | D24: Tamil Nadu: Political landscape heats up as Opposition protests against DMK ahead of polls | E24: தொல்லியல் | F24: Archaeology / Excavation | G24: archaeological, keezhadi, adichanallur | H24: Tamil Nadu | I24: aninews.in | J24: India | K24: English/Other | L24: https://aninews.in/news/national/politics/tamil-nadu-political-landscape-heats-up-as-opposition-protests-against-dmk-ahead-of-polls20260317180639/ | N24: Tiruppur (Tamil Nadu) [India], March 17 (ANI): The political temperature in Tamil Nadu heightened as opposition parties staged a large-scale protest in Tiruppur, targeting the ruling Dravida Munnetra Kazhagam (DMK) government while also highlighting central government support for local farmers. The … | O24: full-text | P24: gdelt | Q24: 2026-10-25
A25: 24 | B25: 2026-10-25 | C25: 2026 | D25: சிதிலமடைந்த அன்னதான மடத்தில் பழங்கால கல்வெட்டு கண்டெடுப்பு | E25: கல்வெட்டு, தொல்லியல் | F25: Inscription / Epigraphy, Archaeology / Excavation | G25: கல்வெட்டு, தொல்லியல் | I25: dailythanthi.com | J25: India | K25: Tamil | L25: https://www.dailythanthi.com/news/tamilnadu/ancient-inscription-discovered-in-ruined-annadhana-mutt | N25: தமிழக செய்திகள் சிதிலமடைந்த அன்னதான மடத்தில் பழங்கால கல்வெட்டு கண்டெடுப்பு 17 தூண்களுடன் கட்டப்பட்ட இந்த மடத்தில் தனியாக ஒரு விளக்குத்தூணும் உள்ளது. தென்காசி, வாசுதேவநல்லூர் அருகே தொல்லியல் ஆய்வில் சேதமடைந்த மடத்தில் கல்வெட்டு, பழங்கால சிற்பங்கள் கண்டுபிடிக்கப்பட்டுள்ளன. தென்பொதிகை ஆவணக்காப்பகத்தை ச… | O25: full-text | P25: gnews | Q25: 2026-10-26
A26: 25 | B26: 2026-10-25 | C26: 2026 | D26: செஞ்சி அருகே பழைமையான நடுகல் கண்டெடுப்பு | E26: நடுகல் | F26: Hero stone / Memorial stone | G26: நடுகல் | I26: dinamani.com | J26: India | K26: Tamil | L26: https://www.dinamani.com/all-editions/edition-villupuram/villupuram/2026/Oct/25/%E0%AE%9A%E0%AF%86%E0%AE%9E%E0%AF%8D%E0%AE%9A%E0%AE%BF-%E0%AE%85%E0%AE%B0%E0%AF%81%E0%AE%95%E0%AF%87-%E0%AE%AA%E0%AE%B4%E0%AF%88%E0%AE%AE%E0%AF%88%E0%AE%AF%E0%AE%BE%E0%AE%A9-%E0%AE%A8%E0%AE%9F%E0%AF%81%E0%AE%95%E0%AE%B2%E0%AF%8D-%E0%AE%95%E0%AE%A3%E0%AF%8D%E0%AE%9F%E0%AF%86%E0%AE%9F%E0%AF%81%E0%AE%AA%E0%AF%8D%E0%AE%AA%E0%AF%81 | N26: செஞ்சி அருகே பழைமையான நடுகல் கண்டெடுப்பு செஞ்சி அருகே கண்டெடுக்கப்பட்ட கி.பி.16-ஆம் நூற்றாண்டைச் சோ்ந்த நடுகல். விழுப்புரம் மாவட்டம், செஞ்சியை அடுத்துள்ள துத்தபப்பட்டு கிராமத்தில் 16-ஆம் நூற்றாண்டைச் சோ்ந்க நடுகல் கண்டறியப்பட்டது. செஞ்சி அரசு கலை, அறிவியல் கல்லூரி தமிழ்த் துறை பேராசிரியரும், திருவ… | O26: full-text | P26: gnews | Q26: 2026-10-26
A27: 26 | B27: 2026-10-24 | C27: 2026 | D27: "DMK does what it promises and promises only what it can deliver": Tamil Nadu CM MK Stalin | E27: தொல்லியல் | F27: Archaeology / Excavation | G27: archaeological, keeladi | H27: Tamil Nadu | I27: aninews.in | J27: India | K27: English/Other | L27: https://aninews.in/news/national/general-news/dmk-does-what-it-promises-and-promises-only-what-it-can-deliver-tamil-nadu-cm-mk-stalin20260131191642/ | N27: Sivagangai (Tamil Nadu) [India], January 31 (ANI): Tamil Nadu Chief Minister MK Stalin on Saturday recalled Sivaganga's rich legacy of Tamil civilisation, valour and sacrifice, stating that the district symbolises resistance, freedom and social justice. Addressing a public function, he referred to t… | O27: full-text | P27: gdelt | Q27: 2026-10-24
A28: 27 | B28: 2026-10-24 | C28: 2026 | D28: "Election fear and fever have continued to haunt him": Kanimozhi slams EPS | E28: தொல்லியல் | F28: Archaeology / Excavation | G28: keeladi | H28: Tamil Nadu | I28: aninews.in | J28: India | K28: English/Other | L28: https://aninews.in/news/national/politics/election-fear-and-fever-have-continued-to-haunt-him-kanimozhi-slams-eps20260410081826/ | N28: Erode (Tamil Nadu) [India], April 10 (ANI): DMK leader Kanimozhi Karunanidhi on Thursday hit out at Leader of Opposition in Tamil Nadu assembly Edappadi Palaniswami and said "election fear and fever have continued to haunt him". Speaking in a campaign to support Tamil Nadu minister and DMK candidate… | O28: full-text | P28: gdelt | Q28: 2026-10-24
A29: 28 | B29: 2026-10-24 | C29: 2026 | D29: "How do corrupt individuals get whitewashed after joining BJP?" MK Stalin bombards centre with questions, raises various issues | E29: தொல்லியல் | F29: Archaeology / Excavation | G29: keeladi | H29: Tamil Nadu | I29: aninews.in | J29: India | K29: English/Other | L29: https://aninews.in/news/national/politics/how-do-corrupt-individuals-get-whitewashed-after-joining-bjp-mk-stalin-bombards-centre-with-questions-raises-various-issues20251018135601/ | N29: Chennai (Tamil Nadu) [India], October 18 (ANI): Tamil Nadu Chief Minister MK Stalin on Saturday lambasted the centre over the naming of crucial government projects and legislations in Hindi and Sanskrit, saying that people across the nation had multiple questions. Raising the issue of corrupt indivi… | O29: full-text | P29: gdelt | Q29: 2026-10-24
A30: 29 | B30: 2026-10-24 | C30: 2026 | D30: 2,600-year-old terracotta pipeline found in India | E30: தொல்லியல் | F30: Archaeology / Excavation | G30: archaeology, archaeological, archaeological excavations, keeladi | H30: Tamil Nadu | I30: sott.net | J30: Unknown | K30: English/Other | L30: https://www.sott.net/article/493855-2600-year-old-terracotta-pipeline-found-in-India | N30: OF THE TIMES During the 10th phase of archaeological excavations at the Keeladi archaeological site in Tamil Nadu, India, archaeologists uncovered a terracotta pipeline that shows the existence of an ancient water management practice practiced by humans 2,600 years ago. Ancient city Keeladi in south… | O30: full-text | P30: gdelt | Q30: 2026-10-24
A31: 30 | B31: 2026-10-24 | C31: 2026 | D31: Ancient ring well found at paddy field near Keeladi excavation site | E31: தொல்லியல் | F31: Archaeology / Excavation | G31: archaeological, archeology, archeological, excavation site, keeladi | H31: Tamil Nadu | I31: news.webindia123.com | J31: Unknown | K31: English/Other | L31: https://news.webindia123.com/news/Articles/India/20211220/3877488.html | N31: Saturday, October 24, 2026 News | | | Ancient ring well found at paddy field near Keeladi excavation site Chennai \| Monday, 2021 10:45:08 PM IST | | Workers digging a pit in a paddy field 100 metres away from the proposed museum at the Keeladi excavation site were in for a surprise when the top of … | O31: full-text | P31: gdelt | Q31: 2026-10-24
A32: 31 | B32: 2026-10-24 | C32: 2026 | D32: DMK MP Kanimozhi meets PM Modi, thanks him for upgrade of Thoothukudi airport | E32: தொல்லியல் | F32: Archaeology / Excavation | G32: keeladi, keezhadi | H32: Tamil Nadu | I32: news.webindia123.com | J32: Unknown | K32: English/Other | L32: https://news.webindia123.com/news/Articles/India/20250808/4347655.html | N32: Saturday, October 24, 2026 News | | | DMK MP Kanimozhi meets PM Modi, thanks him for upgrade of Thoothukudi airport New Delhi \| August 8, 2025 8:45:16 PM IST | | Dravida Munnetra Kazhagam (DMK) MP Kanimozhi on Friday met Prime Minister Narendra Modi in the national capital, where she raised importa… | O32: full-text | P32: gdelt | Q32: 2026-10-24
A33: 32 | B33: 2026-10-24 | C33: 2026 | D33: DMK does what it promises and promises only what it can deliver: Tamil Nadu CM MK Stalin | E33: தொல்லியல் | F33: Archaeology / Excavation | G33: archaeological, keeladi | H33: Tamil Nadu | I33: news.webindia123.com | J33: Unknown | K33: English/Other | L33: https://news.webindia123.com/news/Articles/India/20260131/4411075.html | N33: Saturday, October 24, 2026 News | | | "DMK does what it promises and promises only what it can deliver": Tamil Nadu CM MK Stalin Sivagangai (Tamil Nadu) \| January 31, 2026 7:50:19 PM IST | | Tamil Nadu Chief Minister MK Stalin on Saturday recalled Sivaganga's rich legacy of Tamil civilisation, valo… | O33: full-text | P33: gdelt | Q33: 2026-10-24
A34: 33 | B34: 2026-10-24 | C34: 2026 | D34: Dravidian iron for the Aryan horse - The Economic Times | E34: தொல்லியல் | F34: Archaeology / Excavation | G34: archaeology, keeladi | H34: Tamil Nadu, Egypt, China | I34: economictimes.indiatimes.com | J34: Unknown | K34: English/Other | L34: https://economictimes.indiatimes.com/opinion/et-commentary/dravidian-iron-for-the-aryan-horse/articleshow/123325961.cms | N34: Colonial historians argued the ‘Aryan invasion theory’ that light-skinned chariot-riding people destroyed Harappan cities, conquered India, enslaved local dark-skinned people and created the caste system. To counter this, there was the ‘out of India’ theory popularised by many Brahmins, that Harappa… | O34: full-text | P34: gdelt | Q34: 2026-10-24
A35: 34 | B35: 2026-10-24 | C35: 2026 | D35: Election fear and fever have continued to haunt him: Kanimozhi slams EPS | E35: தொல்லியல் | F35: Archaeology / Excavation | G35: keeladi | H35: Tamil Nadu | I35: news.webindia123.com | J35: Unknown | K35: English/Other | L35: https://news.webindia123.com/news/Articles/India/20260410/4437393.html | N35: Saturday, October 24, 2026 News | | | "Election fear and fever have continued to haunt him": Kanimozhi slams EPS Erode (Tamil Nadu) \| April 10, 2026 8:52:28 AM IST | | DMK leader Kanimozhi Karunanidhi on Thursday hit out at Leader of Opposition in Tamil Nadu assembly Edappadi Palaniswami and said "… | O35: full-text | P35: gdelt | Q35: 2026-10-24
A36: 35 | B36: 2026-10-24 | C36: 2026 | D36: Human skeletal remains unearthed at TN's Kondagai excavation site | E36: தொல்லியல் | F36: Archaeology / Excavation | G36: archaeology, archeology, excavation site, keeladi | H36: Tamil Nadu | I36: aninews.in | J36: India | K36: English/Other | L36: https://www.aninews.in/news/national/general-news/human-skeletal-remains-unearthed-at-tns-kondagai-excavation-site20200813140212/ | N36: Madurai (Tamil Nadu) [India], Aug 13 (ANI): Human skeletal remains were unearthed from the Kondagai excavation site near Tamil Nadu's Madurai by the State's Department of Archaeology, on Wednesday. The remains have been sent to Madurai Kamaraj University for DNA analysis. While speaking to ANI, Siva… | O36: full-text | P36: gdelt | Q36: 2026-10-24
A37: 36 | B37: 2026-10-24 | C37: 2026 | D37: Rs 8876.57 cr allocated to police department in Tamil Nadu's budget | E37: தொல்லியல் | F37: Archaeology / Excavation | G37: keeladi | H37: Tamil Nadu | I37: aninews.in | J37: India | K37: English/Other | L37: https://www.aninews.in/news/national/general-news/rs-887657-cr-allocated-to-police-department-in-tamil-nadus-budget20200214110902/ | N37: Chennai (Tamil Nadu) [India], Feb 14 (ANI): The Tamil Nadu government has allocated a total amount of Rs 8876.57 Crores for the police department in the budget for this financial year. "A total amount of Rs 8876.57 Crores has been allocated for the police department, including Rs 431 Crores for the … | O37: full-text | P37: gdelt | Q37: 2026-10-24
A38: 37 | B38: 2026-10-24 | C38: 2026 | D38: Skeletal remains of animal found at Manalur excavation site in Tamil Nadu | E38: தொல்லியல் | F38: Archaeology / Excavation | G38: archaeology, excavation site, keeladi, tnsda | H38: Tamil Nadu | I38: aninews.in | J38: India | K38: English/Other | L38: https://www.aninews.in/news/national/general-news/skeletal-remains-of-animal-found-at-manalur-excavation-site-in-tamil-nadu20200605102614/ | N38: Madurai (Tamil Nadu) [India], June 5 (ANI): Skeletal remains of an animal have been unearthed at Manalur near Madurai under the sixth phase of excavations at Keeladi site, undertaken by the Tamil Nadu State Department of Archaeology (TNSDA). Tamil Nadu Chief Minister Edappadi K Palaniswami had start… | O38: full-text | P38: gdelt | Q38: 2026-10-24
... A42: 41 | B42: 2026-10-24 | C42: 2026 | D42: Tamil Nadu: MK Stalin visits Sivaganga archaeology site | E42: தொல்லியல் | F42: Archaeology / Excavation | G42: archaeology, archeology, keeladi | H42: Tamil Nadu | I42: aninews.in | J42: India | K42: English/Other | L42: https://aninews.in/news/national/general-news/tamil-nadu-mk-stalin-visits-sivaganga-archaeology-site20190927172127/ | N42: Sivaganga (Tamil Nadu) [India], Sept 27 (ANI): Opposition leader and Dravida Munnetra Kazhagam (DMK) president MK Stalin on Friday visited the Keeladi archaeology site as part of the fifth phase of excavation in Sivaganga in Tamil Nadu. The fifth phase of excavation started in June and likely to clo… | O42: full-text | P42: gdelt | Q42: 2026-10-24
A43: 42 | B43: 2026-10-23 | C43: 2026 | D43: Rare Simhavishnu-era hero stone sheds light on Pallava society, Tamil writing | E43: நடுகல் | F43: Hero stone / Memorial stone | G43: hero stone, hero-stone | I43: magzter.com | J43: Unknown | K43: English/Other | L43: https://www.magzter.com/stories/newspaper/The-New-Indian-Express-Chennai/RARE-SIMHAVISHNUERA-HERO-STONE-SHEDS-LIGHT-ON-PALLAVA-SOCIETY-TAMIL-WRITING | O43: title-only | P43: gnews | Q43: 2026-10-24
A44: 43 | B44: 2026-10-23 | C44: 2026 | D44: Rare Simhavishnu-era hero stone sheds light on Pallava society, Tamil writing | E44: கல்வெட்டு, நடுகல் | F44: Inscription / Epigraphy, Hero stone / Memorial stone | G44: inscription, inscriptions, inscribed, epigraphist, hero stone, hero stones, hero-stone | H44: Tamil Nadu | I44: newindianexpress.com | J44: India | K44: English/Other | L44: https://www.newindianexpress.com/amp/story/states/tamil-nadu/2026/Oct/23/rare-simhavishnu-era-hero-stone-sheds-light-on-pallava-society-tamil-writing | N44: Tamil Nadu Rare Simhavishnu-era hero stone sheds light on Pallava society, Tamil writing Written in Vattelutthu, the rare inscription naming the sixth-century ruler commemorates Keeranthai Maayan, who died during the conflict at Uthappi, and refers to the territorial division of Kovur Nadu. COIMBATO… | O44: full-text | P44: gnews | Q44: 2026-10-24
A45: 44 | B45: 2026-10-23 | C45: 2026 | D45: Rare Simhavishnu-era hero stone sheds light on Pallava society, Tamil writing | E45: கல்வெட்டு, நடுகல் | F45: Inscription / Epigraphy, Hero stone / Memorial stone | G45: inscription, inscriptions, inscribed, epigraphist, hero stone, hero stones, hero-stone | H45: Tamil Nadu | I45: newindianexpress.com | J45: India | K45: English/Other | L45: https://www.newindianexpress.com/states/tamil-nadu/2026/Oct/23/rare-simhavishnu-era-hero-stone-sheds-light-on-pallava-society-tamil-writing | N45: Tamil Nadu Rare Simhavishnu-era hero stone sheds light on Pallava society, Tamil writing Written in Vattelutthu, the rare inscription naming the sixth-century ruler commemorates Keeranthai Maayan, who died during the conflict at Uthappi, and refers to the territorial division of Kovur Nadu. COIMBATO… | O45: full-text | P45: gnews | Q45: 2026-10-25
A46: 45 | B46: 2026-10-23 | C46: 2026 | D46: Researchers decode two hero stones in Dharmapuri | E46: கல்வெட்டு, நடுகல் | F46: Inscription / Epigraphy, Hero stone / Memorial stone | G46: inscription, inscriptions, inscribed, epigraphist, vatteluttu, hero stone, hero stones, hero-stone | H46: Tamil Nadu | I46: thehindu.com | J46: India | K46: English/Other | L46: https://www.thehindu.com/news/cities/Coimbatore/researchers-decodes-two-hero-stones-in-dharmapuri/article71616552.ece/amp/ | N46: Two hero stones, dating to sixth century CE and 13th century CE, found in Dharmapuri have now been documented by the researchers of Coimbatore-based Yaakkai Trust. The hero stones and a stone inscription were documented during field surveys in Harur and Palacode by a three-member team of researchers… | O46: full-text | P46: gnews | Q46: 2026-10-24
A47: 46 | B47: 2026-10-23 | C47: 2026 | D47: Researchers decode two hero stones in Dharmapuri | E47: கல்வெட்டு, நடுகல் | F47: Inscription / Epigraphy, Hero stone / Memorial stone | G47: inscription, inscriptions, inscribed, epigraphist, vatteluttu, hero stone, hero stones, hero-stone | H47: Tamil Nadu | I47: thehindu.com | J47: India | K47: English/Other | L47: https://www.thehindu.com/news/cities/Coimbatore/researchers-decodes-two-hero-stones-in-dharmapuri/article71616552.ece | N47: Two hero stones, dating to sixth century CE and 13th century CE, found in Dharmapuri have now been documented by the researchers of Coimbatore-based Yaakkai Trust. The hero stones and a stone inscription were documented during field surveys in Harur and Palacode by a three-member team of researchers… | O47: full-text | P47: gnews | Q47: 2026-10-24
A48: 47 | B48: 2026-10-23 | C48: 2026 | D48: கண்டாச்சிபுரம் அருகே பாறை ஓவியங்கள் கண்டுபிடிப்பு | E48: பாறை ஓவியம் | F48: Rock art / Rock painting | G48: பாறை ஓவியங்கள் | H48: China | I48: dinamalar.com | J48: India | K48: Tamil | L48: https://www.dinamalar.com/news/tamil-nadu-district-news-viluppuram/kandachipuram-near-rock-paintings-discovered/4356018 | N48: உள்ளடக்கத்திற்கு செல்ல UPDATED : அக் 22, 2026 03:58 PM ADDED : அக் 22, 2026 03:55 PM விழுப்புரம்: கண்டாச்சிபுரம் அருகே 5 ஆயிரம் ஆண்டுகள் பழமையான பாறை ஓவியங்கள் கண்டுபிடிக்கப்பட்டுள்ளன. விழுப்புரம் மாவட்டம், கண்டாச்சிபுரம் அடுத்த அடுக்கம் கிராமத்தில் வேட்டவலத்தை சேர்ந்த ஆசிரியர் பாரதிராஜா, சீனுவாசன் … | O48: full-text | P48: gnews | Q48: 2026-10-23
A49: 48 | B49: 2026-10-23 | C49: 2026 | D49: பண்டைய தமிழகம் குறித்த புதிய தகவலை தரும் அரூா், பாலக்கோடு நடுகற்கள்: வரலாற்று ஆய்வாளா்கள் | E49: கல்வெட்டு, நடுகல் | F49: Inscription / Epigraphy, Hero stone / Memorial stone | G49: கல்வெட்டு, கல்வெட்டுகள், வட்டெழுத்து, நடுகல், நடுகற்கள் | H49: Tamil Nadu | I49: dinamani.com | J49: India | K49: Tamil | L49: https://www.dinamani.com/amp/story/all-editions/edition-dharmapuri/dharmapuri/2026/Oct/23/arur-palacode-midstones-provide-new-information-about-ancient-tamil-nadu-historians | N49: தருமபுரி பண்டைய தமிழகம் குறித்த புதிய தகவலை தரும் அரூா், பாலக்கோடு நடுகற்கள்: வரலாற்று ஆய்வாளா்கள் தருமபுரி மாவட்டம் அரூா், பாலக்கோடு பகுதிகளில் கண்டெடுக்கப்பட்ட நடுகற்கள் பொ.ஆ. 6 ஆம் நூற்றாண்டு, 1299-ஆம் ஆண்டை சோ்ந்தவை என்பதால் பண்டைய தமிழகத்தின் அரசியல், சமூக வரலாறு குறித்த புதிய தகவல்களை அளித்து… | O49: full-text | P49: gnews | Q49: 2026-10-23
A50: 49 | B50: 2026-10-22 | C50: 2026 | D50: 5000 ஆண்டுகள் பழமையான பாறை ஓவியங்கள் கண்டுபிடிப்பு | E50: பாறை ஓவியம் | F50: Rock art / Rock painting | G50: பாறை ஓவியங்கள் | I50: temple.dinamalar.com | J50: India | K50: Tamil | L50: https://temple.dinamalar.com/news_detail.php?id=147462 | N50: | | | | முதல் பக்கம் » இன்றைய செய்திகள் | | | 5000 ஆண்டுகள் பழமையான பாறை ஓவியங்கள் கண்டுபிடிப்பு பதிவு செய்த நாள் 26 அக் 2024 08:10 செஞ்சி; செஞ்சி அருகே 5000 ஆண்டுகள் பழமையான பாறை ஓவியங்களை ஆய்வாளர்கள் கண்டுபிடித்துள்ளனர். விழுப்புரம் மாவட்டம் செஞ்சி அடுத்த கப்பை கிராமத்தைச் சேர்ந்தவர் சரவணகுமார். இ… | O50: full-text | P50: gdelt | Q50: 2026-10-23
A51: 50 | B51: 2026-10-22 | C51: 2026 | D51: ASI to begin final phase of inscription recopying at Thanjavur Big Temple | E51: கல்வெட்டு, தொல்லியல் | F51: Inscription / Epigraphy, Archaeology / Excavation | G51: inscription, inscriptions, epigraphy, archaeological | H51: Tamil Nadu | I51: newindianexpress.com | J51: India | K51: English/Other | L51: https://www.newindianexpress.com/states/tamil-nadu/2026/Oct/22/asi-to-begin-final-phase-of-inscription-recopying-at-thanjavur-big-temple | N51: Tamil Nadu ASI to begin final phase of inscription recopying at Thanjavur Big Temple A team of more than 15 members will work for over two weeks to recopy Tamil and Marathi inscriptions found inside the temple. CHENNAI: The Archaeological Survey of India (ASI) will begin the final phase of recopying… | O51: full-text | P51: gnews | Q51: 2026-10-23
A52: 51 | B52: 2026-10-22 | C52: 2026 | D52: From sanskritisation to backwardation - The Economic Times | E52: கல்வெட்டு | F52: Inscription / Epigraphy | G52: inscriptions, copper plates | H52: Andhra / Telangana | I52: economictimes.indiatimes.com | J52: Unknown | K52: English/Other | L52: https://economictimes.indiatimes.com/opinion/et-commentary/from-sanskritisation-to-backwardation/articleshow/121683091.cms | N52: A century ago, many communities wanted to be recognised as Brahmins and Kshatriya. Today, the same groups want to be Other Backward Community (OBC). The old varna model (Brahmin, Kshatriya, Vaishya, Shudra, Ati-shudra or Pancham) is now replaced by a new categorisation (General, OBC, Scheduled Caste… | O52: full-text | P52: gdelt | Q52: 2026-10-22
A53: 52 | B53: 2026-10-22 | C53: 2026 | D53: PM Modi releases commemorative coin of Rajendra Chola I in TN's Gangaikonda Cholapuram | E53: கல்வெட்டு, தொல்லியல் | F53: Inscription / Epigraphy, Archaeology / Excavation | G53: copper plates, archaeological | H53: Tamil Nadu | I53: ianslive.in | J53: India | K53: English/Other | L53: https://ianslive.in/pm-modi-honours-rajendra-chola-i-at-gangaikonda-cholapuram-releases-commemorative-coin--20250727151628 | N53: Chennai, July 27 (IANS) Prime Minister Narendra Modi on Sunday participated in the valedictory celebrations of the Aadi Thiruvathirai festival, marking the birth anniversary of the illustrious Chola emperor, Rajendra Chola I, at the historic Gangaikonda Cholapuram in Tamil Nadu's Ariyalur district. … | O53: full-text | P53: gdelt | Q53: 2026-10-22
A54: 53 | B54: 2026-10-22 | C54: 2026 | D54: Rediscover the Prehistoric Legacy: Solo Art Exhibition Brings Satpura Rock Paintings to Life | E54: பாறை ஓவியம் | F54: Rock art / Rock painting | G54: rock art, rock paintings, rock-art | H54: Tamil Nadu | I54: news.webindia123.com | J54: Unknown | K54: English/Other | L54: https://news.webindia123.com/news/Articles/Business/20250315/4297160.html | N54: Thursday, October 22, 2026 News | | | Rediscover the Prehistoric Legacy: Solo Art Exhibition Brings Satpura Rock Paintings to Life \| March 15, 2025 11:43:01 AM IST | | VMPL Chennai (Tamil Nadu) [India], March 15: Witness the echoes of human history unfold at the much-anticipated solo art exhibition… | O54: full-text | P54: gdelt | Q54: 2026-10-22
A55: 54 | B55: 2026-10-22 | C55: 2026 | D55: Rediscover the Prehistoric Legacy: Solo Art Exhibition Brings Satpura Rock Paintings to Life | E55: பாறை ஓவியம் | F55: Rock art / Rock painting | G55: rock art, rock paintings, rock-art | H55: Tamil Nadu | I55: aninews.in | J55: India | K55: English/Other | L55: https://aninews.in/news/business/rediscover-the-prehistoric-legacy-solo-art-exhibition-brings-satpura-rock-paintings-to-life20250315112842/ | N55: VMPL Chennai (Tamil Nadu) [India], March 15: Witness the echoes of human history unfold at the much-anticipated solo art exhibition, "Reverberations of the Past," curated by Ruchi Atreya. This unique showcase will take place at the prestigious Lalit Kala Akademi Gallery, Chennai, from 18th March to … | O55: full-text | P55: gdelt | Q55: 2026-10-22
A56: 55 | B56: 2026-10-22 | C56: 2026 | D56: ஆதிச்சநல்லுார் அகழாய்வு இடத்தில் நிரந்தர கொட்டகை அமைக்க முடிவு | E56: தொல்லியல் | F56: Archaeology / Excavation | G56: தொல்லியல், தொல்லியல் துறை, அகழாய்வு, தொல்பொருட்கள், ஈமத்தாழி | I56: dinamalar.com | J56: India | K56: Tamil | L56: https://www.dinamalar.com/news/tamil-nadu-news/decision-to-set-up-permanent-shed-at-adichanallur-excavation-site/4356282 | N56: ஆதிச்சநல்லுார் அகழாய்வு இடத்தில் நிரந்தர கொட்டகை அமைக்க முடிவு ADDED : அக் 22, 2026 06:36 PM – நமது நிருபர் – துாத்துக்குடி மாவட்டம் ஆதிச்சநல்லுாரில், அகழாய்வு இடங்களை பாதுகாக்கும் வகையில், நிரந்தர கொட்டகை அமைக்க, மத்திய தொல்லியல் துறை முடிவு செய்துள்ளது. துாத்துக்குடி மாவட்டம், தாமிரபரணி ஆற்றங்கரைய… | O56: full-text | P56: gnews | Q56: 2026-10-23
A57: 56 | B57: 2026-10-22 | C57: 2026 | D57: தொற்றுநோய், அனர்த்தத்தினால் உயிரிழந்தவர்களாக இருக்கலாம் ; செம்மணி தொடர்பில் தொல்லியல் பேராசிரியர் ராஜ் சோமதேவவின் அறிக்கை கூறுக | E57: தொல்லியல் | F57: Archaeology / Excavation | G57: தொல்லியல் | I57: virakesari.lk | J57: Sri Lanka | K57: Tamil | L57: https://www.virakesari.lk/article/264183 | O57: title-only | P57: gnews | Q57: 2026-10-23
A58: 57 | B58: 2026-10-21 | C58: 2026 | D58: 11ம் நுாற்றாண்டு நடுகல் சிற்பம் காஞ்சிபுரத்தில் கண்டெடுப்பு | E58: நடுகல் | F58: Hero stone / Memorial stone | G58: நடுகல் | H58: China | I58: dinamalar.com | J58: India | K58: Tamil | L58: https://www.dinamalar.com/news/tamil-nadu-district-news-kancheepuram/11th-century-medieval-sculpture-discovered-in-kanchipuram/4354622 | N58: உள்ளடக்கத்திற்கு செல்ல 11ம் நுாற்றாண்டு நடுகல் சிற்பம் காஞ்சிபுரத்தில் கண்டெடுப்பு ADDED : அக் 20, 2026 08:16 PM அக்.20 / பி.சீனிவாசன் / காஞ்சிபுரம் / 9087585110 / 2226 / 2:12 மணி. காஞ்சிபுரம்: காஞ்சிபுரம் தும்பவனத்தம்மன் கோவிலில், 11ம் நுாற்றாண்டை சேர்ந்த நடுகல் சிற்பம் கண்டெடுக்கப்பட்டுள்ளது. காஞ்… | O58: full-text | P58: gnews | Q58: 2026-10-21
A59: 58 | B59: 2026-10-21 | C59: 2026 | D59: Congress Manickam Tagore moves adjournment motion in LS for cancellation of Madurai Tungsten mining project | E59: கல்வெட்டு | F59: Inscription / Epigraphy | G59: inscriptions, vatteluttu | H59: Tamil Nadu | I59: news.webindia123.com | J59: Unknown | K59: English/Other | L59: https://news.webindia123.com/news/Articles/India/20241212/4265343.html | N59: Wednesday, October 21, 2026 News | | | Congress' Manickam Tagore moves adjournment motion in LS for cancellation of Madurai Tungsten mining project New Delhi \| December 12, 2024 11:42:13 AM IST | | Congress MP Manickam Tagore on Thursday moved an adjournment motion notice in the Lok Sabha seeking t… | O59: full-text | P59: gdelt | Q59: 2026-10-21
A60: 59 | B60: 2026-10-21 | C60: 2026 | D60: Congress' Manickam Tagore moves adjournment motion in LS for cancellation of Madurai Tungsten mining project | E60: கல்வெட்டு | F60: Inscription / Epigraphy | G60: inscriptions, vatteluttu | H60: Tamil Nadu | I60: aninews.in | J60: India | K60: English/Other | L60: https://aninews.in/news/national/politics/congress-manickam-tagore-moves-adjournment-motion-in-ls-for-cancellation-of-madurai-tungsten-mining-project20241212110951/ | N60: New Delhi [India], December 12 (ANI): Congress MP Manickam Tagore on Thursday moved an adjournment motion notice in the Lok Sabha seeking to discuss the cancellation of the Tungsten mining project in Tamil Nadu's Madurai. Congress MP Tagore stated that the proposed mining project presents a serious … | O60: full-text | P60: gdelt | Q60: 2026-10-21
A61: 60 | B61: 2026-10-21 | C61: 2026 | D61: How Brahmins helped create temple-states and kingdoms in South India and Southeast Asia | E61: கல்வெட்டு | F61: Inscription / Epigraphy | G61: copper plates | H61: Tamil Nadu, Thailand, Indonesia, Vietnam, Myanmar, Cambodia | I61: bangaloremirror.indiatimes.com | J61: Unknown | K61: English/Other | L61: https://bangaloremirror.indiatimes.com/opinion/columns-views-pet-puja-queer-issues-dialogue-gardening-greenskeeper-opinions/kings-brahmins/articleshow/64524148.cms | N61: How Brahmins helped create temple-states and kingdoms in South India and Southeast Asia It is fashionable nowadays to use the word ‘Brahmin ’ with contempt, inversing the contempt of many Indian elites for lower castes. It mirrors the contempt for all things ‘white’ seen in the intellectual West. On… | O61: full-text | P61: gdelt | Q61: 2026-10-21
A62: 61 | B62: 2026-10-21 | C62: 2026 | D62: Tungsten Mining Project: Madurai farmers opposes proposal, to meet Union Minister in Delhi today | E62: கல்வெட்டு | F62: Inscription / Epigraphy | G62: inscriptions, vatteluttu | H62: Tamil Nadu | I62: news.webindia123.com | J62: Unknown | K62: English/Other | L62: https://news.webindia123.com/news/Articles/India/20250122/4279120.html | N62: Wednesday, October 21, 2026 News | | | Tungsten Mining Project: Madurai farmers opposes proposal, to meet Union Minister in Delhi today New Delhi \| January 22, 2025 10:12:27 AM IST | | The Central Government proposed establishing a tungsten mine in Nayakkarpatty, Madurai, but the plan has faced sig… | O62: full-text | P62: gdelt | Q62: 2026-10-21
A63: 62 | B63: 2026-10-21 | C63: 2026 | D63: Tungsten Mining Project: Madurai farmers opposes proposal, to meet Union Minister in Delhi today | E63: கல்வெட்டு | F63: Inscription / Epigraphy | G63: inscriptions, vatteluttu | H63: Tamil Nadu | I63: aninews.in | J63: India | K63: English/Other | L63: https://aninews.in/news/national/general-news/tungsten-mining-project-madurai-farmers-opposes-proposal-to-meet-union-minister-in-delhi-today20250122100249/ | N63: New Delhi [India], January 22 (ANI): The Central Government proposed establishing a tungsten mine in Nayakkarpatty, Madurai, but the plan has faced significant opposition due to the area's status as a biodiversity hotspot. A group of 10 individuals, including farmers from Arittapatti and Vellalapatt… | O63: full-text | P63: gdelt | Q63: 2026-10-21
A64: 63 | B64: 2026-10-21 | C64: 2026 | D64: காஞ்சிபுரம் கோவிலில் 11-ம் நூற்றாண்டு வீரக்கல் சிற்பம் கண்டுபிடிப்பு! | E64: கல்வெட்டு, நடுகல் | F64: Inscription / Epigraphy, Hero stone / Memorial stone | G64: கல்வெட்டு, வீரக்கல் | I64: dailythanthi.com | J64: India | K64: Tamil | L64: https://www.dailythanthi.com/amp/story/news/tamilnadu/11th-century-veerakkal-sculpture-discovered-in-kanchipuram-temple | N64: தமிழக செய்திகள் காஞ்சிபுரம் கோவிலில் 11-ம் நூற்றாண்டு வீரக்கல் சிற்பம் கண்டுபிடிப்பு! போர்வீரர் கம்பீரமான தோற்றத்துடன் இடதுபுறம் திரும்பி நிற்பதுபோல் வடிவமைக்கப்பட்டுள்ளார். காஞ்சிபுரம், காஞ்சிபுரம் தும்பவனத்தம்மன் கோவிலில் வாள், கேடயத்துடன் போர்வீரர் காட்சியளிக்கும் பழமையான சிற்பம் கண்டுபிடிக்கப்பட… | O64: full-text | P64: gnews | Q64: 2026-10-22
A65: 64 | B65: 2026-10-21 | C65: 2026 | D65: காஞ்சிபுரம் கோவிலில் 11-ம் நூற்றாண்டு வீரக்கல் சிற்பம் கண்டுபிடிப்பு! | E65: கல்வெட்டு, நடுகல் | F65: Inscription / Epigraphy, Hero stone / Memorial stone | G65: கல்வெட்டு, வீரக்கல் | I65: dailythanthi.com | J65: India | K65: Tamil | L65: https://www.dailythanthi.com/news/tamilnadu/11th-century-veerakkal-sculpture-discovered-in-kanchipuram-temple | N65: தமிழக செய்திகள் காஞ்சிபுரம் கோவிலில் 11-ம் நூற்றாண்டு வீரக்கல் சிற்பம் கண்டுபிடிப்பு! போர்வீரர் கம்பீரமான தோற்றத்துடன் இடதுபுறம் திரும்பி நிற்பதுபோல் வடிவமைக்கப்பட்டுள்ளார். காஞ்சிபுரம், காஞ்சிபுரம் தும்பவனத்தம்மன் கோவிலில் வாள், கேடயத்துடன் போர்வீரர் காட்சியளிக்கும் பழமையான சிற்பம் கண்டுபிடிக்கப்பட… | O65: full-text | P65: gnews | Q65: 2026-10-27
A66: 65 | B66: 2026-10-21 | C66: 2026 | D66: கீழடி அகழாய்வு குழிகள் மூடல் | E66: தொல்லியல் | F66: Archaeology / Excavation | G66: தொல்லியல், தொல்லியல் துறை, அகழாய்வு, கீழடி | I66: dinamalar.com | J66: India | K66: Tamil | L66: https://www.dinamalar.com/news/tamil-nadu-district-news-sivagangai/closure-of-keezhadi-dredging-pits/4354328 | N66: உள்ளடக்கத்திற்கு செல்ல UPDATED : அக் 20, 2026 05:16 PM ADDED : அக் 20, 2026 05:14 PM கீழடி: கீழடி 11ம் கட்ட அகழாய்வில் இதுவரை கண்டெடுக்கப்பட்ட பொருட்களை ஆவணப்படுத்தும் பணி தொடங்கியுள்ளது. ஆய்வு பணிகள் தொடர்ந்து நடந்து வரும் நிலையில் மாலை நேரங்களில் மழை பெய்வதால் அகழாய்வு குழிகள் தார்ப்பாய் போட்டு மூ… | O66: full-text | P66: gnews | Q66: 2026-10-21
A67: 66 | B67: 2026-10-21 | C67: 2026 | D67: தருமபுரியில் நடுகல் கல்வெட்டுகள் கண்டெடுப்பு – வரலாற்று முக்கியத்துவம் என்ன? | E67: கல்வெட்டு, நடுகல், தொல்லியல் | F67: Inscription / Epigraphy, Hero stone / Memorial stone, Archaeology / Excavation | G67: கல்வெட்டு, கல்வெட்டுகள், கல்வெட்டுக்கள், வட்டெழுத்து, நடுகல், தொல்லியல் | I67: vikatan.com | J67: India | K67: Tamil | L67: https://www.vikatan.com/amp/story/science%2Fhistory%2Fnew-memorial-stone-inscriptions-discovered-in-dharmapuri | N67: "வீரவிஸ்வநாதன் காலத்திய கல்வெட்டுகள் வெகு அரிதாகவே தமிழ்நாட்டில் கிடைத்துள்ள சூழலில், தற்போது கிடைத்துள்ள இந்த நடுகல் கல்வெட்டு தமிழ்நாட்டின் அரசியல் வரலாற்று எழுதியலுக்கு மிக முக்கியமான ஆவணமாகும்" Published: 21st Oct, 2026 at 14:41 PM Updated: 12 hours ago நடுகல் கல்வெட்டு கோவையை தலைமையிடமாக கொண்டு… | O67: full-text | P67: gnews | Q67: 2026-10-22
A68: 67 | B68: 2026-10-21 | C68: 2026 | D68: தருமபுரியில் நடுகல் கல்வெட்டுகள் கண்டெடுப்பு – வரலாற்று முக்கியத்துவம் என்ன? | E68: கல்வெட்டு, நடுகல், தொல்லியல் | F68: Inscription / Epigraphy, Hero stone / Memorial stone, Archaeology / Excavation | G68: கல்வெட்டு, கல்வெட்டுகள், கல்வெட்டுக்கள், வட்டெழுத்து, நடுகல், தொல்லியல் | I68: vikatan.com | J68: India | K68: Tamil | L68: https://www.vikatan.com/science/history/new-memorial-stone-inscriptions-discovered-in-dharmapuri | N68: Open App தருமபுரியில் நடுகல் கல்வெட்டுகள் கண்டெடுப்பு – வரலாற்று முக்கியத்துவம் என்ன? "வீரவிஸ்வநாதன் காலத்திய கல்வெட்டுகள் வெகு அரிதாகவே தமிழ்நாட்டில் கிடைத்துள்ள சூழலில், தற்போது கிடைத்துள்ள இந்த நடுகல் கல்வெட்டு தமிழ்நாட்டின் அரசியல் வரலாற்று எழுதியலுக்கு மிக முக்கியமான ஆவணமாகும்" கோவையை தலைமையிடம… | O68: full-text | P68: gnews | Q68: 2026-10-22
A69: 68 | B69: 2026-10-20 | C69: 2026 | D69: 1,500 ஆண்டுகளுக்கு முந்தைய விநாயகி சிற்பம் கண்டுபிடிப்பு | E69: கல்வெட்டு, தொல்லியல் | F69: Inscription / Epigraphy, Archaeology / Excavation | G69: கல்வெட்டு, கல்வெட்டுகள், கல்வெட்டு ஆய்வாளர், தொல்லியல், தொல்லியல் துறை | H69: Tamil Nadu | I69: temple.dinamalar.com | J69: India | K69: Tamil | L69: https://temple.dinamalar.com/news_detail.php?id=119567 | N69: | | | | முதல் பக்கம் » இன்றைய செய்திகள் | | | 1,500 ஆண்டுகளுக்கு முந்தைய விநாயகி சிற்பம் கண்டுபிடிப்பு பதிவு செய்த நாள் 21 டிச 2021 11:12 சென்னை : செங்கல்பட்டு மாவட்டம்,மதுராந்தகம் ஒன்றியம் இரும்பேட்டில், ஐந்தாம் நூற்றாண்டைச் சேர்ந்த கல்வெட்டுடன் கூடிய விநாயகி உள்ளிட்ட சிற்பங்கள் கண்டுபிடிக்கப்பட்டு… | O69: full-text | P69: gdelt | Q69: 2026-10-20
A70: 69 | B70: 2026-10-20 | C70: 2026 | D70: 489 ஆண்டுக்கு முற்பட்ட கல்வெட்டு, சிலை கண்டுபிடிப்பு | E70: கல்வெட்டு, நடுகல் | F70: Inscription / Epigraphy, Hero stone / Memorial stone | G70: கல்வெட்டு, நடுகல் | I70: temple.dinamalar.com | J70: India | K70: Tamil | L70: https://temple.dinamalar.com/news_detail.php?id=110285 | N70: | | | | முதல் பக்கம் » இன்றைய செய்திகள் | | | 489 ஆண்டுக்கு முற்பட்ட கல்வெட்டு, சிலை கண்டுபிடிப்பு பதிவு செய்த நாள் 02 ஜன 2021 10:01 தம்மம்பட்டி: உலிபுரத்தில், 489 ஆண்டுகளுக்கு முற்பட்ட கல்வெட்டு, நவகண்ட சிலைகள் கண்டுபிடிக்கப்பட்டுள்ளன. சேலம் மாவட்டம், ஆத்தூர் அடுத்த, தம்மம்பட்டி அருகே, உலிபுரத்தில்… | O70: full-text | P70: gdelt | Q70: 2026-10-20
A71: 70 | B71: 2026-10-20 | C71: 2026 | D71: 7ம் நுாற்றாண்டை சார்ந்த விநாயகர் புடைப்பு சிற்பம் கண்டுபிடுப்பு | E71: கல்வெட்டு | F71: Inscription / Epigraphy | G71: கல்வெட்டு | I71: temple.dinamalar.com | J71: India | K71: Tamil | L71: https://temple.dinamalar.com/news_detail.php?id=148904 | N71: | | | | முதல் பக்கம் » இன்றைய செய்திகள் | | | 7ம் நுாற்றாண்டை சார்ந்த விநாயகர் புடைப்பு சிற்பம் கண்டுபிடுப்பு பதிவு செய்த நாள் 31 டிச 2024 11:12 விழுப்புரம் மாவட்டத்தில், பல்லவர் கால எழுத்துப் பொறிப்புடன் கூடிய விநாயகர் புடைப்புச் சிற்பம் கண்டுபிடிக்கப்பட்டுள்ளது. விழுப்புரம் மாவட்டம், திண்டிவனம் அர… | O71: full-text | P71: gdelt | Q71: 2026-10-20
A72: 71 | B72: 2026-10-20 | C72: 2026 | D72: PM Modi gifts PM Lee a replica of Buddhagupta Stele | E72: கல்வெட்டு | F72: Inscription / Epigraphy | G72: inscription | H72: Malaysia, Indonesia | I72: aninews.in | J72: India | K72: English/Other | L72: https://www.aninews.in/news/world/asia/pm-modi-gifts-pm-lee-a-replica-of-buddhagupta-stele201806011515200001/ | N72: Singapore City [Singapore], June 1 (ANI): Prime Minister Narendra Modi gifted Singapore Prime Minister Lee Hsien Loong a replica of 6th century CE Buddhagupta Stele, as per sources. It bears Sanskrit phrases in Pallava script and serves as an important evidence of the transmission of Buddhism from I… | O72: full-text | P72: gdelt | Q72: 2026-10-20
A73: 72 | B73: 2026-10-20 | C73: 2026 | D73: PM Modi gifts PM Lee a replica of Buddhagupta Stele | E73: கல்வெட்டு | F73: Inscription / Epigraphy | G73: inscription | H73: Malaysia, Indonesia | I73: aninews.in | J73: India | K73: English/Other | L73: https://www.aninews.in/news/pm-modi-gifts-pm-lee-a-replica-of-buddhagupta-stele201806011515200001/ | N73: Singapore City [Singapore], June 1 (ANI): Prime Minister Narendra Modi gifted Singapore Prime Minister Lee Hsien Loong a replica of 6th century CE Buddhagupta Stele, as per sources. It bears Sanskrit phrases in Pallava script and serves as an important evidence of the transmission of Buddhism from I… | O73: full-text | P73: gdelt | Q73: 2026-10-20
A74: 73 | B74: 2026-10-20 | C74: 2026 | D74: அழியும் நிலையில் பல்லவர் வரலாற்று சின்னங்கள் | E74: கல்வெட்டு, தொல்லியல் | F74: Inscription / Epigraphy, Archaeology / Excavation | G74: கல்வெட்டு, தொல்லியல், தொல்லியல் துறை, கற்படுக்கை | I74: temple.dinamalar.com | J74: India | K74: Tamil | L74: https://temple.dinamalar.com/news_detail.php?id=75467 | N74: | | | | முதல் பக்கம் » இன்றைய செய்திகள் | | | அழியும் நிலையில் பல்லவர் வரலாற்று சின்னங்கள் பதிவு செய்த நாள் 04 ஜன 2018 12:01 மதுராந்தகம் : பல்லவர் கால, 1,300 ஆண்டுகளுக்கு முற்பட்ட வரலாற்று சின்னங்களை காப்பாற்ற வேண்டும் என, தொல்லியல் ஆர்வலர்கள் கோரிக்கை விடுத்துள்ளனர். மதுராந்தகம் தாலுகா விராலுார் ஊர… | O74: full-text | P74: gdelt | Q74: 2026-10-20
A75: 74 | B75: 2026-10-20 | C75: 2026 | D75: பல்லவர் கால கொற்றவை சிற்பம் செங்கல்பட்டு அருகே கண்டெடுப்பு | E75: கல்வெட்டு, தொல்லியல் | F75: Inscription / Epigraphy, Archaeology / Excavation | G75: கல்வெட்டு, கல்வெட்டு ஆய்வாளர், தொல்லியல், தொல்லியல் துறை | H75: Tamil Nadu | I75: temple.dinamalar.com | J75: India | K75: Tamil | L75: https://temple.dinamalar.com/news_detail.php?id=143931 | N75: | | | | முதல் பக்கம் » இன்றைய செய்திகள் | | | பல்லவர் கால கொற்றவை சிற்பம் செங்கல்பட்டு அருகே கண்டெடுப்பு பதிவு செய்த நாள் 28 மே 2024 11:05 சென்னை : செங்கல்பட்டு மாவட்டம், சாத்தமங்கலம் கிராமத்தில், பல்லவர் காலத்தைச் சேர்ந்த கொற்றவை சிற்பம் கண்டெடுக்கப்பட்டுள்ளது. செங்கல்பட்டு மாவட்டம், ஈசூர் அருகில் … | O75: full-text | P75: gdelt | Q75: 2026-10-20
A76: 75 | B76: 2026-10-20 | C76: 2026 | D76: மலைக்க வைக்கும் குடைவரை கோவில்கள் | E76: கல்வெட்டு, தொல்லியல் | F76: Inscription / Epigraphy, Archaeology / Excavation | G76: கல்வெட்டு, கல்வெட்டுகள், தொல்லியல், தொல்லியல் துறை | I76: temple.dinamalar.com | J76: India | K76: Tamil | L76: https://temple.dinamalar.com/news_detail.php?id=68458 | N76: | | | | முதல் பக்கம் » இன்றைய செய்திகள் | | | மலைக்க வைக்கும் குடைவரை கோவில்கள் பதிவு செய்த நாள் 23 மே 2017 12:05 திருவள்ளூர் மாவட்டம், ஆர்.கே.பேட்டையில் இருந்து, 30 கி.மீ., துாரத்தில் கண்ணமங்கலம் சாலையில் அமைந்துள்ளது பஞ்ச பாண்டவர் மலை. இந்த மலை மீது உள்ள வற்றாத சுனையும், சுனையை சுற்றிலும் புடைப்பு… | O76: full-text | P76: gdelt | Q76: 2026-10-20
A77: 76 | B77: 2026-10-19 | C77: 2026 | D77: 1000 ஆண்டுகள் பழமை வாய்ந்த சுப்ரமணியர் கோவில் கும்பாபிஷேகம் | E77: கல்வெட்டு | F77: Inscription / Epigraphy | G77: கல்வெட்டு | I77: temple.dinamalar.com | J77: India | K77: Tamil | L77: https://temple.dinamalar.com/news_detail.php?id=102419 | N77: | | | | முதல் பக்கம் » இன்றைய செய்திகள் | | | 1000 ஆண்டுகள் பழமை வாய்ந்த சுப்ரமணியர் கோவில் கும்பாபிஷேகம் பதிவு செய்த நாள் 31 ஜன 2020 12:01 பொள்ளாச்சி: பொள்ளாச்சியில் ஆயிரம் ஆண்டுகள் பழமை வாய்ந்த சுப்ரமணிய சுவாமி கோவில் கும்பாபிஷேக விழா, நேற்று நடந்தது. பொள்ளாச்சியில் பழமை வாய்ந்த சுப்ரமணிய சுவாமி க… | O77: full-text | P77: gdelt | Q77: 2026-10-19
A78: 77 | B78: 2026-10-19 | C78: 2026 | D78: 13ம் நுாற்றாண்டை சேர்ந்த நிலக்கொடை கல்வெட்டு கண்டுபிப்பு | E78: கல்வெட்டு, தொல்லியல் | F78: Inscription / Epigraphy, Archaeology / Excavation | G78: கல்வெட்டு, தொல்லியல் | I78: temple.dinamalar.com | J78: India | K78: Tamil | L78: https://temple.dinamalar.com/news_detail.php?id=118911 | N78: | | | | முதல் பக்கம் » இன்றைய செய்திகள் | | | 13ம் நுாற்றாண்டை சேர்ந்த நிலக்கொடை கல்வெட்டு கண்டுபிப்பு பதிவு செய்த நாள் 24 நவ 2021 01:11 பெருங்குடி : மதுரை பெருங்குடி கண்மாய் கரையில் 13ம் நுாற்றாண்டை சேர்ந்த நிலக்கொடை கல்வெட்டு கண்டுபிடிக்கப்பட்டது. அதில் விக்கிரம பாண்டியன் பேரரையான் என்ற சிற்றரசர் … | O78: full-text | P78: gdelt | Q78: 2026-10-19
A79: 78 | B79: 2026-10-19 | C79: 2026 | D79: 13ம் நூற்றாண்டு கல்வெட்டு சிவகங்கையில் கண்டுபிடிப்பு | E79: கல்வெட்டு, தொல்லியல் | F79: Inscription / Epigraphy, Archaeology / Excavation | G79: கல்வெட்டு, கல்வெட்டுகள், கல்வெட்டுக்கள், தொல்லியல் | I79: temple.dinamalar.com | J79: India | K79: Tamil | L79: https://temple.dinamalar.com/news_detail.php?id=73442 | N79: | | | | முதல் பக்கம் » இன்றைய செய்திகள் | | | 13ம் நூற்றாண்டு கல்வெட்டு சிவகங்கையில் கண்டுபிடிப்பு பதிவு செய்த நாள் 06 நவ 2017 11:11 சிவகங்கை: சிவகங்கையில் பிற்கால பாண்டிய மன்னர் காலத்து 13 ம் நுாற்றாண்டைச் சேர்ந்த இரண்டு கல்வெட்டுக்கள் கண்டறியப்பட்டன. சிவகங்கை ராமகிருஷ்ணா நடுநிலைப்பள்ளி அருகே அறநில… | O79: full-text | P79: gdelt | Q79: 2026-10-19
A80: 79 | B80: 2026-10-19 | C80: 2026 | D80: 13ம் நூற்றாண்டைச் சேர்ந்த கல்வெட்டு கண்டுபிடிப்பு | E80: கல்வெட்டு, தொல்லியல் | F80: Inscription / Epigraphy, Archaeology / Excavation | G80: கல்வெட்டு, கல்வெட்டுகள், தொல்லியல் | H80: Puducherry | I80: temple.dinamalar.com | J80: India | K80: Tamil | L80: https://temple.dinamalar.com/news_detail.php?id=118042 | N80: | | | | முதல் பக்கம் » இன்றைய செய்திகள் | | | 13ம் நூற்றாண்டைச் சேர்ந்த கல்வெட்டு கண்டுபிடிப்பு பதிவு செய்த நாள் 25 அக் 2021 01:10 ராஜபாளையம்: ராஜபாளையம் அருகே சோழபுரம் கிராமத்தில் 13ஆம் நூற்றாண்டைச் சேர்ந்த பாண்டியர் கால தமிழ் கல்வெட்டு கண்டுபிடிக்கப்பட்டுள்ளது. விருதுநகர் மாவட்டம் ராஜபாளையத்தில் இ… | O80: full-text | P80: gdelt | Q80: 2026-10-19
A81: 80 | B81: 2026-10-19 | C81: 2026 | D81: 500 ஆண்டு முந்தைய ஆதிசிவன் கோயில்: கருநாகம் வந்ததால் பூஜை | E81: கல்வெட்டு | F81: Inscription / Epigraphy | G81: கல்வெட்டு, கல்வெட்டுகள் | I81: temple.dinamalar.com | J81: India | K81: Tamil | L81: https://temple.dinamalar.com/news_detail.php?id=105544 | N81: | | | | முதல் பக்கம் » இன்றைய செய்திகள் | | | 500 ஆண்டு முந்தைய ஆதிசிவன் கோயில்: கருநாகம் வந்ததால் பூஜை பதிவு செய்த நாள் 13 ஜூன் 2020 10:06 காரியாபட்டி: காரியாபட்டி கணக்கனேந்தலில் ஆதிசிவன் கோயில் இருந்தது தற்போதைய தலைமையினருக்கு தெரியாது. இங்கு கருநாகம் நடமாட்டம் இருந்துள்ள நிலையில் இதனால் யாருக்கும… | O81: full-text | P81: gdelt | Q81: 2026-10-19
A82: 81 | B82: 2026-10-19 | C82: 2026 | D82: 500 ஆண்டுகளுக்கு முந்தைய கல்வெட்டு கண்டுபிடிப்பு | E82: கல்வெட்டு | F82: Inscription / Epigraphy | G82: கல்வெட்டு | I82: temple.dinamalar.com | J82: India | K82: Tamil | L82: https://temple.dinamalar.com/news_detail.php?id=130957 | N82: | | | | முதல் பக்கம் » இன்றைய செய்திகள் | | | 500 ஆண்டுகளுக்கு முந்தைய கல்வெட்டு கண்டுபிடிப்பு பதிவு செய்த நாள் 22 டிச 2022 10:12 அருப்புக்கோட்டை" அருப்புக்கோட்டை அருகே 500 ஆண்டுகளுக்கு முந்தைய விஜய நகர மன்னர் காலத்திய கல்வெட்டு கண்டுபிடிக்கப்பட்டுள்ளது. அருப்புக்கோட்டை திருச்சுழி அருகே நரிக்குடி வே… | O82: full-text | P82: gdelt | Q82: 2026-10-19
A83: 82 | B83: 2026-10-19 | C83: 2026 | D83: 900-yr-old inscription found in Mangaluru temple | E83: கல்வெட்டு | F83: Inscription / Epigraphy | G83: inscription | H83: Karnataka | I83: bangaloremirror.indiatimes.com | J83: Unknown | K83: English/Other | L83: https://bangaloremirror.indiatimes.com/news/state/900-yr-old-inscription-found-in-mangaluru-temple/articleshow/60755205.cms | N83: 900-yr-old inscription found in Mangaluru temple Historians say the discovery refers to Alupa ruler Kulashekara and his liegeman A 900-year-old inscription was discovered at Polali Rajarajeshwari temple located on the outskirts of Mangaluru . It was found during the ongoing renovation works of the t… | O83: full-text | P83: gdelt | Q83: 2026-10-19
A84: 83 | B84: 2026-10-19 | C84: 2026 | D84: ASI, Bhubaneswar Circle releases list of monuments, sites which will reopen from July 6 | E84: கல்வெட்டு, தொல்லியல் | F84: Inscription / Epigraphy, Archaeology / Excavation | G84: inscription, archaeological | I84: aninews.in | J84: India | K84: English/Other | L84: https://www.aninews.in/news/national/general-news/asi-bhubaneswar-circle-releases-list-of-monuments-sites-which-will-reopen-from-july-620200704223659/ | N84: Bhubaneswar (Odisha) [India], July 4 (ANI): The Archaeological Survey of India (ASI), Bhubaneswar Circle on Saturday released a list of monuments, sites, and museums that will open from July 6 in the state. According to the release, a total of 31 monuments, sites, and museums that fall under ASI, Bh… | O84: full-text | P84: gdelt | Q84: 2026-10-19
A85: 84 | B85: 2026-10-19 | C85: 2026 | D85: BM Trippin’ Tales: Have a date with history, so close to Bengaluru | E85: கல்வெட்டு | F85: Inscription / Epigraphy | G85: inscription, inscriptions | I85: bangaloremirror.indiatimes.com | J85: Unknown | K85: English/Other | L85: https://bangaloremirror.indiatimes.com/bangalore/others/bm-trippin-tales-have-a-date-with-history-so-close-to-bengaluru/articleshow/107240573.cms | N85: BM Trippin’ Tales: Have a date with history, so close to Bengaluru Avani has historical significance dating back to 339 AD We explore various locations drawn by the intriguing stories associated with them. Places with mythological connections pique our interest, and one such destination is Avani in … | O85: full-text | P85: gdelt | Q85: 2026-10-19
A86: 85 | B86: 2026-10-19 | C86: 2026 | D86: Indian Express invokes UNESCO inscription to secularise Garba, vilify Hindu groups for Muslim ban | E86: கல்வெட்டு | F86: Inscription / Epigraphy | G86: inscription | H86: Tamil Nadu, Kerala | I86: opindia.com | J86: Unknown | K86: English/Other | L86: https://www.opindia.com/2026/10/the-indian-express-2023-unesco-inscription-secularise-garba-vilify-hindu-groups-muslims/ | N86: Islamo-leftists have a penchant for vilifying and sermonising Hindus about their religious beliefs and festivals. Diwali is reserved for guilt-tripping Hindus for bursting firecrackers, Holi for an agenda on ‘consent’ and animal rights, and similar narratives accompany festivals like Raksha Bandhan,… | O86: full-text | P86: gnews | Q86: 2026-10-20
A87: 86 | B87: 2026-10-19 | C87: 2026 | D87: Pre-Colonial History of Indonesia | E87: கல்வெட்டு, தொல்லியல் | F87: Inscription / Epigraphy, Archaeology / Excavation | G87: inscription, inscriptions, archaeological | H87: Indonesia, China | I87: indonesia-investments.com | J87: Unknown | K87: English/Other | L87: https://www.indonesia-investments.com/culture/politics/precolonial-history/item123 | N87: - 19 October 2026 (closed) - Jakarta Composite Index (4,996.61) -188.49 -3.64% - GDP Growth Q2-2026 5.29% (y/y) - Inflation September 2026 +3.28% (y/y) - Central Bank BI Rate September 2026 5.75% Pre-Colonial History of Indonesia In the period before western European powers were able to control Sout… | O87: full-text | P87: gdelt | Q87: 2026-10-20
A88: 87 | B88: 2026-10-19 | C88: 2026 | D88: அனுமன், கல் யானை வீரன் நடுகல் கண்டுபிடிப்பு | E88: கல்வெட்டு, நடுகல் | F88: Inscription / Epigraphy, Hero stone / Memorial stone | G88: கல்வெட்டு, நடுகல் | H88: Tamil Nadu | I88: temple.dinamalar.com | J88: India | K88: Tamil | L88: https://temple.dinamalar.com/news_detail.php?id=111907 | N88: | | | | முதல் பக்கம் » இன்றைய செய்திகள் | | | அனுமன், கல் யானை வீரன் நடுகல் கண்டுபிடிப்பு பதிவு செய்த நாள் 05 மார் 2021 11:03 மதுரை: மதுரை அப்பன் திருப்பதியில் 17- 18ம் நுாற்றாண்டின் அனுமன், வண்டியூரில் கல் யானை வீரன் நடு கற்களை சிற்பக்கலை வல்லுநர்கள் தேவி, சசிகலா, வரலாற்று ஆய்வாளர் அறிவுச்செல்வம் க… | O88: full-text | P88: gdelt | Q88: 2026-10-19
A89: 88 | B89: 2026-10-19 | C89: 2026 | D89: அபிஷேக பிரியனுக்கு அன்னாபிஷேகம்: சிவாலயங்களில் பக்தர்கள் பரவசம் | E89: கல்வெட்டு | F89: Inscription / Epigraphy | G89: கல்வெட்டு | H89: Puducherry | I89: temple.dinamalar.com | J89: India | K89: Tamil | L89: https://temple.dinamalar.com/news_detail.php?id=117973 | N89: | | | | முதல் பக்கம் » இன்றைய செய்திகள் | | | அபிஷேக பிரியனுக்கு அன்னாபிஷேகம்: சிவாலயங்களில் பக்தர்கள் பரவசம் பதிவு செய்த நாள் 21 அக் 2021 11:10 ஐப்பசி பவுர்ணமி திருநாளில், அனைத்து சிவாலயங்களிலும், சிவலிங்கத்துக்கு அன்னத்தால் அலங்காரம் செய்து வழிபடுவது வழக்கம். நேற்று, திருப்பூர் சுற்றுப்பகுதியில் உ… | O89: full-text | P89: gdelt | Q89: 2026-10-19
A90: 89 | B90: 2026-10-19 | C90: 2026 | D90: அயோத்தி கும்பாபிஷேகம்; இது ராம பக்தியின் துவக்கம் அல்ல.. பழந்தமிழரின் தொடர்ச்சி! | E90: கல்வெட்டு, தொல்லியல் | F90: Inscription / Epigraphy, Archaeology / Excavation | G90: கல்வெட்டு, கல்வெட்டுகள், செப்பேடு, தொல்லியல், தொல்லியல் துறை | H90: Tamil Nadu, Sri Lanka | I90: temple.dinamalar.com | J90: India | K90: Tamil | L90: https://temple.dinamalar.com/news_detail.php?id=141086 | N90: | | | | முதல் பக்கம் » இன்றைய செய்திகள் | | | அயோத்தி கும்பாபிஷேகம்; இது ராம பக்தியின் துவக்கம் அல்ல.. பழந்தமிழரின் தொடர்ச்சி! பதிவு செய்த நாள் 21 ஜன 2024 08:01 திருமாலின் தசாவதாரங்களில், சிறப்பு வாய்ந்தது ராமாவதாரம். கம்பர், நன்மையும் செல்வமும் நாளும் நல்குமே என, ராம வழிபாட்டை சிறப்பிக்கிறார். ராமா… | O90: full-text | P90: gdelt | Q90: 2026-10-19
A91: 90 | B91: 2026-10-19 | C91: 2026 | D91: அலங்காநல்லூரில் சிதிலமடைந்த நிலையில் பிற்கால பாண்டியர் கோயில் | E91: கல்வெட்டு | F91: Inscription / Epigraphy | G91: கல்வெட்டு, கல்வெட்டு ஆய்வாளர் | I91: temple.dinamalar.com | J91: India | K91: Tamil | L91: https://temple.dinamalar.com/news_detail.php?id=118151 | N91: | | | | முதல் பக்கம் » இன்றைய செய்திகள் | | | அலங்காநல்லூரில் சிதிலமடைந்த நிலையில் பிற்கால பாண்டியர் கோயில் பதிவு செய்த நாள் 31 அக் 2021 12:10 அலங்காநல்லுார் : மதுரை அலங்காநல்லுார் அருகே கிழவிகுளத்தில் இருந்து 5 கி.மீ.,ல் பச்சை வயல்வெளிகள் நடுவில் நம் வரலாற்று பொக்கிஷங்களை சுமந்தபடி சிதிலமடைந்த நில… | O91: full-text | P91: gdelt | Q91: 2026-10-19
A92: 91 | B92: 2026-10-19 | C92: 2026 | D92: அழிவின் விளிம்பில் பாண்டியர் கால சிவன் கோவில் | E92: கல்வெட்டு, தொல்லியல் | F92: Inscription / Epigraphy, Archaeology / Excavation | G92: கல்வெட்டு, கல்வெட்டுகள், தொல்லியல், தொல்லியல் துறை | H92: Tamil Nadu | I92: temple.dinamalar.com | J92: India | K92: Tamil | L92: https://temple.dinamalar.com/news_detail.php?id=140381 | N92: | | | | முதல் பக்கம் » இன்றைய செய்திகள் | | | அழிவின் விளிம்பில் பாண்டியர் கால சிவன் கோவில் பதிவு செய்த நாள் 17 டிச 2023 10:12 ராமநாதபுரம் மாவட்டம் மேலக்கொடுமலுாரில் உள்ள வரலாற்று சிறப்பு மிக்க பாண்டியர் கால சிவன் கோவில், அழியும் நிலையில் உள்ளதால், அதை புனரமைத்து பாதுகாக்க வேண்டும் என, வரலாற்று ஆய்வ… | O92: full-text | P92: gdelt | Q92: 2026-10-19
A93: 92 | B93: 2026-10-19 | C93: 2026 | D93: கள்ளிக்குடியில் கி.பி.8ம் நுாற்றாண்டு விஷ்ணு சிலை கண்டுபிடிப்பு | E93: கல்வெட்டு | F93: Inscription / Epigraphy | G93: கல்வெட்டு | I93: temple.dinamalar.com | J93: India | K93: Tamil | L93: https://temple.dinamalar.com/news_detail.php?id=107600 | N93: | | | | முதல் பக்கம் » இன்றைய செய்திகள் | | | கள்ளிக்குடியில் கி.பி.8ம் நுாற்றாண்டு விஷ்ணு சிலை கண்டுபிடிப்பு பதிவு செய்த நாள் 15 செப் 2020 10:09 மதுரை : மதுரை மாவட்டம் கள்ளிக்குடி பெரிய உலகாணிகுண்டாறு மேற்கு கரையில் 8ம் நுாற்றாண்டு பாண்டியர் கால விஷ்ணு சிலை கண்டுபிடிக்கப்பட்டது. அரசு அருங்காட்சிய க… | O93: full-text | P93: gdelt | Q93: 2026-10-19
A94: 93 | B94: 2026-10-19 | C94: 2026 | D94: காஞ்சியில் பல்லவர் கால மூத்ததேவி.. சோழர் கால அய்யனார் சிலை | E94: கல்வெட்டு | F94: Inscription / Epigraphy | G94: கல்வெட்டு | I94: temple.dinamalar.com | J94: India | K94: Tamil | L94: https://temple.dinamalar.com/news_detail.php?id=138500 | N94: | | | | முதல் பக்கம் » இன்றைய செய்திகள் | | | காஞ்சியில் பல்லவர் கால மூத்ததேவி.. சோழர் கால அய்யனார் சிலை பதிவு செய்த நாள் 11 செப் 2023 11:09 காஞ்சிபுரத்தை அடுத்த கீழ்சிறுணை பெருகல் கிராமத்தில், தொண்டை மண்டல வரலாற்று ஆய்வு சங்கத்தினர், பல்லவர் கால மூத்ததேவி சிற்பத்தையும்; சோழர் கால அய்யனார் எனப்படும்… | O94: full-text | P94: gdelt | Q94: 2026-10-19
A95: 94 | B95: 2026-10-19 | C95: 2026 | D95: கீழடி அருகே கி.பி., 12ம் நூற்றாண்டை சேர்ந்த கல்வெட்டு, சிலைகள் கண்டெடுப்பு | E95: கல்வெட்டு, தொல்லியல் | F95: Inscription / Epigraphy, Archaeology / Excavation | G95: கல்வெட்டு, கல்வெட்டுகள், தொல்லியல், கீழடி | I95: temple.dinamalar.com | J95: India | K95: Tamil | L95: https://temple.dinamalar.com/news_detail.php?id=156278 | N95: | | | | முதல் பக்கம் » இன்றைய செய்திகள் | | | கீழடி அருகே கி.பி., 12ம் நூற்றாண்டை சேர்ந்த கல்வெட்டு, சிலைகள் கண்டெடுப்பு பதிவு செய்த நாள் 27 நவ 2025 11:11 கீழடி; கீழடி அருகே அம்பலத்தாடி கிராமத்தில் கி.பி., 12ம் நூற்றாண்டைச் சேர்ந்த கல்வெட்டு, சிலைகளை ஆய்வாளர்கள் கண்டறிந்துள்ளனர். கீழடி, கொந்தகை, உள்… | O95: full-text | P95: gdelt | Q95: 2026-10-20
A96: 95 | B96: 2026-10-19 | C96: 2026 | D96: குன்றத்தில் பாரம்பரியமாக நடந்து வரும் 4 ஏர் பூட்டுதல் | E96: கல்வெட்டு | F96: Inscription / Epigraphy | G96: கல்வெட்டு | I96: temple.dinamalar.com | J96: India | K96: Tamil | L96: https://temple.dinamalar.com/news_detail.php?id=113041 | N96: | | | | முதல் பக்கம் » இன்றைய செய்திகள் | | | குன்றத்தில் பாரம்பரியமாக நடந்து வரும் 4 ஏர் பூட்டுதல் பதிவு செய்த நாள் 15 ஏப் 2021 01:04 திருப்பரங்குன்றம், : தமிழ்ப் புத்தாண்டை முன்னிட்டு பாரம்பரியமாக நடந்துவரும் திருப்பரங்குன்றம் கிராமத்தினர் சார்பில் மலைக்கு பின்புறமுள்ள கோயில் நிலத்தில் நான்கு ஏர் … | O96: full-text | P96: gdelt | Q96: 2026-10-19
A97: 96 | B97: 2026-10-19 | C97: 2026 | D97: கொங்கபட்டியில் கிடைத்த தமிழி(பிராமி) கல்வெட்டு | E97: கல்வெட்டு, நடுகல், தொல்லியல் | F97: Inscription / Epigraphy, Hero stone / Memorial stone, Archaeology / Excavation | G97: கல்வெட்டு, கல்வெட்டுக்கள், கல்வெட்டு ஆய்வாளர், நடுகல், தொல்லியல், தொல்லியல் துறை | I97: temple.dinamalar.com | J97: India | K97: Tamil | L97: https://temple.dinamalar.com/news_detail.php?id=111939 | N97: | | | | முதல் பக்கம் » இன்றைய செய்திகள் | | | கொங்கபட்டியில் கிடைத்த தமிழி(பிராமி) கல்வெட்டு பதிவு செய்த நாள் 06 மார் 2021 05:03 உசிலம்பட்டி : உசிலம்பட்டி அருகே கொங்கபட்டியில் கிடைத்த தமிழி(பிராமி) கல்வெட்டு 2000 ஆண்டுகளுக்கு முன்பாக இறந்தவரின் நினைவாக வைக்கப்பட்ட கல்வெட்டாக இருக்கலாம் என தொல்லியல் … | O97: full-text | P97: gdelt | Q97: 2026-10-19
A98: 97 | B98: 2026-10-19 | C98: 2026 | D98: சிதிலமடைந்த புல்லுகுடி சிவன் கோயில் புனரமைக்க அரசு நடவடிக்கை எடுக்குமா | E98: கல்வெட்டு, தொல்லியல் | F98: Inscription / Epigraphy, Archaeology / Excavation | G98: கல்வெட்டு, கல்வெட்டுகள், தொல்லியல் | I98: temple.dinamalar.com | J98: India | K98: Tamil | L98: https://temple.dinamalar.com/news_detail.php?id=155537 | N98: | | | | முதல் பக்கம் » இன்றைய செய்திகள் | | | சிதிலமடைந்த புல்லுகுடி சிவன் கோயில் புனரமைக்க அரசு நடவடிக்கை எடுக்குமா பதிவு செய்த நாள் 24 அக் 2025 11:10 திருவாடானை: ராமநாதபுரம் மாவட்டம் திருவாடானை அருகே புல்லுகுடியில் பழமை வாய்ந்த கைலாசநாதர் சிவன் கோயில் பராமரிப்பின்றி கருவறை உட்பட கட்டுமானங்கள் சிதி… | O98: full-text | P98: gdelt | Q98: 2026-10-19
A99: 98 | B99: 2026-10-19 | C99: 2026 | D99: சிதைந்து கிடக்கும் சோழர் கால நாகநாதர் கோவில்: மாதிரி கும்பாபிஷேகம் நடத்த முடிவு | E99: கல்வெட்டு, தொல்லியல் | F99: Inscription / Epigraphy, Archaeology / Excavation | G99: கல்வெட்டு, தொல்லியல், தொல்லியல் துறை | I99: temple.dinamalar.com | J99: India | K99: Tamil | L99: https://temple.dinamalar.com/news_detail.php?id=133010 | N99: | | | | முதல் பக்கம் » இன்றைய செய்திகள் | | | சிதைந்து கிடக்கும் சோழர் கால நாகநாதர் கோவில்: மாதிரி கும்பாபிஷேகம் நடத்த முடிவு பதிவு செய்த நாள் 08 மார் 2023 10:03 தஞ்சாவூர்: கும்பகோணம் அருகே மானம்பாடியில் ராஜேந்திர சோழன் காலத்தில் கட்டப்பட்ட நாகநாதசுவாமி கோவிலில், மாதிரி கும்பாபிஷேகம் நடத்தப்படும… | O99: full-text | P99: gdelt | Q99: 2026-10-19
A100: 99 | B100: 2026-10-19 | C100: 2026 | D100: சித்திரைதான் தமிழ் புத்தாண்டு : வரலாற்று ஆதாரங்களை பட்டியலிடுகிறார் ஆய்வாளர் | E100: கல்வெட்டு | F100: Inscription / Epigraphy | G100: கல்வெட்டு, கல்வெட்டுகள், கல்வெட்டுக்கள், வட்டெழுத்து, கிரந்த எழுத்து | H100: Puducherry, Kerala, Sri Lanka, Thailand, Cambodia | I100: temple.dinamalar.com | J100: India | K100: Tamil | L100: https://temple.dinamalar.com/news_detail.php?id=119141 | N100: | | | | முதல் பக்கம் » இன்றைய செய்திகள் | | | சித்திரைதான் தமிழ் புத்தாண்டு : வரலாற்று ஆதாரங்களை பட்டியலிடுகிறார் ஆய்வாளர் பதிவு செய்த நாள் 04 டிச 2021 12:12 அண்மையில் பொங்கல் இலவச பொருட்கள் பையின் மாதிரியை வெளியிட்டு புதிய சர்ச்சைக்கு வித்திட்டுள்ளது தமிழக அரசு. கருணாநிதி ஆட்சியில் இருந்தபோது தமிழ்… | O100: full-text | P100: gdelt | Q100: 2026-10-19
A101: 100 | B101: 2026-10-19 | C101: 2026 | D101: செஞ்சி அருகே 800 ஆண்டு பழமையான கல்வெட்டு கண்டுபிடிப்பு | E101: கல்வெட்டு | F101: Inscription / Epigraphy | G101: கல்வெட்டு | I101: temple.dinamalar.com | J101: India | K101: Tamil | L101: https://temple.dinamalar.com/news_detail.php?id=164881 | N101: | | | | முதல் பக்கம் » இன்றைய செய்திகள் | | | செஞ்சி அருகே 800 ஆண்டு பழமையான கல்வெட்டு கண்டுபிடிப்பு பதிவு செய்த நாள் 21 செப் 2026 10:09 செஞ்சி: செஞ்சி அடுத்த போத்துவாய் கிராம மலைக்குன்றில் 800 ஆண்டுகள் பழமையான கல்வெட்டு, பாண்டியர்களின் மீன் சின்னங்களும் கண்டுபிடிக்கப்பட்டுள்ளன. செஞ்சி அடுத்த போத்து… | O101: full-text | P101: gdelt | Q101: 2026-10-19
A102: 101 | B102: 2026-10-19 | C102: 2026 | D102: செஞ்சி அருகே பழங்கால விஷ்ணு துர்கை, சிற்பங்கள் கண்டுபிடிப்பு | E102: கல்வெட்டு, நடுகல் | F102: Inscription / Epigraphy, Hero stone / Memorial stone | G102: கல்வெட்டு, கல்வெட்டு ஆய்வாளர், நடுகல் | I102: temple.dinamalar.com | J102: India | K102: Tamil | L102: https://temple.dinamalar.com/news_detail.php?id=155939 | N102: | | | | முதல் பக்கம் » இன்றைய செய்திகள் | | | செஞ்சி அருகே பழங்கால விஷ்ணு துர்கை, சிற்பங்கள் கண்டுபிடிப்பு பதிவு செய்த நாள் 11 நவ 2025 03:11 செஞ்சி; செஞ்சி அருகே பழங்கால சிற்பங்களை வரலாற்று ஆய்வாளர் கண்டு பிடித்துள்ளார். விழுப்புரத்தை சேர்ந்த வரலாற்று ஆய்வாளர் செங்குட்டுவன் செஞ்சி அடுத்த நங்கியானந்த… | O102: full-text | P102: gdelt | Q102: 2026-10-19
A103: 102 | B103: 2026-10-19 | C103: 2026 | D103: சோழர் கால கல்வெட்டு கண்டெடுப்பு; வீரனுக்காக ஒரு ஊரையே உருவாக்கியதாக செய்தி! | E103: கல்வெட்டு, தொல்லியல் | F103: Inscription / Epigraphy, Archaeology / Excavation | G103: கல்வெட்டு, கிரந்த எழுத்து, தொல்லியல் | I103: temple.dinamalar.com | J103: India | K103: Tamil | L103: https://temple.dinamalar.com/news_detail.php?id=138449 | N103: | | | | முதல் பக்கம் » இன்றைய செய்திகள் | | | சோழர் கால கல்வெட்டு கண்டெடுப்பு; வீரனுக்காக ஒரு ஊரையே உருவாக்கியதாக செய்தி! பதிவு செய்த நாள் 08 செப் 2023 11:09 சென்னை:கிருஷ்ணகிரி மாவட்டம், தேவர்முக்குளம் பள்ளிகொண்ட பெருமாள் கூரையில் இருந்து, சோழர் கால வணிக குழு சார்ந்த கல்வெட்டு கண்டெடுக்கப்பட்டுள்ளது… | O103: full-text | P103: gdelt | Q103: 2026-10-19
...

Sheet Research papers
A1: No | B1: Year | C1: Date | D1: Title | E1: Authors | F1: Journal / venue | G1: Keyword group (Tamil) | H1: Keyword group (English) | I1: Matched terms | J1: Places mentioned | K1: Language | L1: Link | M1: Free full text | N1: DOI | O1: Abstract (start) | P1: Found via | Q1: Found on
A2: 1 | B2: 2026 | C2: 2026-05-25 | D2: "Regional Traditions of Smoking: A Comparative Study of Terracotta Pipes in South and North India with Evidence from Vembakottai" | E2: P. Baskar | F2: Zenodo (CERN European Organization for Nuclear Research) | G2: தொல்லியல் | H2: Archaeology / Excavation | I2: archaeology, keeladi, adichanallur, vembakottai | J2: Tamil Nadu | K2: English/Other | L2: https://doi.org/10.5281/zenodo.20376141 | M2: https://doi.org/10.5281/zenodo.20376141 | N2: 10.5281/zenodo.20376141 | O2: Abstract: Terracotta smoking pipes constitute an important yet understudied class of early modern artifacts in South Asian archaeology, reflecting the widespread adoption of tobacco following its introduction in the late 16th century CE. This study presents a detailed analysis of a group of terracotta pipe bowls recovered from Vembakottai, Tamil Nadu, focusing on their morphology, manufacturing technology, use-wear patterns, and chronological significance. The assemblage is characterized by predominantly globular and bulbous forms with short stem sockets, minimal decoration, and clear evidence | P2: OpenAlex | Q2: 2026-10-17
A3: 2 | B3: 2026 | C3: 2026-03-11 | D3: A CULTURAL AND HISTORICAL STUDY OF HERO-STONE (NADUKAL) WORSHIP AMONG MALAYALIS (TRIBLE) IN THE KALVARAYAN HILLY AREA OF HERO-STONE WORSHIP | E3: Asaikkannu Sakthivel; Franklin Thambi Jose. S | F3: International Journal of Education Psychology and Counseling | G3: நடுகல், தொல்லியல் | H3: Hero stone / Memorial stone, Archaeology / Excavation | I3: hero stone, hero stones, hero-stone, nadukal, archaeology, archaeological, megalithic | J3: Tamil Nadu | K3: English/Other | L3: https://doi.org/10.35631/ijepc.1162036 | M3: https://doi.org/10.35631/ijepc.1162036 | N3: 10.35631/ijepc.1162036 | O3: Background: This paper analyzes the hero-stone (Nadukal) traditions of the Malayali tribes in the Kalrayan Hills. From the Megalithic era through the Sangam age, erecting memorials for warriors who perished in battle was a cornerstone of Tamil culture, extensively documented in the Tolkappiyam, Sangam literature, and devotional hymns. The study employs a Qualitative Descriptive-Historical Design. It adopts a longitudinal perspective to track the evolution of worship from prehistoric archaeological evidence to contemporary ethnographic practices. By integrating archaeology and anthropology, the | P3: OpenAlex | Q3: 2026-10-17
A4: 3 | B4: 2026 | C4: 2026-06-05 | D4: A Comprehensive Review on the Origin and Evolution of Varmam | E4: L.Deepa Nandhini | F4: Journal of chemical health risks | G4: கல்வெட்டு, தொல்லியல் | H4: Inscription / Epigraphy, Archaeology / Excavation | I4: inscriptions, archaeological | K4: English/Other | L4: https://jchr.org/index.php/JCHR/article/view/14545 | M4: https://jchr.org/index.php/JCHR/article/download/14545/7814 | O4: Introduction: Varmam is a unique therapeutic and martial science of the Siddha Medicine that focuses on vital energy points of the human body for the prevention and management of diseases Objectives: The present review aims to explore the historical origin, evolution, and therapeutic significance of Varmam through classical literature and contemporary evidence. Methods: A narrative literature review was conducted using classical Siddha texts, Tamil literary sources, palm-leaf manuscripts, archaeological evidences, and published scientific articles retrieved from databases including PubMed, Sco | P4: OpenAlex | Q4: 2026-10-17
A5: 4 | B5: 2026 | C5: 2026-01-26 | D5: A Computational Framework for the Structural Analysis of the Indus Valley Script: Integrating Comprehensive Inference, Nexus Validation, and Cross-Script Motif Alignment | E5: August Tudor | F5: Zenodo (CERN European Organization for Nuclear Research) | G5: கல்வெட்டு, தொல்லியல் | H5: Inscription / Epigraphy, Archaeology / Excavation | I5: inscriptions, graffiti marks, archaeological | J5: Tamil Nadu | K5: English/Other | L5: https://doi.org/10.5281/zenodo.18371284 | M5: https://doi.org/10.5281/zenodo.18371284 | N5: 10.5281/zenodo.18371284 | O5: The Indus Valley Script (IVS), dating to c. 2600–1900 BCE, remains one of the world's most enduring undeciphered writing systems. Despite over a century of scholarship, the absence of bilingual texts and the brevity of inscriptions (median 4–5 signs) have prevented consensus on whether the script encodes a full language or functions as a restricted symbolic system. This paper presents CI+NIS, an original, reproducible computational framework that integrates Comprehensive Inference (CI)—a dynamic Bayesian-Frequentist fusion—with the Nexus Inferential System (NIS), which validates inferred struc | P5: OpenAlex | Q5: 2026-10-17
A6: 5 | B6: 2026 | C6: 2026-09-01 | D6: A Critical Study of the Social Status of the Brahmins Belonging to Various Vedic Śākhās Mentioned in Ancient Indian Inscriptions | E6: Deepshikha Mondal; Dr. Nandadulal Mandal | F6: Zenodo (CERN European Organization for Nuclear Research) | G6: கல்வெட்டு | H6: Inscription / Epigraphy | I6: inscriptions, copper plates | K6: English/Other | L6: https://doi.org/10.5281/zenodo.22709831 | M6: https://doi.org/10.5281/zenodo.22709831 | N6: 10.5281/zenodo.22709831 | O6: Abstract: Inscriptions constitute the earliest and most fundamental primary source for the study of ancient Indian history and literature. These epigraphic records illuminate multifaceted dimensions of the socio-political, cultural, and religious history of contemporary India, as well as the preservation of the Indian knowledge tradition. In particular, land-grant inscriptions—recorded on copper plates and stone slabs—provide detailed documentation regarding the gotra (lineage), pravara (ancestral heritage), śākhā (Vedic recension/branch), domicile, and scholarly devotion of the Brahmins of th | P6: OpenAlex | Q6: 2026-10-17
A7: 6 | B7: 2026 | C7: 2026-09-21 | D7: A Historical Study of the Tamil Inscriptions Discovered at the Buddhist Heritage Site of Velgam Vehera | E7: U.S.Y. Sahan Mahesh Senarath yapa | F7: Zenodo (CERN European Organization for Nuclear Research) | G7: கல்வெட்டு, தொல்லியல் | H7: Inscription / Epigraphy, Archaeology / Excavation | I7: inscriptions, archaeology | J7: Sri Lanka | K7: English/Other | L7: https://doi.org/10.5281/zenodo.22870959 | M7: https://doi.org/10.5281/zenodo.22870959 | N7: 10.5281/zenodo.22870959 | O7: The ruins of an ancient Buddhist monastery are found at Periyakulam in the Kattukulampattu division of the Trincomalee District. Formerly referred to as Natanar Kovil, it is known today as Velgam Vehera. The ruins of this monastery exhibit distinct Tamil architectural characteristics. Notably, at least sixteen Tamil inscriptions dating to the eleventh century, during the reigns of several Chola emperors, have been discovered here. Fourteen of these have been published by Professors K. Indrapala and A. Velupillai. Broadly, these epigraphs indicate that this Buddhist institution in Periyakulam f | P7: OpenAlex | Q7: 2026-10-16
A8: 7 | B8: 2026 | C8: 2026-04-20 | D8: A Structural-Semantic Model of the Indus Script: Syntagmatic Patterns and Dravidian Continuity | E8: Ella Kiseleva | F8: Zenodo (CERN European Organization for Nuclear Research) | G8: கல்வெட்டு, தொல்லியல் | H8: Inscription / Epigraphy, Archaeology / Excavation | I8: inscription, archaeological | J8: Tamil Nadu | K8: English/Other | L8: https://doi.org/10.5281/zenodo.19662775 | M8: https://doi.org/10.5281/zenodo.19662775 | N8: 10.5281/zenodo.19662775 | O8: This study presents a structural-semantic model of the Indus Valley script based on the statistical analysis of sign sequences in the EBUDS corpus (Yadav et al., TIFR, 2007). The model proposes that Indus signs function as operators within fixed syntagmatic patterns rather than as phonetic notations. The interpretation is validated through internal positional analysis and external comparison with Tamil Siddha concepts and Vedic Sanskrit. The core of the model consists of eight high-frequency sign sequences extracted from the EBUDS corpus. These sequences form a coherent syntagmatic structure t | P8: OpenAlex | Q8: 2026-10-17
A9: 8 | B9: 2026 | C9: 2026-05-03 | D9: A Study of Maritime Trade in the Tamil Twin Epics | E9: A, Prasanth | F9: International Research Journal of Tamil | G9: தொல்லியல் | H9: Archaeology / Excavation | I9: archaeological | K9: English/Other | L9: https://irjt.iorpress.org/index.php/irjt/article/view/2582 | O9: Numerous studies conducted by governmental and non-governmental researchers have sought to establish the antiquity and richness of Tamil civilization. Drawing upon archaeological evidence and literary sources, these studies have contributed significantly to understanding the historical identity and achievements of the Tamil people. Among the many aspects of Tamil civilization, maritime trade occupies a prominent place, demonstrating the Tamils' active participation in overseas commerce from ancient times. In this context, the present study explores the maritime trade practices reflected in the | P9: Journal: International Research Journal of Tamil | Q9: 2026-10-16
A10: 9 | B10: 2026 | C10: 2026-05-03 | D10: A Study of Tamil Culture through Akananuru | E10: S, Mary Janet; S, Mejila Jeevi | F10: International Research Journal of Tamil | G10: நடுகல் | H10: Hero stone / Memorial stone | I10: hero stones, nadukal | K10: English/Other | L10: https://irjt.iorpress.org/index.php/irjt/article/view/2588 | O10: Akananuru occupies a distinguished place in the Sangam literary tradition as a classical anthology that vividly portrays the inner world of human emotions and love with remarkable literary sophistication. It integrates human feelings, the various stages of love, natural landscapes, and social ethics into a unified poetic expression. Consequently, Akananuru is valued not only as a literary masterpiece but also as an important cultural document that preserves the traditions and way of life of the ancient Tamils.An examination of Tamil culture through Akananuru reveals that culture is not merely | P10: Journal: International Research Journal of Tamil | Q10: 2026-10-16
A11: 10 | B11: 2026 | C11: 2026-02-12 | D11: A Sustainable Tourism Model for Keeladi and the Sangam Landscape | E11: Arachchi Mudiyanselage Kanishka Kalhari; G. Paranthaman | F11: Shanlax International Journal of Management | G11: தொல்லியல் | H11: Archaeology / Excavation | I11: archaeological, excavation site, keeladi | J11: Sri Lanka | K11: English/Other | L11: https://doi.org/10.34293/management.v13is1-i2-feb.10400 | M11: https://shanlaxjournals.in/journals/index.php/management/article/download/10400/9055 | N11: 10.34293/management.v13is1-i2-feb.10400 | O11: This research addresses the critical need for a sustainable tourism paradigm in the Vaigai River Valley which is anchored on the record-breaking excavation site of Keeladi. Although Keeladi with its 6 th century BCE urban sophistication, demonstrated through carbon dating (580 BCE) reinvents the history of South Asia, the contemporary tourism cannot be seen as changing or tied to the local economy. In this paper, there are several suggestions to convert the corridor, which is a passive viewing model, to an active narrative immersion circuit through offerings of an Integrated Heritage Landscape | P11: OpenAlex | Q11: 2026-10-17
A12: 11 | B12: 2026 | C12: 2026-03-04 | D12: AI Powered OCR Solution for Tamil Historical Document | E12: Ms.T. Saraswathi; HARISH S; Abishek Kumar B | F12: International Conference on Intelligent Sustainable Systems (ICISS) | G12: கல்வெட்டு | H12: Inscription / Epigraphy | I12: inscriptions | K12: English/Other | L12: https://doi.org/10.1109/iciss67859.2026.11453612 | N12: 10.1109/iciss67859.2026.11453612 | O12: Palm leaves, plates of copper and stone inscriptions which were used in ancient Tamil are an invaluable cultural source yet manual reading of these sources is largely hampered by the physical decay, the blurring of the scripts and complicated ligatures. Existing optical character recognition (OCR) technologies cannot recognize such historical documents well due to noise, variation in spacing and changes in style. This project presents an artificial intelligence-based OCR system that is specifically trained to work with ancient Tamil manuscripts. Through a semi-supervised form of deep learning, | P12: OpenAlex | Q12: 2026-10-17
A13: 12 | B13: 2026 | C13: 2026-07-10 | D13: AI – Based Recognition and Interpretation of Ancient Tamil Inscriptions and Palm Leaf Manuscripts | E13: T. Ramanandhini, Dr. M. Gopianand, Gowtham K, M. Safeeka Department of Computer Applications PSNA College of Engineering and Technology, Dindigul,India | F13: Zenodo (CERN European Organization for Nuclear Research) | G13: கல்வெட்டு | H13: Inscription / Epigraphy | I13: inscriptions | K13: English/Other | L13: https://doi.org/10.5281/zenodo.23036680 | M13: https://doi.org/10.5281/zenodo.23036680 | N13: 10.5281/zenodo.23036680 | O13: Ancient Tamil manuscripts and carvescontain valuable historical, literary, and culturalinformation. Therefore, many items have deterioratedover time, making their explanation difficult. Thisstudy presents a web-based system designed torecognize and interpret ancient Tamil scripts usingthe Gemini Vision model. The proposed system viewsthe images of manuscripts and carves the text content,which is changed into simple Tamil explanations forbetter understanding. This enables modern readersto access and interpret ancient knowledge moreeasily than before. Flask and MySQL were used tomanage user auth | P13: OpenAlex | Q13: 2026-10-16
A14: 13 | B14: 2026 | C14: 2026-09-04 | D14: ARCHAEOLOGICAL AND HISTORICAL EVIDENCE FOR FOREST RIGHTS CLAIMS OF NARIYUTHU VILLAGE UNDER THE FOREST RIGHTS ACT, 2006 | E14: THANUSHKODI S | F14: Zenodo (CERN European Organization for Nuclear Research) | G14: தொல்லியல் | H14: Archaeology / Excavation | I14: archaeological | J14: Tamil Nadu | K14: English/Other | L14: https://doi.org/10.5281/zenodo.22307110 | M14: https://doi.org/10.5281/zenodo.22307110 | N14: 10.5281/zenodo.22307110 | O14: PURPOSE AND METHODOLOGY: A comprehensive compilation of epigraphical and archaeological evidence sourced from the Avanam journal (Tamil Nadu Archaeological Society), academic research, archival district gazetteers, and direct field data. This evidence dossier has been systematically compiled under the Forest Rights Act, 2006, and the Amended Rules, 2012 (Rule 13), to legally substantiate the traditional land rights of the people of Nariyuthu. | P14: OpenAlex | Q14: 2026-10-17
A15: 14 | B15: 2026 | C15: 2026-06-18 | D15: Accounting approaches to the study of historical Tamil events | E15: Thangavelu Chinnasamy | F15: De Computis - Revista Española de Historia de la Contabilidad | G15: கல்வெட்டு, தொல்லியல் | H15: Inscription / Epigraphy, Archaeology / Excavation | I15: inscriptions, archaeological, keeladi, adichanallur | K15: English/Other | L15: https://doi.org/10.26784/issn.1886-1881.23.1.13660 | M15: https://www.upo.es/revistas/index.php/decomputis/article/download/13660/11422 | N15: 10.26784/issn.1886-1881.23.1.13660 | O15: This study examines the historical development of accounting in Tamil civilization based on archaeological, literary, epigraphic, and administrative evidence, tracing its evolution from the Sangam period (300 BCE–300 CE) to the institutional systems of the Chola and Pandya dynasties (9th–14th centuries CE). Findings from sites such as Keeladi, Adichanallur, and Poompuhar reveal early urban and commercial organization that required structured economic record-keeping. Tamil literary sources, including the Thirukkural and Sangam anthologies, along with temple inscriptions and palm-leaf manuscript | P15: OpenAlex | Q15: 2026-10-17
A16: 15 | B16: 2026 | C16: 2026-04-19 | D16: Addendum to Molina (2026e) — The Meluhhan Commercial Package and the Keezhadi Phonologization Event: Triple-Point Verification of Proto-Dravidian Continuity from the Indus Valley to Tamil-Brahmi (2500-600 BCE) | E16: Juan Gabriel Molina | F16: Zenodo (CERN European Organization for Nuclear Research) | G16: கல்வெட்டு, தொல்லியல் | H16: Inscription / Epigraphy, Archaeology / Excavation | I16: tamil-brahmi, tamil brahmi, archaeology, archaeological, megalithic, keeladi, keezhadi, tnsda | J16: Tamil Nadu | K16: English/Other | L16: https://doi.org/10.5281/zenodo.19655074 | M16: https://doi.org/10.5281/zenodo.19655074 | N16: 10.5281/zenodo.19655074 | O16: This deposit is a formal addendum to Molina (2026e), FMX-IVT-2026-PUB, which established the Meluhhan Interregnum Hypothesis and the selective survival of Indus administrative frame signs into the South Indian Megalithic period (Fisher p = 1.62 x 10^-19, odds ratio 16.7, medial control 0/12). The present addendum extends that deposit with four additional findings. First, triple-point verification of Proto-Dravidian as the spoken language of the Harappan/Meluhhan civilization. The phonetic anchor is the sesame loanword ellu (DEDR 834), frozen in Akkadian and Sumerian at the Harappan institution | P16: OpenAlex | Q16: 2026-10-16
A17: 16 | B17: 2026 | C17: 2026-04-19 | D17: Addendum to Molina (2026e) — The Meluhhan Commercial Package and the Keezhadi Phonologization Event: Triple-Point Verification of Proto-Dravidian Continuity from the Indus Valley to Tamil-Brahmi (2500-600 BCE) — Private Technical Record | E17: Juan Gabriel Molina | F17: Zenodo (CERN European Organization for Nuclear Research) | G17: கல்வெட்டு, தொல்லியல் | H17: Inscription / Epigraphy, Archaeology / Excavation | I17: tamil-brahmi, tamil brahmi, keezhadi | K17: English/Other | L17: https://doi.org/10.5281/zenodo.19655145 | M17: https://doi.org/10.5281/zenodo.19655145 | N17: 10.5281/zenodo.19655145 | O17: Private technical companion to public deposit FMX-IVT-2026-ADD-PUB and addendum private record to main deposit FMX-IVT-2026-PVT. Deposited as a restricted record for priority timestamping only. Not available for public access. Full analytical methodology and proprietary technical record withheld pending peer-reviewed publication. SHA-256 of this document is embedded in public deposit FMX-IVT-2026-ADD-PUB. Part of the Molina Methodology cross-corpus structural analysis series. Reference: FMX-IP-2026. | P17: OpenAlex | Q17: 2026-10-16
A18: 17 | B18: 2026 | C18: 2026-06-01 | D18: Administrative Procedures in the Chola Anaimangalam (Leiden) Plates: Reconstructing the Bureaucratic Workflow of a Land Grant | E18: Hemanth Thiru | F18: Zenodo (CERN European Organization for Nuclear Research) | G18: கல்வெட்டு | H18: Inscription / Epigraphy | I18: inscription, copper plate, copper plates, copper-plate | K18: English/Other | L18: https://doi.org/10.5281/zenodo.20493947 | M18: https://doi.org/10.5281/zenodo.20493947 | N18: 10.5281/zenodo.20493947 | O18: The Anaimangalam Copper Plates, widely known as the Leiden Copper Plates and formerly preserved at Leiden University1, constitute an important epigraphical record from the Chola period. The inscription documents a land grant issued during the reign of Rajaraja Chola I in support of the Chulamani Vihara at Nagapattinam, a Buddhist institution associated with the rulers of the Srivijaya kingdom. While the plates are often discussed in relation to Chola lineage, and maritime diplomacy, they also preserve exceptionally detailed evidence concerning administrative procedure and bureaucratic governan | P18: OpenAlex | Q18: 2026-10-17
A19: 18 | B19: 2026 | C19: 2026-01-07 | D19: Advanced Deep Learning OCR Algorithm for Deciphering and Digitizing Chola Period Tamil Inscriptions | E19: M Rajalakshmi; Shanthi Jeyabal; Manoj Ranjan Mishra; Bibhuti Bhusan Dash; Utpal Chandra De; Sudhansu Shekhar Patra | F19: International Conference on Mobile Computing and Sustainable Informatics (ICMCSI) | G19: கல்வெட்டு | H19: Inscription / Epigraphy | I19: inscriptions | K19: English/Other | L19: https://doi.org/10.1109/icmcsi67283.2026.11412629 | N19: 10.1109/icmcsi67283.2026.11412629 | O19: The Tamil inscriptions of the Chola are important in terms of conserving historical, cultural and linguistic history of the area. It could be tedious and time-consuming to read these inscriptions with the hand though. This paper discusses a customized Optical Character Recognition (OCR) system that facilitates easier digitization and transcription of old Tamil inscriptions. The solution is considered to be a combination of the YOLOv8, Tensorflow, and PyTorch systems that will promote the effectiveness of character recognition, segmentation, and detection. Our experiment with the method on a nu | P19: OpenAlex | Q19: 2026-10-16
A20: 19 | B20: 2026 | C20: 2026-04-17 | D20: An Automated Tamil Inscription Translator using Deep Learning for Robust Character Recognition and Epigraphic Text Formation | E20: Dr. P. Manivanan, R. Premrajesh, P. Senthamil Selvi and K. Murugananthi | F20: Zenodo (CERN European Organization for Nuclear Research) | G20: கல்வெட்டு | H20: Inscription / Epigraphy | I20: inscription, inscriptions | K20: English/Other | L20: https://doi.org/10.5281/zenodo.19634764 | M20: https://doi.org/10.5281/zenodo.19634764 | N20: 10.5281/zenodo.19634764 | O20: ABSTRACT An automated system developed using Deep Learning techniques was proposed to translate ancient Tamil inscriptions, characterized by their difficulty in recognizing characters, forming epigraphic text, degraded conditions, background noise, and irregular shaped characters, through the use of a combination of image enhancement techniques, Optical Character Recognition (OCR), and Natural Language Processing (NLP) to enhance the accuracy of recognition and create a coherent Tamil document. The OCR utilized a convolutional neural network (CNN) for character recognition while an artificial | P20: OpenAlex | Q20: 2026-10-16
A21: 20 | B21: 2026 | C21: 2026-07-20 | D21: An Epigraphical Corpus of 10 Indus Valley Tablets: Mirror Inversions, Traced Overlays, Dravidian Etymological Dictionary (DEDR) Tamil-Brahmi Glosses and English conceptual meaning | E21: Prabhakaran Karunakaran | F21: Zenodo (CERN European Organization for Nuclear Research) | G21: கல்வெட்டு | H21: Inscription / Epigraphy | I21: tamil-brahmi, tamil brahmi | K21: English/Other | L21: https://doi.org/10.5281/zenodo.21452528 | M21: https://doi.org/10.5281/zenodo.21452528 | N21: 10.5281/zenodo.21452528 | O21: NOTICE: Public access to the files in this repository has been temporarily restricted by the author | P21: OpenAlex | Q21: 2026-10-16
A22: 21 | B22: 2026 | C22: 2026-08-20 | D22: Ancient Tamil Governance Analytics: Mining the Uthiramerur Inscriptions for Democratic Insights | E22: Ramanathan Srinivasan; P. S. Aithal | F22: Zenodo (CERN European Organization for Nuclear Research) | G22: கல்வெட்டு | H22: Inscription / Epigraphy | I22: inscriptions | J22: Tamil Nadu | K22: English/Other | L22: https://doi.org/10.5281/zenodo.22031949 | M22: https://doi.org/10.5281/zenodo.22031949 | N22: 10.5281/zenodo.22031949 | O22: Purpose: Using data analytics and digital humanities, this paper investigates the governance records of Uthiramerur, a tenth-century Tamil village. The Uthiramerur assembly (sabha) is notable for its use of the kuṭavōlai, a palm-leaf ballot, for drawing lots. The records primarily exist as stone inscriptions placed during the reign of Parāntaka Chola I (c. 919 – 921 CE). The palm-leaf ballots, by contrast, were ephemeral. The inscriptions of Uthiramerur were treated as data, and the construction of the electoral algorithm and design of the committees (variyams) along with the rules of disquali | P22: OpenAlex | Q22: 2026-10-16
A23: 22 | B23: 2026 | C23: 2026-08-20 | D23: Ancient Tamil Governance Analytics: Mining the Uthiramerur Inscriptions for Democratic Insights | E23: Ramanathan Srinivasan; P. S. Aithal | F23: Poornaprajna International Journal of Philosophy & Languages (PIJPL) | G23: கல்வெட்டு | H23: Inscription / Epigraphy | I23: inscriptions | J23: Tamil Nadu | K23: English/Other | L23: https://doi.org/10.64818/pijpl.3107.4634.0053 | M23: https://www.poornaprajnapublication.com/index.php/pijpl/article/download/241/232/462 | N23: 10.64818/pijpl.3107.4634.0053 | O23: Purpose: Using data analytics and digital humanities, this paper investigates the governance records of Uthiramerur, a tenth-century Tamil village. The Uthiramerur assembly (sabha) is notable for its use of the kuṭavōlai, a palm-leaf ballot, for drawing lots. The records primarily exist as stone inscriptions placed during the reign of Parāntaka Chola I (c. 919 – 921 CE). The palm-leaf ballots, by contrast, were ephemeral. The inscriptions of Uthiramerur were treated as data, and the construction of the electoral algorithm and design of the committees (variyams) along with the rules of disquali | P23: OpenAlex | Q23: 2026-10-16
A24: 23 | B24: 2026 | C24: 2026-01-12 | D24: Archaeological Excavation Sites in Theni District: A Study on Iron Age and Early Historic Antiquities in Theni District | E24: Dr. S. Kasthuri | F24: Zenodo (CERN European Organization for Nuclear Research) | G24: தொல்லியல் | H24: Archaeology / Excavation | I24: archaeological, archaeological excavation | J24: Tamil Nadu | K24: English/Other | L24: https://doi.org/10.5281/zenodo.18222328 | M24: https://doi.org/10.5281/zenodo.18222328 | N24: 10.5281/zenodo.18222328 | O24: The Theni district of Tamil Nadu occupies a significant position in understanding the cultural developments of South India during the Iron Age and Early Historic periods. Archaeological evidence from this region, particularly burial monuments and habitation remains, indicates sustained human occupation from prehistoric times onward. Although earlier discoveries were reported during the colonial period and later surveys by scholars of the Archaeological Survey of India and Tamil University, focused and systematic investigation of Theni district remained limited. The present study addresses this | P24: OpenAlex | Q24: 2026-10-17
A25: 24 | B25: 2026 | C25: 2026-01-08 | D25: Archaeological Heritage of Tamil Nadu: Mahabalipuram | E25: Dr. A. Jesintha Vilveena | F25: Zenodo (CERN European Organization for Nuclear Research) | G25: தொல்லியல் | H25: Archaeology / Excavation | I25: archaeology, archaeological | J25: Tamil Nadu | K25: English/Other | L25: https://doi.org/10.5281/zenodo.18185250 | M25: https://doi.org/10.5281/zenodo.18185250 | N25: 10.5281/zenodo.18185250 | O25: Abstract Historians have two major avenues which they take to better understand the ancient world: archaeology and the study of source texts. Primary sources are those sources closest to the origin of the information or idea under study. Primary sources have been distinguished from secondary sources, which often cite, comment on, or build upon primary sources. Archaeological sites are merely the residues of settlements and structures, reduced to rubble and earthworks by decay, erosion, stone-robbing and the invasions of plant and animal life. Mahabalipuram is a monument complex on the Coromend | P25: OpenAlex | Q25: 2026-10-17
A26: 25 | B26: 2026 | C26: 2026-07-16 | D26: Architectural Historiography of the Airavatesvara Temple: Revisiting Chola Heritage through Epigraphic and Cultural Narratives | E26: K. Selva Kumar; S. Thangaraju | F26: International Journal of Arts Architecture & Design | G26: கல்வெட்டு, தொல்லியல் | H26: Inscription / Epigraphy, Archaeology / Excavation | I26: inscriptions, archaeological | K26: English/Other | L26: https://doi.org/10.62030/2026julypaper3 | M26: https://worlduniversityofdesign.ac.in/JAARD/wp-content/uploads/2026/07/3.-NEW-JAARD_-selva-kumar.docx.pdf | N26: 10.62030/2026julypaper3 | O26: The Airavatesvara Temple at Darasuram is widely regarded as one of the most refined creations of Later Chola architecture and sacred artistic imagination. Constructed during the reign of Rajaraja II in the twelfth century CE, the monument reflects the maturity of Chola artistic traditions and religious patronage. This article revisits the historiography of Chola temple heritage by closely examining the epigraphic, architectural, and cultural materials associated with Darasuram. Drawing extensively from the works of C. Sivaramamurti, S.R. Balasubrahmanyam, S.R. Krishnamurthi, and G.J.R. Mevisse | P26: OpenAlex | Q26: 2026-10-17
A27: 26 | B27: 2026 | C27: 2026-09-15 | D27: Beekeeping-Mediated Yield Enhancement and Monofloral Honey Production in Moringa (Moringa oleifera) Orchards | E27: Stephen Devanesan; Abraham Verghese; K. S. Premila; M. A. Rashmi | F27: Insect Environment | G27: தொல்லியல் | H27: Archaeology / Excavation | I27: korkai | J27: Tamil Nadu | K27: English/Other | L27: https://doi.org/10.55278/glii2516 | N27: 10.55278/glii2516 | O27: The drumstick tree (Moringa oleifera Lam.) is a nutrient-rich, entomophilous tree crop whose flowers depend heavily on insect visitation for fruit set, yet its association with managed honey bees has received little documented attention. This study reports on-farm observations from a moringa-growing belt in Korkai Manaloor, Eral, Tuticorin (Tamil Nadu), where migratory colonies of Apis cerana indica were introduced into orchards at approximately 5% flowering. Bee-assisted pollination increased fruit set by up to 30-fold on tagged branches, alongside marked gains in fruit size and weight, with | P27: OpenAlex | Q27: 2026-10-17
A28: 27 | B28: 2026 | C28: 2026-02-04 | D28: Boat Forms of Tamilnadu. | E28: B. Arunachalam | F28: Routledge eBooks | G28: தொல்லியல் | H28: Archaeology / Excavation | I28: archaeological, archaeological excavations | J28: Tamil Nadu | K28: English/Other | L28: https://doi.org/10.4324/9781003724094-18 | N28: 10.4324/9781003724094-18 | O28: It is difficult to estimate the age of the maritime, sea-faring traditions of the Tamil speaking people in the deep south of the Indian peninsula. Thor Heyrdahl who carried out archaeological excavations in the Maldive islands in the seventies of the twentieth century, is of the view that a distinctly hindu stratum of artifacts like the lingam and sun temples exist in the central group of islands, underlying the Buddhist stratum. The script characters appear to be old Damili/Brahmi. He is of the view that there was a definite sea-link and regular voyages between the Tamil coast, and later the | P28: OpenAlex | Q28: 2026-10-16
A29: 28 | B29: 2026 | C29: 2026-07-01 | D29: Communicative Practices and Societal Structures: Insights from Early Brahmi Inscriptions in Sri Lanka (3rd Century BCE–1st Century CE) | E29: J. D. A. Kumara | F29: KDU Journal of Multidisciplinary Studies | G29: கல்வெட்டு | H29: Inscription / Epigraphy | I29: inscriptions | J29: Sri Lanka | K29: English/Other | L29: https://doi.org/10.4038/kjms.v8i1.183 | M29: https://kjms.sljol.info/articles/183/files/6a6c3fed1c5cc.pdf | N29: 10.4038/kjms.v8i1.183 | O29: This study focuses on the communications found in early Brahmi inscriptions in Sri Lanka, shedding light on the social, cultural, economic, and religious practices of the period from the 3rd century BCE to the 1st century CE. The main data set for this study consists of 244 Early Brahmi inscriptions from the 3rd century BCE to the 1st century CE. Using the compilation of Nandasena Mudiyanse, the texts from the Mihintale inscriptions to the Madabavita inscriptions were analyzed to reveal the communicative practices of the period. The methodology used in this study is epigraphical analysis with | P29: OpenAlex | Q29: 2026-10-17
A30: 29 | B30: 2026 | C30: 2026-05-20 | D30: Context-Aware and Confidence-Guided Recognition of Ancient Tamil Stone Inscriptions using Multimodal Graph Learning | E30: Balasubramanian Murugan; P. Visalakshi | F30: International Conference on Intelligent Communication Technologies and Virtual Mobile Networks (ICICV) | G30: கல்வெட்டு | H30: Inscription / Epigraphy | I30: inscription, inscriptions | K30: English/Other | L30: https://doi.org/10.1109/icicv68925.2026.11554787 | N30: 10.1109/icicv68925.2026.11554787 | O30: The historic, cultural and linguistic information about the ancient Tamil people is abundant in the stone inscriptions of the antiquity however, the automatic identification of such inscriptions is hard because of the surface erosion, uneven carving and absence of text boundaries. The majority of the current inscription recognition systems are concerned with transcription accuracy without paying attention to the reliability and explainability of the obtained results, therefore, limiting their use in real-world epigraphic studies. As a solution to these problems, this paper introduces a context | P30: OpenAlex | Q30: 2026-10-16
A31: 30 | B31: 2026 | C31: 2026-10-11 | D31: Corpora & Datasets — Acquisition & Provenance Log | E31: Tristen Pierson | F31: OSF Preprints (OSF Preprints) | G31: கல்வெட்டு, தொல்லியல் | H31: Inscription / Epigraphy, Archaeology / Excavation | I31: inscription, inscriptions, epigraphy, kodumanal | J31: Tamil Nadu | K31: English/Other | L31: https://osf.io/dfrhz | M31: https://osf.io/dfrhz | O31: Acquisition and provenance log for the corpora and datasets the program works from (Phase-107 acquisition audit, 2026-10-05; canonical copy: reports/phase107_acquisition_log.json in glossa-lab). INGESTED (with provenance): - Holdat corpus — 1,670 seals / 7,002 tokens / 390 Mahadevan-numbered signs (public GitHub source recorded in CITATIONS.md A.13). - ICIT (Wells & Fuls, Interactive Corpus of Indus Texts) via the public Lipi export (field-cady MIT mirror) — 5,679 source inscriptions / 19,942 tokens; converted working layer 1,007 inscriptions / 2,238 tokens (Wells to Mahadevan numbering via th | P31: OpenAlex | Q31: 2026-10-17
A32: 31 | B32: 2026 | C32: 2026-01-01 | D32: Cultural Legacy of the Later Pandyas | E32: KUNDRAKUDI ADIGALAR PUBLICATIONS | F32: Figshare | G32: கல்வெட்டு | H32: Inscription / Epigraphy | I32: inscriptions | K32: English/Other | L32: https://doi.org/10.6084/m9.figshare.31828582 | M32: https://doi.org/10.6084/m9.figshare.31828582 | N32: 10.6084/m9.figshare.31828582 | O32: The Later Pandyas played an important role in shaping the culture, religion, and arts of the Tamil region, though their contributions are often overlooked. This book aims to highlight their significance through careful and responsible study. It explores key aspects of Pandya culture such as temple architecture, religion, art, literature, and education, based on inscriptions, literary sources, and modern historical research. | P32: OpenAlex | Q32: 2026-10-17
A33: 32 | B33: 2026 | C33: 2026-02-10 | D33: Decentralized Governance in Ancient India: Insights from Vedic Assemblies to Chola Inscriptions | E33: Santhosh Juvvaka | F33: Zenodo (CERN European Organization for Nuclear Research) | G33: கல்வெட்டு | H33: Inscription / Epigraphy | I33: inscriptions | K33: English/Other | L33: https://doi.org/10.5281/zenodo.19022625 | M33: https://doi.org/10.5281/zenodo.19022625 | N33: 10.5281/zenodo.19022625 | O33: The paper concludes that reconnecting modern decentralization reforms with these indigenous traditions can strengthen participatory democracy, enhance local accountability, promote ethical governance, and support culturally grounded approaches to sustainable development. By recovering this civilizational wisdom, India can enrich its grassroots democratic framework with deeper normative legitimacy. | P33: OpenAlex | Q33: 2026-10-17
A34: 33 | B34: 2026 | C34: 2026-06-26 | D34: Deciphering Indus Valley Civilisation Tablets and Seals through the Lens of Tamil Brahmi Script: Further Readings of 3 tablets | E34: Prabhakaran Karunakaran | F34: Zenodo (CERN European Organization for Nuclear Research) | G34: கல்வெட்டு, தொல்லியல் | H34: Inscription / Epigraphy, Archaeology / Excavation | I34: inscriptions, tamil-brahmi, tamil brahmi, copper plates, archaeological | K34: English/Other | L34: https://doi.org/10.5281/zenodo.20923773 | M34: https://doi.org/10.5281/zenodo.20923773 | N34: 10.5281/zenodo.20923773 | O34: Building directly upon Version 1 and Version II—which deciphered 10 and 5 tablets respectively—this paper expands the corpus by analyzing 3 additional Indus Valley inscriptions. Utilizing the identical Tamil-Brahmi methodology, this update brings the total number of deciphered tablets across the research series to 18. This research extends the syllabic framework established in Versions I and II, which decodes Indus Valley Civilisation inscriptions using the structural and phonetic values of the Tamil-Brahmi script. While earlier iterations successfully interpreted 15 distinct tablets, the curr | P34: OpenAlex | Q34: 2026-10-16
A35: 34 | B35: 2026 | C35: 2026-07-01 | D35: Decoding Ancient Sustainable Wall Construction: A Life Cycle Assessment of Materials at Keezhadi, Tamil Nadu | E35: Ezhil Murugan; M. Senthil | F35: International Conference on Applying New Technology in Green Buildings (ATiGB) | G35: தொல்லியல் | H35: Archaeology / Excavation | I35: keezhadi | J35: Tamil Nadu | K35: English/Other | L35: https://doi.org/10.1109/atigb70203.2026.11628442 | N35: 10.1109/atigb70203.2026.11628442 | P35: OpenAlex | Q35: 2026-10-17
A36: 35 | B36: 2026 | C36: 2026-01-01 | D36: Decorative patterns that emerge through pathupattu | E36: V.Mariselvi; Dr.A.Vijayalakshmi | F36: Zenodo (CERN European Organization for Nuclear Research) | G36: தொல்லியல் | H36: Archaeology / Excavation | I36: தொல்லியல் | K36: Tamil | L36: https://doi.org/10.5281/zenodo.18871049 | M36: https://doi.org/10.5281/zenodo.18871049 | N36: 10.5281/zenodo.18871049 | O36: பத்துப்பாட்டு ஒரு பண்பாட்டுச் சுரங்கமாகும். வீரயுக காலத்தின் நுனியில் வாழ்ந்து கொண்டிருந்த மக்களின் வாழ்வியலைப் பதிவு செய்துள்ளது. அவர்களது கலை, பண்பாடு, பொருளாதார நிலை, பழக்கவழக்கம் போன்றவற்றை வெளிப்படுத்துகிறது. நமது பண்பாட்டின் அலங்கார முறைகளை கோயில் சிற்பங்களும் தொல்லியல் ஆய்வுகளில் வெளிப்படும் அணிகலன்களும் காட்டுகின்றன. மகளிர் தம்மை அழகுபடுத்திக் கொள்ள செங்கழுநீர் இதழ்களைக் கொண்டு மாலை கட்டியுள்ளனர். பொன்னாலான அணிகலன்களை அணிந்துள்ளனர். கூந்தலுக்கு நறும்புகை ஊட்டியுள்ளனர். கத்தூரி, சந்தனம் போன்ற மணப்பொருள்களை அரைத்துப் பூசியுள்ளனர். மெல்லிய நூலால் செய்த புடவைகளுக்கு மணப்புகை ஊட்டியுள்ளனர். | P36: OpenAlex | Q36: 2026-10-17
A37: 36 | B37: 2026 | C37: 2026-01-01 | D37: Deep Search: An Approach Towards Tamil Character Recognition in Ancient Inscriptions | E37: R. Anand; M. Abhimanyu; A. Ashvinraja; S. Dinakar Raj Pandian | F37: Lecture notes in networks and systems | G37: கல்வெட்டு | H37: Inscription / Epigraphy | I37: inscriptions | K37: English/Other | L37: https://doi.org/10.1007/978-3-032-31097-2_3 | N37: 10.1007/978-3-032-31097-2_3 | P37: OpenAlex | Q37: 2026-10-16
A38: 37 | B38: 2026 | C38: 2026-01-12 | D38: Dolmens of Kodaikanal Hills: Uncovering Megalithic Traditions in Tamil Nadu with a Focus on Kodaikanal | E38: Dr. L.R. Charlet Sharmili | F38: Zenodo (CERN European Organization for Nuclear Research) | G38: தொல்லியல் | H38: Archaeology / Excavation | I38: megalithic | J38: Tamil Nadu | K38: English/Other | L38: https://doi.org/10.5281/zenodo.18222158 | M38: https://doi.org/10.5281/zenodo.18222158 | N38: 10.5281/zenodo.18222158 | O38: The dolmens in the Kodaikanal hills provide a remarkable insight into the burial practices, technological abilities, and spiritual beliefs of the Iron Age people who inhabited the region. According to R.M. Wheeler (1956) megaliths are “those monuments which are built on rough, large, undressed blocks of stones, usually though not invariably of rudimental character. These monuments are connected with burials, which fulfil funerary or commemorative or religious functions.” Megalithic monuments occur on surface at the foot of the hills and hillocks, unlike other underground pre- historic and prot | P38: OpenAlex | Q38: 2026-10-17
A39: 38 | B39: 2026 | C39: 2026-07-16 | D39: Economic Conditions and Development under the Nayak Rule in Tamil Nadu (A.D. 1529– 1736) | E39: Mr. Suresh. S; Dr. Augustin. J | F39: Journal of Asia Entrepreneurship and Sustainability | G39: கல்வெட்டு | H39: Inscription / Epigraphy | I39: inscriptions | J39: Tamil Nadu | K39: English/Other | L39: https://doi.org/10.66635/e5t5pk69 | M39: https://asiaentrepreneurshipjournal.com/index.php/jaes/article/download/466/341 | N39: 10.66635/e5t5pk69 | O39: The Nayak rule in Tamil Nadu marked a significant period in the socio-economic and political history of South India. Emerging from the decline of the Vijayanagara Empire after the Battle of Talikota (1565), the Nayaks established independent kingdoms in Madurai, Thanjavur, and Senji, laying the foundations for regional governance and economic development. Their administration emphasized agricultural expansion, irrigation, taxation, temple-centered economic organization, trade promotion, and decentralized governance through the Palaiyakkarar system. Economic prosperity was closely linked to eff | P39: OpenAlex | Q39: 2026-10-17
A40: 39 | B40: 2026 | C40: 2026-03-01 | D40: Enhancing Tamil Palm Leaf Manuscript Character Recognition via Real-ESRGAN and Deformable Vision Transformers | E40: C. Balaji; P. Lalitha | F40: International Conference on Intelligent Sustainable Systems (ICISS) | G40: கல்வெட்டு | H40: Inscription / Epigraphy | I40: epigraphy | K40: English/Other | L40: https://doi.org/10.1109/iciss67859.2026.11453914 | N40: 10.1109/iciss67859.2026.11453914 | O40: In ancient period in Tamil culture used to written in palm leaves like literature, medicine and philosophy after so many decades cause severe degradation—including ink fading, biological damage, and physical cracks—that affects effective optical character recognition (OCR). Traditional method to recognize the characters from palm leaves using OCR systems and deep learning techniques. In Tamil language contains Uyir letters (12), Meyi letters (18), Uyir Meyi letters (216) and ayutha letter (1). In degraded contexts, the real challenges in overlapping of characters, broken strokes and complex gl | P40: OpenAlex | Q40: 2026-10-16
A41: 40 | B41: 2026 | C41: 2026-02-01 | D41: Epigraphy, Patronage, and Institutional Continuity: The Namapureeswarar Temple of Alangudi (13th–18th Centuries CE) | E41: T. Rajathi; M Gayathri Devi | F41: International Journal of History | G41: கல்வெட்டு | H41: Inscription / Epigraphy | I41: inscription, inscriptions, epigraphy | J41: Tamil Nadu | K41: English/Other | L41: https://doi.org/10.22271/27069109.2026.v8.i2b.652 | M41: https://www.historyjournal.net/article/652/8-2-18-270.pdf | N41: 10.22271/27069109.2026.v8.i2b.652 | O41: Alangudi, situated in the present Pudukkottai district of Tamil Nadu, was known in earlier times as Kidarankonda Cholapuram. The Namapureeswarar temple located in this village stands as an important monument of the later Pandya period, both in terms of architecture and epigraphical heritage. The presiding deity of the temple is referred to as Namapureesvarar in Sanskrit and as Perudaiya Nayanar in Tamil inscriptions, reflecting the bilingual religious culture of medieval South India. The present study is based primarily on thirty stone inscriptions engraved on the walls of the temple. These re | P41: OpenAlex | Q41: 2026-10-16
A42: 41 | B42: 2026 | C42: 2026-03-18 | D42: Ethnography of Khosargudi in Tamil | E42: P, Velmurugan | F42: International Research Journal of Tamil | G42: தொல்லியல் | H42: Archaeology / Excavation | I42: archaeological | J42: Tamil Nadu | K42: English/Other | L42: https://irjt.iorpress.org/index.php/irjt/article/view/2506 | O42: The Moovendras excelled in trade and administration within their territory. Due to this myth, various ethnic groups entered Tamil Nadu. As a result, the foreigners waged various wars to suppress the ruling power of the Moovendras. Some of them migrated to Tamil Nadu in search of livelihood. The natives who came here initially led a simple life and later improved themselves on many levels. The arriving natives established themselves as the bravest of the brave. The literature shows that the monks used these relics to win their battles. It is also known that the leaders who emerged from these vi | P42: Journal: International Research Journal of Tamil | Q42: 2026-10-16
A43: 42 | B43: 2026 | C43: 2026-03-18 | D43: Ethnography of Khosargudi in Tamil | E43: Velmurugan P | F43: International Research Journal of Tamil | G43: தொல்லியல் | H43: Archaeology / Excavation | I43: archaeological | J43: Tamil Nadu | K43: English/Other | L43: https://irjt.iorpress.org/index.php/irjt/article/view/2506 | M43: https://irjt.iorpress.org/index.php/irjt/article/view/2506 | O43: The Moovendras excelled in trade and administration within their territory. Due to this myth, various ethnic groups entered Tamil Nadu. As a result, the foreigners waged various wars to suppress the ruling power of the Moovendras. Some of them migrated to Tamil Nadu in search of livelihood. The natives who came here initially led a simple life and later improved themselves on many levels. The arriving natives established themselves as the bravest of the brave. The literature shows that the monks used these relics to win their battles. It is also known that the leaders who emerged from these vi | P43: OpenAlex | Q43: 2026-10-17
A44: 43 | B44: 2026 | C44: 2026-07-01 | D44: Exploring the Cultural Tourism in Tamil Nadu: A Special Reference to Thoothukudi District | E44: S. Subramaniyan | F44: International Journal of Humanities and Arts | G44: தொல்லியல் | H44: Archaeology / Excavation | I44: archaeological | J44: Tamil Nadu | K44: English/Other | L44: https://doi.org/10.33545/26647699.2026.v8.i7a.422 | N44: 10.33545/26647699.2026.v8.i7a.422 | O44: The Cultural tourism sector of the tourism business is expanding at the highest rate, travellers are increasingly becoming specialised. The draw of adventure, culture, history, and archaeological sites, among other things, indicates a surge in tourists in any area. Particularly recently, and it is anticipated to continue, there has been an upsurge in the interest of tourists from abroad, including India. Cultural places, for instance, are among the most popular tourist destinations in Tamil Nadu, particularly in the Thoothukudi district. The investigation of the role that cultural sites have i | P44: OpenAlex | Q44: 2026-10-17
A45: 44 | B45: 2026 | C45: 2026-03-27 | D45: Fieldwork in Tamil Nadu, January-February 2026 | E45: Emmanuel Francis | F45: Industrias Culturais (Universidade de Coimbra) | G45: கல்வெட்டு | H45: Inscription / Epigraphy | I45: inscriptions | J45: Tamil Nadu, Puducherry | K45: English/Other | L45: https://dharma.hypotheses.org/7917 | M45: https://dharma.hypotheses.org/7917 | N45: 10.58079/15ypr | O45: --- A blogpost by Renato Dávalos --- In January and February, a fieldwork mission throughout Tamil Nadu was carried out by Renato Dávalos to locate, read in situ and document Tamil inscriptions related to the public recitation of devotional hymns and the stories of the Tamil Śaiva saints. Part of the fieldwork was carried out during workshops held in Pondicherry and Kanchipuram and involved several members from the DHARMA Project and from other projects. First phase – Revising transcrip... | P45: OpenAlex | Q45: 2026-10-16
A46: 45 | B46: 2026 | C46: 2026-08-01 | D46: From Colonial Vaults to National Heritage: A Legal, Historical, and Diplomatic Study on the Restitution of the Chola Leiden Copper Plates | E46: V Purushothaman | F46: International Journal of History | G46: கல்வெட்டு | H46: Inscription / Epigraphy | I46: copper plates | K46: English/Other | L46: https://doi.org/10.22271/27069109.2026.v8.i8b.866 | M46: https://www.historyjournal.net/article/866/8-8-34-798.pdf | N46: 10.22271/27069109.2026.v8.i8b.866 | O46: On 16 May 2026, the Dutch government formally handed over to India a set of 24 copper plates stored in the city of Leiden in the western Netherlands for the last three centuries. The handover ceremony was held in The Hague. But the Leiden Plates are much more: they were, over their 1,000-year history, conduits for the many entanglements of the Indian Ocean World. It is a story of Buddhism and Shaivism, imperialism and colonialism, and of warfare, famine, and cosmopolitanism. The handover was the result of years of diplomatic efforts by New Delhi. The Aannaimangalam plates, or Leiden plates, ar | P46: OpenAlex | Q46: 2026-10-17
A47: 46 | B47: 2026 | C47: 2026-04-18 | D47: Functional Extraction and Structural Continuity: The Selective Survival of Indus Administrative Frame Signs into the South Indian Megalithic Period (1900–600 BCE) | E47: Juan Gabriel Molina | F47: Zenodo (CERN European Organization for Nuclear Research) | G47: கல்வெட்டு, தொல்லியல் | H47: Inscription / Epigraphy, Archaeology / Excavation | I47: inscriptions, tamil-brahmi, tamil brahmi, megalithic, keezhadi, adichanallur | K47: English/Other | L47: https://doi.org/10.5281/zenodo.19645860 | M47: https://doi.org/10.5281/zenodo.19645860 | N47: 10.5281/zenodo.19645860 | O47: This deposit establishes intellectual priority over the following finding: the transition from the Indus Valley script to the South Indian Megalithic graffiti corpus (1900–600 BCE) was not random cultural drift but a Functional Extraction — the selective survival of the administrative frame layer (openers and closers) while the administrative content layer (medial signs) was completely discarded. Three independent statistical tests confirm this finding. Fisher's exact test on the sign survival contingency table yields p = 1.62 × 10⁻¹⁹, odds ratio 16.7 — high-lock signs (openers and closers) ar | P47: OpenAlex | Q47: 2026-10-16
A48: 47 | B48: 2026 | C48: 2026-01-01 | D48: Global and Local Feature Extraction Using Deep Learning Technique for Keyword Spotting in Ancient Tamil Inscriptions | E48: A. Vidhyavani; T. Manoranjitham | F48: International Research Journal of Multidisciplinary Scope | G48: கல்வெட்டு | H48: Inscription / Epigraphy | I48: inscription, inscriptions | K48: English/Other | L48: https://doi.org/10.47857/irjms.2026.v07i01.08737 | M48: https://doi.org/10.47857/irjms.2026.v07i01.08737 | N48: 10.47857/irjms.2026.v07i01.08737 | O48: Ancient Tamil scripts preserved in stone inscriptions represent valuable cultural, historical, and social heritage. However, extracting meaningful information from these inscriptions remains a challenging task due to severe degradation, erosion, noise, and complex character structures. Word spotting (WS) has emerged as an effective alternative to traditional optical character recognition (OCR) systems for information retrieval from such degraded documents. This paper proposes a hybrid deep learning framework for word spotting in ancient Tamil inscription images. The proposed system consists of | P48: OpenAlex | Q48: 2026-10-16
A49: 48 | B49: 2026 | C49: 2026-08-14 | D49: Graffiti, Script, and the Brahmi Question: | E49: anthony hettige pushpika indunil | F49: Figshare | G49: கல்வெட்டு, தொல்லியல் | H49: Inscription / Epigraphy, Archaeology / Excavation | I49: inscriptions, megalithic, kodumanal, porunthal | J49: Tamil Nadu | K49: English/Other | L49: https://doi.org/10.6084/m9.figshare.33260814 | M49: https://doi.org/10.6084/m9.figshare.33260814 | N49: 10.6084/m9.figshare.33260814 | O49: The origin of the Brahmi script remains unresolved among three competing hypotheses: derivation from a Semitic (most likely Aramaic) prototype under Mauryan patronage; derivation from the Indus Valley Civilization (IVC) script across a roughly millennium-long gap; and indigenous emergence from a South Indian megalithic graffiti tradition, as argued principally by K. Rajan on the basis of stratigraphic sequences at Kodumanal, Porunthal, Vallam, and Mangudi. This paper conducts a comparative evidentiary assessment of the second and third hypotheses, evaluating the IVC script corpus and the Tamil | P49: OpenAlex | Q49: 2026-10-16
A50: 49 | B50: 2026 | C50: 2026-01-15 | D50: Historical Evidences of the Sangam Age Reflected in Indian Literatures | E50: Shanlax Journals | F50: Shanlax International Journal of Arts Science and Humanities | G50: தொல்லியல் | H50: Archaeology / Excavation | I50: archaeological | K50: English/Other | L50: https://doi.org/10.5281/zenodo.18206140 | M50: https://doi.org/10.5281/zenodo.18206140 | N50: 10.5281/zenodo.18206140 | O50: The Sangam Age, dating roughly from 300 BCE to 300 CE, represents a formative phase in the history of South India and the wider Indian cultural world. The Tamil literary works of this period are not merely poetic compositions but important historical sources that provide insight into early political institutions, economic systems, social organization, and religious thought. This study examines how Sangam texts reflect historical realities and how their descriptions correspond with references found in Sanskrit epics, Puranic traditions, and Buddhist and Jain literatures. By comparing literary t | P50: OpenAlex | Q50: 2026-10-17
A51: 50 | B51: 2026 | C51: 2026-01-01 | D51: Historical Records from the Copper Plate Inscription of the Vadakal Palayakkarar: Based on the Evidence from the Tamil University Museum | E51: A Raja | F51: Shanlax International Journal of Tamil Research | G51: கல்வெட்டு | H51: Inscription / Epigraphy | I51: inscription, inscriptions, copper plate, copper plates, copper-plate | J51: Tamil Nadu | K51: English/Other | L51: https://doi.org/10.34293/tamil.v10i3.10034 | M51: https://doi.org/10.34293/tamil.v10i3.10034 | N51: 10.34293/tamil.v10i3.10034 | O51: Pottery shards with sripts, copper plates, stone inscriptions, palm-leaf manuscripts, and paper documents serve as evidentiary sources that narrate the ancient history of Tamil Nadu. Furthermore, these inscriptions serve as primary sources that describe the culture, administrative systems, social structures, and the donations and charities given to temples and society. In this context, this article discusses the historical information contained in the copper plate inscription from the period of the second Maratha king Sahaji, which was found in the Palayakkarar mansion at Vadakal in the Sirkaz | P51: OpenAlex | Q51: 2026-10-16
A52: 51 | B52: 2026 | C52: 2026-08-03 | D52: History and Heritage of Saivite Temples in the Kumbakonam Region | E52: M. Amirthavalli; A. Karkuzhali | F52: International Journal of Economic Practices and Theories | G52: கல்வெட்டு, தொல்லியல் | H52: Inscription / Epigraphy, Archaeology / Excavation | I52: inscriptions, archaeological | J52: Tamil Nadu | K52: English/Other | L52: https://doi.org/10.52783/ijept.836 | M52: https://ijapt.org/index.php/journal/article/download/836/669 | N52: 10.52783/ijept.836 | O52: The Kumbakonam region of Tamil Nadu is one of the most significant centres of Saivism in South India, renowned for its concentration of ancient temples that reflect the continuity of religious traditions, artistic excellence, and cultural heritage. The Saivite temples of this region, established and expanded under the patronage of the Cholas, Pandyas, Nayaks, and Marathas, serve as invaluable sources for understanding the historical, social, political, and economic development of Tamil society. These temples are distinguished by their remarkable Dravidian architecture, intricate sculptures, in | P52: OpenAlex | Q52: 2026-10-17
A53: 52 | B53: 2026 | C53: 2026-06-01 | D53: India’s first marine commandos: how the pallava ships won wars from Sri Lanka to Karnataka | E53: B Shrinivasan | F53: International Journal of History | G53: கல்வெட்டு, தொல்லியல் | H53: Inscription / Epigraphy, Archaeology / Excavation | I53: inscriptions, copper plates, archaeological | J53: Karnataka, Sri Lanka | K53: English/Other | L53: https://doi.org/10.22271/27069109.2026.v8.i6b.808 | M53: https://www.historyjournal.net/article/808/8-6-18-183.pdf | N53: 10.22271/27069109.2026.v8.i6b.808 | O53: This article examines the naval warfare strategy of the Pallava Dynasty, positioning them as pioneers of organized maritime military operations in South India. Drawing on archaeological evidence from Mamallapuram port, numismatic data of ship-motif Pallava coins, and epigraphic sources including the Kuram Copper Plates and Kasakudi Plates, the study reconstructs Pallava naval campaigns under Narasimhavarman I (630–668 CE). Key findings indicate that the Pallavas deployed coordinated sea-borne forces to intervene in Sri Lankan succession wars and to capture the Chalukya capital of Vatapi in 642 | P53: OpenAlex | Q53: 2026-10-17
A54: 53 | B54: 2026 | C54: 2026-01-01 | D54: Inheritance, Consent, and Ownership: Women’s Role in Land Transactions in 13th Century Tamil Nadu | E54: Dr. RamadeviSekhar | F54: article | G54: கல்வெட்டு | H54: Inscription / Epigraphy | I54: inscription | J54: Tamil Nadu | K54: English/Other | L54: https://doi.org/10.54646/kej.2026.09 | M54: https://doi.org/10.54646/kej.2026.09 | N54: 10.54646/kej.2026.09 | O54: This study examines a thirteenth-century Tamil inscription discovered at the Tillai Kali Amman temple in Chidambaram, issued during the third regnal year of the Pallava chief Kopperunjinga. The record documents a land sale undertaken by a Brahmin household and provides valuable evidence regarding inheritance practices and legal conventions of the time, particularly in relation to women’s property rights. The inscription enumerates seven members of the family, including three women, who are all identified as legitimate co owners of the property. While male representatives appear to have acted o | P54: OpenAlex | Q54: 2026-10-16
A55: 54 | B55: 2026 | C55: 2026-06-30 | D55: Inscriptions and Institutions: Tamil Script History and Temple Governance in Andhra Pradesh | E55: Keerthigan Krsnan Gopikrishnan | F55: article | G55: கல்வெட்டு | H55: Inscription / Epigraphy | I55: inscriptions | J55: Andhra / Telangana | K55: English/Other | L55: https://doi.org/10.13140/rg.2.2.11747.92960 | M55: https://doi.org/10.13140/rg.2.2.11747.92960 | N55: 10.13140/rg.2.2.11747.92960 | P55: OpenAlex | Q55: 2026-10-16
A56: 55 | B56: 2026 | C56: 2026-01-01 | D56: Invocation to Goddess in Tamil Literature | E56: N. Ashadevi | F56: Shanlax International Journal of Arts Science and Humanities | G56: தொல்லியல் | H56: Archaeology / Excavation | I56: archaeological | K56: English/Other | L56: https://doi.org/10.34293/sijash.v13i3.9806 | M56: https://shanlaxjournals.in/journals/index.php/sijash/article/download/9806/8408 | N56: 10.34293/sijash.v13i3.9806 | O56: The Mother Goddess occupies a central position in the Hindu religious system and is revered as Sakti, the primordial source of energy without which male deities are considered powerless. This study examines the evolution and significance of Mother Goddess worship in Tamil literary traditions from ancient to modern times. The objective of the paper is to analyse how Goddess worship—particularly in the forms of Kotravai, Kali, Kollipavai, Mariyamman, and Meenakshi—is represented in classical Tamil texts and epics.Methodologically, the study adopts a historical and textual analysis, drawing upon | P56: OpenAlex | Q56: 2026-10-17
A57: 56 | B57: 2026 | C57: 2026-03-26 | D57: Kalveetu AI: Deep Learning-Based Ancient Tamil Inscription Recognition | E57: Dr. K. S. Ramanujam; Dr. R. Shobarani; Dr. F. Jerald; Bharathwaaj G; Deepak P; Dinesh S | F57: Zenodo (CERN European Organization for Nuclear Research) | G57: கல்வெட்டு | H57: Inscription / Epigraphy | I57: inscription, inscriptions | K57: English/Other | L57: https://doi.org/10.5281/zenodo.19229892 | M57: https://doi.org/10.5281/zenodo.19229892 | N57: 10.5281/zenodo.19229892 | O57: Ancient stone inscriptions serve as high critical historical artifacts, yet their interpretation is affected by script degradation, stylistic variations, and the unavailability of labeled data. This paper presents Kalveetu AI, a deep learning– based system designed to translate ancient Tamil inscription characters into their modern characters. A Convolutional Neural Network (CNN) is used for singlecharacter classification. To solve the challenge of data scarcity, where only one image per ancient character available where normal augmentation process couldn't satisfy the CNN model data requireme | P57: OpenAlex | Q57: 2026-10-16
A58: 57 | B58: 2026 | C58: 2026-05-25 | D58: Keezhadi Tamil Mapping — E8 Intelligence Research | E58: Andrew Stewart Caldin | F58: Zenodo (CERN European Organization for Nuclear Research) | G58: தொல்லியல் | H58: Archaeology / Excavation | I58: keezhadi | K58: English/Other | L58: https://doi.org/10.5281/zenodo.20375610 | M58: https://doi.org/10.5281/zenodo.20375610 | N58: 10.5281/zenodo.20375610 | O58: 94% entropy reduction, Indus to Tamil. Author: Andrew Stewart Caldin, Independent Researcher, UK. Part of the E8 Intelligence Research series. Platform: e8intelligence.com | P58: OpenAlex | Q58: 2026-10-17
A59: 58 | B59: 2026 | C59: 2026-01-01 | D59: Knowledge and Its Transmission in Ancient Tamilnadu | E59: Dr. R. Sumesh | F59: International Journal of Research and Innovation in Social Science | G59: கல்வெட்டு | H59: Inscription / Epigraphy | I59: inscriptions | J59: Tamil Nadu | K59: English/Other | L59: https://doi.org/10.47772/ijriss.2026.100900426 | M59: https://rsisinternational.org/journals/ijriss/uploads/vol10-iss9-pg6337-6339-202610_pdf.pdf | N59: 10.47772/ijriss.2026.100900426 | O59: Ancient Tamil Nadu possessed a highly advanced and indigenous system of knowledge production and transmission long before formal institutionalization of education. This paper examines the nature of knowledge (Arivu) and its transmission mechanisms in ancient Tamil society from the Sangam Age (c. 300 BCE - 300 CE) to the later Chola period (c. 9th-13th century CE). Drawing upon primary sources such as Tolkappiyam, Sangam literature (Ettuthokai and Pathupattu), Thirukkural, Silappathikaram, and epigraphical evidence of Chola inscriptions, the study analyzes the typology of knowledge, the agents | P59: OpenAlex | Q59: 2026-10-17
A60: 59 | B60: 2026 | C60: 2026-07-07 | D60: Localizing Heritage: Archaeologies of the Recent Past in Postwar Jaffna, Sri Lanka | E60: Gill Juleff; Thamotharampillai Sanathanan; Ruth Young; John P. Cooper; Emma Dwyer; Adrián Oyaneder | F60: Historical Archaeology | G60: தொல்லியல் | H60: Archaeology / Excavation | I60: archaeology | J60: Sri Lanka | K60: English/Other | L60: https://doi.org/10.1007/s41636-026-00636-0 | M60: https://link.springer.com/content/pdf/10.1007/s41636-026-00636-0.pdf | N60: 10.1007/s41636-026-00636-0 | O60: Abstract The role of archaeology in divisive nationalism, colonial supremacism, and the marginalization of subaltern groups is increasingly evident globally. Such legacies are visible in Sri Lanka, not least in its north and east, where many regard archaeology as either irrelevant or as a weapon directed against them. We outline the genesis of a UK-Sri Lankan project that responds to this situation and focus on a workshop held in Jaffna with University of Jaffna partners that tested the potential for archaeology and heritage to foster affirmation of identity and sense of place in communities r | P60: OpenAlex | Q60: 2026-10-17
A61: 60 | B61: 2026 | C61: 2026-06-16 | D61: Maritime Power, Commerce, and Temple Networks in the Chola Naval Expansion, 900-1200 CE | E61: Ajeeshkumar T B | F61: International Journal of History and Archaeology Research Studies (IJHARS) | G61: கல்வெட்டு, தொல்லியல் | H61: Inscription / Epigraphy, Archaeology / Excavation | I61: inscriptions, copper plate, copper-plate, archaeological | K61: English/Other | L61: https://doi.org/10.5281/zenodo.20825948 | M61: https://doi.org/10.5281/zenodo.20825948 | N61: 10.5281/zenodo.20825948 | O61: This article examines the relationship between naval power, long-distance commerce, and temple institutional networks in the overseas expansion of the imperial Chola dynasty between the reign of Rajaraja I (r. 985-1014) and the decline of Chola maritime dominance in the late twelfth century. Drawing on Tamil copper-plate inscriptions, the Tanjore temple records, Chinese Song dynasty annals, and the archaeological evidence from port sites across the Bay of Bengal littoral, as well as the analytical frameworks developed by K. A. Nilakanta Sastri, Kenneth Hall, and Hermann Kulke, the study argues | P61: OpenAlex | Q61: 2026-10-17
A62: 61 | B62: 2026 | C62: 2026-06-16 | D62: Maritime Power, Commerce, and Temple Networks in the Chola Naval Expansion, 900-1200 CE | E62: Ajeeshkumar T B | F62: International Journal of History and Archaeology Research Studies (IJHARS) | G62: கல்வெட்டு, தொல்லியல் | H62: Inscription / Epigraphy, Archaeology / Excavation | I62: inscriptions, copper plate, copper-plate, archaeological | K62: English/Other | L62: https://doi.org/10.63090/ijhars/3049.1622.0034 | M62: https://doi.org/10.63090/ijhars/3049.1622.0034 | N62: 10.63090/ijhars/3049.1622.0034 | O62: This article examines the relationship between naval power, long-distance commerce, and temple institutional networks in the overseas expansion of the imperial Chola dynasty between the reign of Rajaraja I (r. 985-1014) and the decline of Chola maritime dominance in the late twelfth century. Drawing on Tamil copper-plate inscriptions, the Tanjore temple records, Chinese Song dynasty annals, and the archaeological evidence from port sites across the Bay of Bengal littoral, as well as the analytical frameworks developed by K. A. Nilakanta Sastri, Kenneth Hall, and Hermann Kulke, the study argues | P62: OpenAlex | Q62: 2026-10-17
A63: 62 | B63: 2026 | C63: 2026-09-13 | D63: Maritime Trade and Foreign Relations of Ancient Tamil Nadu in Sangam Literature – A Historical Study. | E63: P., Manjusri,; Prof. S., Boopalan, | F63: Zenodo (CERN European Organization for Nuclear Research) | G63: தொல்லியல் | H63: Archaeology / Excavation | I63: archaeological, archaeological excavations, kodumanal, alagankulam, korkai, arikamedu | J63: Tamil Nadu, Puducherry | K63: English/Other | L63: https://doi.org/10.5281/zenodo.22734041 | M63: https://doi.org/10.5281/zenodo.22734041 | N63: 10.5281/zenodo.22734041 | O63: The research paper titled "Maritime Trade and Foreign Relations of Ancient Tamil Nadu in Sangam Literature: A Historical Study" (சங்க இலக்கியங்களில் பண்டைத் தமிழகத்தின் கடல்சார் வணிகமும் அயல்நாட்டு உறவுகளும் – ஓர் வரலாற்று ஆய்வு) by Scholar Pa. Manjushri and Prof. Sa. Boobalan evaluates the complex maritime network, subaltern economics, and cross-cultural trade routes of ancient Tamil Nadu. Utilizing core Sangam texts like Pattinapalai, Perumpanatrupadai, Akananuru, Natrinai, and Nedunalvadai, the study deconstructs the ocean as a vital space for economic exchange rather than a simple geograph | P63: OpenAlex | Q63: 2026-10-17
A64: 63 | B64: 2026 | C64: 2026-05-10 | D64: Maritime Trade in Ancient Tamilakam: Archaeological Evidence from the Sangam Age Indo-Roman Commerce | E64: Sujamol Joseph | F64: International Journal of Arts Science Humanities Research Studies (IJASHRS) | G64: கல்வெட்டு, தொல்லியல் | H64: Inscription / Epigraphy, Archaeology / Excavation | I64: inscriptions, tamil-brahmi, tamil brahmi, archaeological, alagankulam, korkai, arikamedu, pattanam | J64: Puducherry, Kerala | K64: English/Other | L64: https://doi.org/10.63090/ijashrs/3139.8944.0013 | M64: https://doi.org/10.63090/ijashrs/3139.8944.0013 | N64: 10.63090/ijashrs/3139.8944.0013 | O64: Ancient Tamilakam, the southernmost peninsular region of the Indian subcontinent during the Sangam Age, occupied a strategic position in the maritime trade networks linking the Mediterranean world, the Red Sea, the Persian Gulf, the eastern coast of Africa, and Southeast Asia. Archaeological investigations over the past century, supplemented by literary and epigraphic evidence from Tamil Sangam poetry, Greco-Roman geographical texts, and Tamil-Brahmi inscriptions, have produced a rich understanding of the Indo-Roman commerce that flourished during the early centuries of the Common Era. This ar | P64: OpenAlex | Q64: 2026-10-16
A65: 64 | B65: 2026 | C65: 2026-01-01 | D65: Measurement systems in Chola Inscriptions (A study based on Eastern Province) | E65: Chrisdina Nirojini Mosasrupan; Gowry Luxmykanthan | F65: article | G65: கல்வெட்டு | H65: Inscription / Epigraphy | I65: inscriptions | K65: English/Other | L65: https://doi.org/10.13140/rg.2.2.16521.81769 | M65: https://doi.org/10.13140/rg.2.2.16521.81769 | N65: 10.13140/rg.2.2.16521.81769 | P65: OpenAlex | Q65: 2026-10-17
A66: 65 | B66: 2026 | C66: 2026-01-25 | D66: Megalithic Culture in Thagadur (Dharmapuri Region) | E66: Shanlax | F66: Shanlax International Journal of Arts Science and Humanities | G66: தொல்லியல் | H66: Archaeology / Excavation | I66: archaeological, megalithic | J66: Tamil Nadu | K66: English/Other | L66: https://doi.org/10.5281/zenodo.18981593 | M66: https://doi.org/10.5281/zenodo.18981593 | N66: 10.5281/zenodo.18981593 | O66: The Thagadur region, corresponding to the present-day Dharmapuri district of Tamil Nadu, represents one of the most significant centres of megalithic culture in South India. Archaeological explorations and excavations conducted in this region have revealed a wide range of megalithic burial monuments, including stone circles, cist burials, dolmens, urn burials, menhirs, and sarcophagi. These monuments, primarily associated with the Iron Age, reflect complex funerary practices, technological advancement in iron usage, and deeply rooted belief systems concerning death and the afterlife. This pape | P66: OpenAlex | Q66: 2026-10-17
A67: 66 | B67: 2026 | C67: 2026-03-10 | D67: Monuments and Archaeological Sites in Krishnagiri District, Tamil Nadu: An Archaeological and Historical Study | E67: Dr. R. Sthanislas V. Muniammal | F67: Zenodo (CERN European Organization for Nuclear Research) | G67: தொல்லியல் | H67: Archaeology / Excavation | I67: archaeological | J67: Tamil Nadu | K67: English/Other | L67: https://doi.org/10.5281/zenodo.18871743 | M67: https://doi.org/10.5281/zenodo.18871743 | N67: 10.5281/zenodo.18871743 | P67: OpenAlex | Q67: 2026-10-17
A68: 67 | B68: 2026 | C68: 2026-01-15 | D68: Muziris and the Global Networks of the Sangam Age: Reassessing Indo-Roman Trade Dynamics | E68: Shanlax Journals | F68: Shanlax International Journal of Arts Science and Humanities | G68: தொல்லியல் | H68: Archaeology / Excavation | I68: archaeological, archaeological excavations, pattanam | J68: Kerala | K68: English/Other | L68: https://doi.org/10.5281/zenodo.18206100 | M68: https://doi.org/10.5281/zenodo.18206100 | N68: 10.5281/zenodo.18206100 | O68: The port of Muziris occupies a distinguished position in the economic and cultural history of early Tamilakam. Functioning as a significant node in Indo-Roman commerce, Muziris facilitated the movement of spices, precious stones, luxury goods, and cultural knowledge across vast maritime networks. This paper reassesses Indo-Roman trade through a multidisciplinary lens, integrating Sangam literary records, Greco-Roman geographical accounts, recent archaeological excavations at Pattanam, and numismatic evidence. It argues that Muziris was not a passive recipient of Mediterranean commercial activi | P68: OpenAlex | Q68: 2026-10-17
A69: 68 | B69: 2026 | C69: 2026-03-01 | D69: Nagarathars: An in-depth examination of a medieval trading group in Chettinadu | E69: AR. Saravanakumar | F69: International Journal of History | G69: கல்வெட்டு, தொல்லியல் | H69: Inscription / Epigraphy, Archaeology / Excavation | I69: inscription, inscriptions, archaeological | J69: Tamil Nadu | K69: English/Other | L69: https://doi.org/10.22271/27069109.2026.v8.i3a.680 | M69: https://www.historyjournal.net/article/680/8-3-21-770.pdf | N69: 10.22271/27069109.2026.v8.i3a.680 | O69: In the context of medieval Chola inscriptions, the abstract covers the "Nagarathars," a business community also known as "Nattukottai Chettiars."The Nagarathars family was renowned for their involvement in banking, lending, and business.They founded a business association and a renowned business community by being actively involved in Tamil social and religious events.The inscriptions also mention their contribution to many temples, as well as their involvement in land transactions.The inscriptions provide a glimpse into the humanitarian activities of the Nagarathars, which include donations, | P69: OpenAlex | Q69: 2026-10-17
A70: 69 | B70: 2026 | C70: 2026-02-01 | D70: Nagaraththar and Narthamalai: A study | E70: M Jeyapathi; M Gayathri Devi | F70: International Journal of History | G70: கல்வெட்டு | H70: Inscription / Epigraphy | I70: inscriptions | J70: Tamil Nadu, Karnataka | K70: English/Other | L70: https://doi.org/10.22271/27069109.2026.v8.i2a.640 | M70: https://www.historyjournal.net/article/640/8-1-32-891.pdf | N70: 10.22271/27069109.2026.v8.i2a.640 | O70: Narthamalai, located in the Pudukkottai region of Tamil Nadu, occupies an important place in the commercial and institutional history of early medieval South India. Epigraphical evidence reveals that this hilly complex functioned as a significant mercantile centre closely associated with the Nagaraththar community from the early Chola period onwards. The present study examines the emergence of Narthamalai as a nagaram a merchant settlement with administrative authority and traces the role of Nagaraththars in shaping its economic, religious, and social landscape. Drawing primarily on inscriptio | P70: OpenAlex | Q70: 2026-10-17
A71: 70 | B71: 2026 | C71: 2026-01-12 | D71: Neolithic Excavations in Tamil Nadu | E71: Dr. Mrs. V. Sheeja | F71: Zenodo (CERN European Organization for Nuclear Research) | G71: தொல்லியல் | H71: Archaeology / Excavation | I71: archaeology, archaeological, kodumanal | J71: Tamil Nadu | K71: English/Other | L71: https://doi.org/10.5281/zenodo.18223728 | M71: https://doi.org/10.5281/zenodo.18223728 | N71: 10.5281/zenodo.18223728 | O71: The Neolithic Age marks a crucial shift in human history, with advancements in agriculture, animal domestication, and tool-making. Tamil Nadu's rich archaeological sites, such as Athirampakkam, Payyampalli, and Kodumanal, offer valuable insights into this transformative period. This study examines recent excavations of Neolithic stone tools and settlements, focusing on tool typology, material composition, and technological evolution. A multidisciplinary approach, incorporating archaeology, geology, and paleoenvironmental studies, helps understand the socio-economic and cultural practices of Ne | P71: OpenAlex | Q71: 2026-10-17
A72: 71 | B72: 2026 | C72: 2026-04-20 | D72: Optimizing deep ensemble learning for ancient Tamil inscription character recognition via metaheuristic weighting | E72: A A Aswathy; P. Uma Maheswari | F72: Discover Artificial Intelligence | G72: கல்வெட்டு | H72: Inscription / Epigraphy | I72: inscription, inscriptions | K72: English/Other | L72: https://doi.org/10.1007/s44163-026-01215-1 | M72: https://doi.org/10.1007/s44163-026-01215-1 | N72: 10.1007/s44163-026-01215-1 | O72: Abstract Character recognition in ancient Tamil inscriptions poses significant challenges due to variations in writing styles, high inter-class similarity, and the complexity of compound characters. This study proposes a novel Weighted Average Deep Ensemble Learning model optimized using the Cuckoo Search Optimization algorithm (Meta-WADE) to address these issues. The model integrates three Deep Convolutional Neural Networks (DCNNs) and two transfer learning models, with their weights optimized via CSO to enhance performance. Extensive experiments on a large dataset of ancient Tamil characters | P72: OpenAlex | Q72: 2026-10-16
A73: 72 | B73: 2026 | C73: 2026-03-06 | D73: Poornimathi-k/Tamil-Inscription: Robust Recognition of Tamil Inscription Letters Using a Hybrid Model Combining Recurrent Neural Networks, Graph Neural Networks, and Attention Mechanisms | E73: Poornimathi-k | F73: Zenodo (CERN European Organization for Nuclear Research) | G73: கல்வெட்டு | H73: Inscription / Epigraphy | I73: inscription | K73: English/Other | L73: https://doi.org/10.5281/zenodo.18888996 | M73: https://doi.org/10.5281/zenodo.18888996 | N73: 10.5281/zenodo.18888996 | O73: This release contains the implementation of the hybrid deep learning model proposed for recognizing ancient Tamil inscription letters and mapping them to modern Tamil characters.The framework combines Convolutional Neural Networks (CNN), Graph Neural Networks (GNN), Recurrent Neural Networks (RNN), and Attention mechanisms to improve recognition accuracy for degraded inscription images.The repository includes the code for preprocessing, segmentation, feature extraction, and character recognition used in the research study titled:"Robust Recognition of Tamil Inscription Letters Using a Hybrid M | P73: OpenAlex | Q73: 2026-10-16
A74: 73 | B74: 2026 | C74: 2026-05-03 | D74: Pottery Art in Tamil Literature | E74: N, Amirthakodi | F74: International Research Journal of Tamil | G74: கல்வெட்டு, தொல்லியல் | H74: Inscription / Epigraphy, Archaeology / Excavation | I74: inscriptions, graffiti marks, archaeological, archaeological excavations, keeladi, adichanallur, kodumanal, arikamedu | J74: Puducherry | K74: English/Other | L74: https://irjt.iorpress.org/index.php/irjt/article/view/2533 | O74: The Sangam Age (c. 3rd century BCE to 3rd century CE) is widely regarded as a golden period that reflects the richness of Tamil society in terms of art, culture, and economic prosperity. During this era, pottery emerged as a significant craft and an integral component of everyday life. This research article examines the various dimensions of pottery art during the Sangam period by drawing upon evidence from archaeological excavations and references found in Sangam literature. Particular attention is given to the pottery unearthed at archaeological sites such as Adichanallur, Arikamedu, Koduman | P74: Journal: International Research Journal of Tamil | Q74: 2026-10-16
A75: 74 | B75: 2026 | C75: 2026-05-03 | D75: Pottery Art in Tamil Literature | E75: Amirthakodi N | F75: International Research Journal of Tamil | G75: கல்வெட்டு, தொல்லியல் | H75: Inscription / Epigraphy, Archaeology / Excavation | I75: inscriptions, graffiti marks, archaeological, archaeological excavations, keeladi, adichanallur, kodumanal, arikamedu | J75: Puducherry | K75: English/Other | L75: https://irjt.iorpress.org/index.php/irjt/article/view/2533 | M75: https://irjt.iorpress.org/index.php/irjt/article/view/2533 | O75: The Sangam Age (c. 3rd century BCE to 3rd century CE) is widely regarded as a golden period that reflects the richness of Tamil society in terms of art, culture, and economic prosperity. During this era, pottery emerged as a significant craft and an integral component of everyday life. This research article examines the various dimensions of pottery art during the Sangam period by drawing upon evidence from archaeological excavations and references found in Sangam literature. Particular attention is given to the pottery unearthed at archaeological sites such as Adichanallur, Arikamedu, Koduman | P75: OpenAlex | Q75: 2026-10-17
A76: 75 | B76: 2026 | C76: 2026-04-19 | D76: Proto-Dravidian as the Spoken Language of the Mature Harappan Civilization: A Five-Domain Convergence Analysis | E76: Juan Gabriel Molina | F76: Zenodo (CERN European Organization for Nuclear Research) | G76: கல்வெட்டு, தொல்லியல் | H76: Inscription / Epigraphy, Archaeology / Excavation | I76: inscriptions, tamil-brahmi, tamil brahmi, graffiti marks, keeladi, keezhadi, tnsda | K76: English/Other | L76: https://doi.org/10.5281/zenodo.19655727 | M76: https://doi.org/10.5281/zenodo.19655727 | N76: 10.5281/zenodo.19655727 | O76: This deposit establishes intellectual priority over the following finding: across five independent lines of evidence — structural, phonetic, metrological, biological, and archaeobotanical — Proto-Dravidian is the most parsimonious explanation for the spoken language of the Mature Harappan civilization (2600-1900 BCE). No alternative hypothesis — Indo-Aryan, Munda, or language isolate — produces consistent evidence across all five domains simultaneously. The structural foundation is established in Molina (2026e), FMX-IVT-2026-PUB: administrative frame signs survived the Harappan collapse select | P76: OpenAlex | Q76: 2026-10-17
A77: 76 | B77: 2026 | C77: 2026-05-13 | D77: Rajendra Chola I (1012–1044 ce ) in South India | E77: Amit Jha | F77: Indian Historical Review | G77: கல்வெட்டு | H77: Inscription / Epigraphy | I77: inscriptions | J77: China | K77: English/Other | L77: https://doi.org/10.1177/03769836261448402 | N77: 10.1177/03769836261448402 | O77: In South India, the Imperial Cholas reigned between 985 and 1044 ce . Raja Raja Chola I (r. 985–1014 ce ) is widely celebrated as a symbol of Tamil pride. However, his son and successor, Rajendra Chola I (r. 1012–1044 ce ), is not accorded equal recognition. Notably, it was Rajendra—not Raja Raja—who dispatched two trade missions to China, strengthening maritime diplomacy. Rajendra is often criticised for his military aggression, particularly the Sri Vijayan expedition. Yet this campaign was largely aimed at protecting Chola’s commercial interests and securing maritime trade routes to China. L | P77: OpenAlex | Q77: 2026-10-17
A78: 77 | B78: 2026 | C78: 2026-07-14 | D78: Reading Stones: Architecture As Social History in Ancient India | E78: Dr. Nutan S. Desai | F78: Zenodo (CERN European Organization for Nuclear Research) | G78: கல்வெட்டு, நடுகல் | H78: Inscription / Epigraphy, Hero stone / Memorial stone | I78: inscriptions, hero stones | J78: Tamil Nadu | K78: English/Other | L78: https://doi.org/10.5281/zenodo.21350774 | M78: https://doi.org/10.5281/zenodo.21350774 | N78: 10.5281/zenodo.21350774 | O78: For a long time, people studying ancient Indian buildings have mainly looked at the art and symbols in temples and stupas. This is important for learning about art and religion, but it has hidden the bigger story of how ordinary people lived. This paper says that buildings are not just old objects. They are real clues that can help us understand the social life of ancient India. If we stop looking only at big temples and palaces and instead look at simple homes, markets, and streets, we can learn a lot. We can see who was rich and who was poor, how people worked and traded, how different relig | P78: OpenAlex | Q78: 2026-10-17
A79: 78 | B79: 2026 | C79: 2026-01-08 | D79: Recapping the Archaeological Excavations at Korkai: An Important Port City of the Sangam Pandyas | E79: G. Pushpa Rani | F79: Zenodo (CERN European Organization for Nuclear Research) | G79: தொல்லியல் | H79: Archaeology / Excavation | I79: archaeological, archaeological excavation, archaeological excavations, adichanallur, korkai | K79: English/Other | L79: https://doi.org/10.5281/zenodo.18185643 | M79: https://doi.org/10.5281/zenodo.18185643 | N79: 10.5281/zenodo.18185643 | O79: South India has a long history and rich cultural heritage, yet till the arrival of the Britishers in South India, the people have no idea about the glory of their past and the achievements of their predecessors. After the coming of the Britishers, they realized the glorious past of the South Indians and through archaeological excavations they started to bring the hidden past to light. For instance, the first archaeological excavation was held at Pallavaram near Chennai by a British Geologist named Robert Bruce Foote in 1863. It confirmed the existence of the Palaeolithic settlements in South I | P79: OpenAlex | Q79: 2026-10-17
A80: 79 | B80: 2026 | C80: 2026-01-12 | D80: Recent Excavations in Tamil Nadu: A Glimpse of Ancient Heritage | E80: Dr. Mrs. M. Tamilselvi | F80: Zenodo (CERN European Organization for Nuclear Research) | G80: கல்வெட்டு, தொல்லியல் | H80: Inscription / Epigraphy, Archaeology / Excavation | I80: inscribed, archaeological, archaeological excavations, keeladi | J80: Tamil Nadu | K80: English/Other | L80: https://doi.org/10.5281/zenodo.18222673 | M80: https://doi.org/10.5281/zenodo.18222673 | N80: 10.5281/zenodo.18222673 | O80: This research paper examines recent archaeological excavations in Tamil Nadu, focusing on the Pattaraiperumbudur and Keeladi sites, which provide significant insights into the region's ancient history and culture. Pattaraiperumbudur, located along the Korttalaiyar River in Thiruvallur District, has revealed evidence of continuous human habitation dating back about 500,000 years. Excavations have uncovered terracotta ring wells, microlithic tools, and pottery, highlighting early human settlement, advanced water management, and technological innovations. The Keeladi excavation, on the banks of t | P80: OpenAlex | Q80: 2026-10-17
A81: 80 | B81: 2026 | C81: 2026-08-10 | D81: Robust recognition of Tamil inscription letters using a hybrid model combining recurrent neural networks, graph neural networks, and attention mechanisms | E81: K. Poornimathi; V. Muralibhaskaran | F81: PeerJ Computer Science | G81: கல்வெட்டு | H81: Inscription / Epigraphy | I81: inscription, inscriptions | K81: English/Other | L81: https://doi.org/10.7717/peerj-cs.3993 | M81: https://peerj.com/articles/cs-3993.pdf | N81: 10.7717/peerj-cs.3993 | O81: Background Character recognition in ancient Tamil inscriptions is a difficult process because of the complex nature, overlapping, and varied sizes of the characters. Traditional Optical Character Recognition (OCR) methods cannot perform optimally in such situations, making it important to develop an efficient character recognition system. Methodology The proposed system is named CUGRA, which represents the integration of five models, namely, Canny, U-Net, Graph Neural Networks (GNN), Recurrent Neural Networks (RNN), and attention models. Its application for Tamil inscription recognition is ref | P81: OpenAlex | Q81: 2026-10-16
A82: 81 | B82: 2026 | C82: 2026-04-01 | D82: SHILPASMRITI: DIGITAL PRESERVATION OF ANCIENT TEMPLES | E82: ADIVI SRI LAKSHMI SREEYA; BHAGAVATHULA SIVADHATRI; D. Thamaraiselvi | F82: JOURNAL OF ADVANCE AND FUTURE RESEARCH | G82: கல்வெட்டு | H82: Inscription / Epigraphy | I82: inscription, inscriptions, tamil-brahmi, tamil brahmi | K82: English/Other | L82: https://doi.org/10.56975/jaafr.v4i4.507960 | M82: https://rjwave.org/jaafr/papers/JAAFR26A4043.pdf | N82: 10.56975/jaafr.v4i4.507960 | O82: Ancient temple inscriptions constitute invaluable historical records that document linguistic evolution, dynastic history, socio-cultural practices, and religious traditions. However, continuous exposure to environmental degradation, biological growth, and human interference has rendered many inscriptions fragile and increasingly illegible. Manual documentation methods are time-intensive and require specialized epigraphic expertise, limiting large-scale preservation efforts. This paper presents ShilpaSmriti, an AI-driven digital preservation framework designed to automatically capture, interpr | P82: OpenAlex | Q82: 2026-10-16
A83: 82 | B83: 2026 | C83: 2026-01-01 | D83: SLAVERY IN ANCIENT AND MEDIEVAL TAMIL SOCIETY - A HISTORICAL PERSPECTIVE | E83: Kaviraj G; Dr. C. Jeya Veera Devan | F83: INTERNATIONAL JOURNAL OF RESEARCH AND ANALYTICAL REVIEWS | G83: கல்வெட்டு | H83: Inscription / Epigraphy | I83: inscriptions | J83: Tamil Nadu | K83: English/Other | L83: https://doi.org/10.56975/ijrar.v13i4.341294 | M83: http://www.ijrar.org/download1.php?file=IJRAR26D1129.pdf | N83: 10.56975/ijrar.v13i4.341294 | O83: The purpose of this study is to refute the general notion that slavery was not practised in ancient Tamil Nadu and to establish, based on historical data, that slavery functioned as an institutionalized system in Tamil society.The study examines the evolution of slavery through Sangam and post-Sangam literature, such as the Purananuru and Thirukkural, and through inscriptions and palm-leaf manuscripts (Mudaliyar documents) from the 15th century CE.Moving beyond the one-dimensional view that untouchability alone was the cause of slavery, this study highlights that economic crises such as famine | P83: OpenAlex | Q83: 2026-10-16
A84: 83 | B84: 2026 | C84: 2026-04-22 | D84: Sankaranarayanaswamy Temple as Pallippadai of Rajaraja Chola I | E84: Jegan Sundararajan | F84: Zenodo (CERN European Organization for Nuclear Research) | G84: கல்வெட்டு | H84: Inscription / Epigraphy | I84: inscriptions, epigraphy | K84: English/Other | L84: https://doi.org/10.5281/zenodo.19700063 | M84: https://doi.org/10.5281/zenodo.19700063 | N84: 10.5281/zenodo.19700063 | O84: This study presents a detailed epigraphical reassessment of selected Chola-period inscriptions, with particular reference to materials from Sripuranthan (identified in inscriptions as Sriparanthaka Chaturvedimangalam). Drawing upon primary sources including South Indian Inscriptions (SII), Epigraphia Indica, and the Annual Reports on Epigraphy (ARE), the work re-examines questions of titulature, identity, and temple foundation within the Chola polity. The analysis focuses on the designation “Muttaraiyan” (Skt. Mutturāja), arguing for its interpretation as a structured princely title rather tha | P84: OpenAlex | Q84: 2026-10-17
A85: 84 | B85: 2026 | C85: 2026-04-29 | D85: Sign 15 and the Structure of the Tamil Nadu Megalithic Graffiti Corpus: A Five-Pillar Statistical Analysis | E85: Adarsh Chaturvedi | F85: Zenodo (CERN European Organization for Nuclear Research) | G85: தொல்லியல் | H85: Archaeology / Excavation | I85: archaeological, megalithic | J85: Tamil Nadu | K85: English/Other | L85: https://doi.org/10.5281/zenodo.19884550 | M85: https://doi.org/10.5281/zenodo.19884550 | N85: 10.5281/zenodo.19884550 | O85: The Tamil Nadu megalithic graffiti corpus, comprising 10,285 base-sign occurrences across 42 sign types from 15,184 potsherds at 140 archaeological sites (c. 1000–200 BCE), has been the subject of visual and morphological analysis for over six decades, beginning with Lal (1960). However, no complete quantitative statistical analysis of the corpus has been published. This paper presents the first Zipf-Mandelbrot frequency analysis and positional grammar study of the full corpus, using data from the tngraffiti.in concordance (Rajan and Sivanantham 2025, 2026). The corpus follows a Zipf-Mandelbro | P85: OpenAlex | Q85: 2026-10-17
A86: 85 | B86: 2026 | C86: 2026-07-06 | D86: Signs Independent of Language and Meaning: A Probabilistic Law of Sign Convergence, Based on the Tamil Nadu Graffiti and the Kaṇṇeżuttu of the Cilappatikāram | E86: Nikhil Raghavendra; Boris Kriger | F86: Zenodo (CERN European Organization for Nuclear Research) | G86: கல்வெட்டு, தொல்லியல் | H86: Inscription / Epigraphy, Archaeology / Excavation | I86: inscriptions, epigraphy, graffiti marks, megalithic | J86: Tamil Nadu | K86: English/Other | L86: https://doi.org/10.5281/zenodo.21223517 | M86: https://doi.org/10.5281/zenodo.21223517 | N86: 10.5281/zenodo.21223517 | O86: Authors Raghavendra, Nikhil — Independent Researcher, SingaporeKriger, Boris — Information Physics Institute; Institute of Integrative and Interdisciplinary Research, Toronto — ORCID: 0009-0001-0034-2903 Title: Signs Independent of Language and Meaning: A Probabilistic Law of Sign Convergence, Based on the Tamil Nadu Graffiti and the Kaṇṇeżuttu of the Cilappatikāram Description This paper confronts a century-old predicament shared by two bodies of ancient Indian symbols—the inscriptions of the Indus Valley seals and the graffiti marks incised on South Indian megalithic and early historic potte | P86: OpenAlex | Q86: 2026-10-16
A87: 86 | B87: 2026 | C87: 2026-10-01 | D87: Singing the Wound: Oppari, Collective Mourning and the Tamil Archive of Grief | E87: T Marx | F87: INTERNATIONAL JOURNAL OF CREATIVE RESEARCH THOUGHTS | G87: நடுகல் | H87: Hero stone / Memorial stone | I87: hero stone, hero-stone | K87: English/Other | L87: https://doi.org/10.56975/ijcrt.v14i10.400554 | M87: https://ijcrt.org/papers/IJCRT2610095.pdf | N87: 10.56975/ijcrt.v14i10.400554 | O87: This paper reads oppari, the Tamil funeral lament sung chiefly by women, through the conceptual framework of trauma and memory studies. It argues that oppari performs, in public and in common, the labour that Sigmund Freud assigned to the private psyche in “Mourning and Melancholia”: the recall, dwelling upon and gradual release of each bond to the lost person. Drawing on Sigmund Freud, Cathy Caruth, Judith Herman, Dori Laub, Maurice Halbwachs, Pierre Nora, Jan Assmann and Ann Cvetkovich, and on ethnographic work by Isabelle Clark-Decès, Margaret Trawick and C. Nadia Seremetakis, the paper mak | P87: OpenAlex | Q87: 2026-10-17
A88: 87 | B88: 2026 | C88: 2026-06-27 | D88: Statistical Evidence for Agglutinative Structure in the Indus Valley Script | E88: Arun G K | F88: Zenodo (CERN European Organization for Nuclear Research) | G88: தொல்லியல் | H88: Archaeology / Excavation | I88: archaeological, megalithic, keeladi | J88: Tamil Nadu | K88: English/Other | L88: https://doi.org/10.5281/zenodo.20971473 | M88: https://doi.org/10.5281/zenodo.20971473 | N88: 10.5281/zenodo.20971473 | O88: We present four independent statistical tests on a pilot corpus of 41 intact uni-corn and bovine seals from the Indus Valley Civilisation (c. 2600–1900 bce), testingthe hypothesis that sign P385 (jar pictogram; Wells 520; ICIT label: TMK) encodesthe Proto-Dravidian masculine nominal suffix -an. . The Suffix Theorem showsP385 occupies the terminal position in 100% of occurrences with zero initial appear-ances (p = 6.54 × 10−21, one-tailed binomial test against a uniform positional null).The Agglutination Ratio shows the bigram P122→P385 occurs 6.92× more oftenthan independent sign probabilities | P88: OpenAlex | Q88: 2026-10-17
A89: 88 | B89: 2026 | C89: 2026-06-11 | D89: THE DEMOTED CREATOR From Prajāpati to Gazette Notification 12011/68/93 — Clay Technology, the Potter Community, and the Administrative Unmaking of India's First Industry | E89: gemsofindology | F89: Zenodo (CERN European Organization for Nuclear Research) | G89: கல்வெட்டு, தொல்லியல் | H89: Inscription / Epigraphy, Archaeology / Excavation | I89: inscribed, keeladi | J89: Egypt | K89: English/Other | L89: https://doi.org/10.5281/zenodo.20635698 | M89: https://doi.org/10.5281/zenodo.20635698 | N89: 10.5281/zenodo.20635698 | O89: The community that bears the name of the creator deity — Prajāpati, the god who in the Brahmanas creates the world by the potter's own method of formed matter and applied heat — is today a line item in Government of India gazette notification 12011/68/93-BCC(C) of 10 September 1993, classified “Other Backward Class.” This paper demonstrates that every station of the intervening five-millennium record contradicts the classification's premise. The Harappan ceramic industry was mass-standardised wheel production at urban and network scale. The Śatapatha Brāhmaṇa's vessel prescriptions are enginee | P89: OpenAlex | Q89: 2026-10-17
A90: 89 | B90: 2026 | C90: 2026-09-26 | D90: THE VAIYAI AND HISTORICAL RECORDS | E90: Pandi Muthu | F90: Zenodo (CERN European Organization for Nuclear Research) | G90: தொல்லியல் | H90: Archaeology / Excavation | I90: archaeology, archaeological, keeladi | J90: Tamil Nadu | K90: English/Other | L90: https://doi.org/10.5281/zenodo.22974178 | M90: https://doi.org/10.5281/zenodo.22974178 | N90: 10.5281/zenodo.22974178 | O90: Across the globe, every society continuously seeks to highlight its antiquity, lineage, heritage, and contributions to human civilization. The Tamil people possess a legacy of antiquity, culture, and civilizational excellence comparable to that of the Greek, Egyptian, Roman, and Indus Valley civilizations. Ongoing research efforts are dedicated to uncovering and documenting this heritage; the Keeladi excavation is one such significant endeavor. Keeladi is located eight kilometers west of Thirupuvanam in the Sivaganga district—a site celebrated as a cradle of Tamil identity. To date, four round | P90: OpenAlex | Q90: 2026-10-17
A91: 90 | B91: 2026 | C91: 2026-05-06 | D91: TamOCR: A Lightweight LLM-Assisted OCR Framework for Digitizing Tamil-Brahmi Inscriptions | E91: K. Saranya; S R Nitthin Kumar; R Praveen Kumar; S Arun Nivesh | F91: International Conference on Pervasive Computing and Social Networking (ICPCSN) | G91: கல்வெட்டு, தொல்லியல் | H91: Inscription / Epigraphy, Archaeology / Excavation | I91: inscription, inscriptions, tamil-brahmi, tamil brahmi, archaeology | K91: English/Other | L91: https://doi.org/10.1109/icpcsn68523.2026.11543656 | N91: 10.1109/icpcsn68523.2026.11543656 | O91: The digitisation of Tamil–Brahmi inscriptions is essential for safeguarding South India’s earliest written heritage, yet real-world OCR deployment is still challenged by weathered stone surfaces, broken or missing glyphs, inconsistent lighting, and highly variable carving styles. In response to survey findings that highlighted the need for modular and resilient OCR pipelines, this work introduces TamOCR, a lightweight, LLM-assisted OCR framework tailored for Tamil–Brahmi inscription digitisation. The framework combines a robust pre-processing stage for contrast enhancement and noise reduction, | P91: OpenAlex | Q91: 2026-10-16
A92: 91 | B92: 2026 | C92: 2026-08-24 | D92: Tamil Brahmi Stone Inscription | E92: Sukumar M | F92: Mendeley Data | G92: கல்வெட்டு, தொல்லியல் | H92: Inscription / Epigraphy, Archaeology / Excavation | I92: inscription, inscriptions, epigraphy, tamil-brahmi, tamil brahmi, archaeology | J92: Tamil Nadu | K92: English/Other | L92: https://doi.org/10.17632/2spz2js9jp | M92: https://doi.org/10.17632/2spz2js9jp | N92: 10.17632/2spz2js9jp | O92: The “Tamil Brahmi Stone Inscription Dataset (TBSI)** is the first open-source benchmark dataset dedicated to the processing and analysis of degraded Tamil stone inscriptions. Due to the lack of publicly available benchmark datasets for this specific domain, this repository bridges a critical gap in digital heritage and computational epigraphy. The dataset is compiled from the official archives of the **Tamil Nadu Department of Archaeology (TNDA)** and other publicly available epigraphic resources. Ancient Tamil stone inscriptions are invaluable historical records, but their automated analysis | P92: OpenAlex | Q92: 2026-10-16
A93: 92 | B93: 2026 | C93: 2026-07-22 | D93: Tamil Civilization As The Precursor Of World Civilization : A Cultural And Historical Analysis | E93: S. Marimuthu; Dr.K.Kalai Selvi | F93: Educational Administration Theory and Practice journal | G93: கல்வெட்டு, தொல்லியல் | H93: Inscription / Epigraphy, Archaeology / Excavation | I93: inscriptions, archaeological | K93: English/Other | L93: https://kuey.net/index.php/kuey/article/view/12064 | M93: https://kuey.net/index.php/kuey/article/download/12064/9446 | O93: Tamil civilization, one of the oldest continuous cultures in the world, has left an indelible mark on global human history. With roots stretching beyond 5000 years, Tamil society has fostered advancements in language, trade, urbanism, spirituality, and science. This paper explores the hypothesis that Tamil civilization is not merely ancient but foundational to world civilization, influencing regions far beyond the Indian subcontinent. Drawing upon archaeological evidence, linguistic research, ancient texts, and cross-cultural connections, this study positions Tamil culture as a mother-root fro | P93: OpenAlex | Q93: 2026-10-16
A94: 93 | B94: 2026 | C94: 2026-04-07 | D94: Tamil Civilization Is More Ancient Than Assumed: A Statistical Case from Radiometric Evidence | E94: Rajeshkumar Venugopal | F94: Zenodo (CERN European Organization for Nuclear Research) | G94: தொல்லியல் | H94: Archaeology / Excavation | I94: archaeology, archaeological, adichanallur, mayiladumparai | J94: Tamil Nadu | K94: English/Other | L94: https://doi.org/10.5281/zenodo.19462511 | M94: https://doi.org/10.5281/zenodo.19462511 | N94: 10.5281/zenodo.19462511 | O94: Radiometric dates from five Tamil Nadu iron age sites — Sivagalai, Adichanallur, Mayiladumparai, Kilnamandi, and Mangadu — place iron-associated activity in peninsular India between 1500 and 3345 BCE. The standard response from the archaeological community has been stratigraphic disturbance: charcoal may predate the iron objects with which it is found. This paper demonstrates that this response is statistically untenable as a blanket refutation. The argument is a direct application of the Bernoulli distribution. If the probability that disturbance fully explains an early date at any single wel | P94: OpenAlex | Q94: 2026-10-17
A95: 94 | B95: 2026 | C95: 2026-06-03 | D95: Tamil Inscriptions encoded by the DHARMA project | E95: Emmanuel Francis | F95: HAL (Le Centre pour la Communication Scientifique Directe) | G95: கல்வெட்டு | H95: Inscription / Epigraphy | I95: inscriptions | K95: English/Other | L95: https://hal.science/hal-05656219v1 | M95: https://hal.science/hal-05656219v1 | O95: International audience | P95: OpenAlex | Q95: 2026-10-16
A96: 95 | B96: 2026 | C96: 2026-01-01 | D96: Tamil Words in Early Prakrit Inscriptions in Sri Lanka | E96: Karan Damodaram Pillai | F96: SSRN Electronic Journal | G96: கல்வெட்டு | H96: Inscription / Epigraphy | I96: inscriptions | J96: Sri Lanka | K96: English/Other | L96: https://doi.org/10.2139/ssrn.6422478 | M96: https://doi.org/10.2139/ssrn.6422478 | N96: 10.2139/ssrn.6422478 | P96: OpenAlex | Q96: 2026-10-16
A97: 96 | B97: 2026 | C97: 2026-06-09 | D97: Tamil speech development | E97: Lakshmi Venkatesh; Savitha Vadakkanthara Hariharan | F97: book-chapter | G97: கல்வெட்டு | H97: Inscription / Epigraphy | I97: tamil-brahmi, tamil brahmi | J97: Sri Lanka, Malaysia | K97: English/Other | L97: https://doi.org/10.1093/9780191964909.003.0081 | N97: 10.1093/9780191964909.003.0081 | O97: Abstract Tamil and its dialects are spoken predominantly in South Asian countries including India, Sri Lanka, Singapore, and Malaysia, and in an extensive diaspora around the world. Tamil is characterized by 26 consonants, 11 vowels, and two diphthongs, and uses the Tamil-Brahmi script. Research on acquisition of Tamil has mainly focused on consonant acquisition, phonological patterns, and word structure among typically developing children. The majority of Tamil consonants are acquired by three years of age with children producing increasingly complex word structures with age. Development of s | P97: OpenAlex | Q97: 2026-10-16
A98: 97 | B98: 2026 | C98: 2026-08-08 | D98: Tamili Inscriptions and Developments of Tamil Paleography - Special Reference To Villupuram | E98: Dr E Jeeva | F98: International Journal of Emerging Multidisciplinary Research and Innovation | G98: கல்வெட்டு, தொல்லியல் | H98: Inscription / Epigraphy, Archaeology / Excavation | I98: inscriptions, tamil-brahmi, tamil brahmi, tamili, vatteluttu, archaeological, archaeological excavations | J98: Tamil Nadu | K98: English/Other | L98: https://doi.org/10.65180/ijemri.2026.2.3.05 | M98: https://ijemri.com/index.php/files/article/download/112/55 | N98: 10.65180/ijemri.2026.2.3.05 | O98: This article explores the paleography of Tamil Nadu through graffiti and epigraphical sources, focusing on Villupuram, a prominent district with a rich history and culture. Paleography is an ancient writing system found in meager antiquities, but it could be the rudimentary writing style of the people in India, particularly Tamil Nadu. Tamil Nadu has vast archaeological and epigraphical sources, which researchers have explored through excavations and exploration. Villupuram has the potential to have an ancient writing system that evolved from archaeological excavations by the department and in | P98: OpenAlex | Q98: 2026-10-16
A99: 98 | B99: 2026 | C99: 2026-10-07 | D99: Telugu Before Its Inscriptions, and the Epigraphic Age Fallacy | E99: Naga Sai Durga Nagesh Seshabattara Venkata | F99: Zenodo (CERN European Organization for Nuclear Research) | G99: கல்வெட்டு | H99: Inscription / Epigraphy | I99: inscriptions | J99: Andhra / Telangana, Sri Lanka | K99: English/Other | L99: https://doi.org/10.5281/zenodo.23207957 | M99: https://doi.org/10.5281/zenodo.23207957 | N99: 10.5281/zenodo.23207957 | O99: Tamil is written on stone nearly eight centuries before Telugu, and a hierarchy is routinely drawn from that fact: Tamil the old language, Telugu the late one. This paper argues that the hierarchy rests on one inference error, the Epigraphic Age Fallacy, which reads the date a language entered the archive as the date the language began. Six lines of evidence are assembled. First, under the principal comparative and Bayesian models examined here, the Tamil and Telugu lineages separate in prehistory: by about 1100 BCE in Krishnamurti's comparative reconstruction, and at the root of the family, a | P99: OpenAlex | Q99: 2026-10-17
A100: 99 | B100: 2026 | C100: 2026-01-28 | D100: Temple Inscriptions of Meenakshi Amman Temple, Madurai: An Epigraphic Analysis of Political, Religious, and Socio-Economic History (13th–17th Century CE) | E100: G. Rajeswari | F100: Anusandhanvallari | G100: கல்வெட்டு, தொல்லியல் | H100: Inscription / Epigraphy, Archaeology / Excavation | I100: inscriptions, epigraphy, grantha script, archaeology, archaeological | J100: Tamil Nadu | K100: English/Other | L100: https://psvmkendra.com/index.php/journal/article/view/2158 | M100: https://psvmkendra.com/index.php/journal/article/download/2158/1889 | O100: The Meenakshi Sundareswarar Temple at Madurai is one of the most significant religious and cultural monuments in South India, renowned not only for its architectural grandeur but also for its extensive corpus of stone inscriptions. These inscriptions constitute an important body of primary historical evidence that documents the political, economic, religious, social, and cultural developments of medieval Tamil Nadu. Spanning the Later Pandya, Vijayanagara, and Nayak periods, the inscriptions provide detailed information on royal patronage, temple administration, land grants, taxation, endowmen | P100: OpenAlex | Q100: 2026-10-17
...

Sheet New (last 7 days)
A1: No | B1: Date | C1: Year | D1: Title | E1: Keyword group (Tamil) | F1: Keyword group (English) | G1: Matched terms | H1: Places mentioned | I1: Source | J1: Source country | K1: Language | L1: URL | M1: Archive copy | N1: Snippet | O1: Match basis | P1: Found via | Q1: Found on
A2: 1 | B2: 2026-10-29 | C2: 2026 | D2: பாண்டியர் கால கல்வெட்டு புதுக்கோட்டையில் கண்டெடுப்பு | E2: கல்வெட்டு | F2: Inscription / Epigraphy | G2: கல்வெட்டு | I2: dinamalar.com | J2: India | K2: Tamil | L2: https://www.dinamalar.com/templenews/165979 | N2: பாண்டியர் கால கல்வெட்டு புதுக்கோட்டையில் கண்டெடுப்பு புதுக்கோட்டை: புதுக்கோட்டை மாவட்டம், பொதுஒக்கூர் என்ற ஊரில், வரலாற்று ஆய்வாளர் காளிதாஸ் குழுவினர், கள ஆய்வு மேற்கொண்டனர். அப்போது, பிள்ளையார் கோவில் திடலுக்கு அருகே கல்வெட்டு ஒன்று, மண்ணில் புதையுண்டு கிடப்பதை கண்டெடுத்தனர். இது குறித்து, காளிதாஸ்… | O2: full-text | P2: gnews | Q2: 2026-10-30
A3: 2 | B3: 2026-10-28 | C3: 2026 | D3: கீழடி அருங்காட்சியகத்தில் ஆய்வு | E3: தொல்லியல் | F3: Archaeology / Excavation | G3: தொல்லியல், தொல்லியல் துறை, அகழாய்வு, கீழடி | I3: dinamalar.com | J3: India | K3: Tamil | L3: https://www.dinamalar.com/news/tamil-nadu-district-news-sivagangai/exploration-at-the-keezhadi-museum/4361468 | N3: உள்ளடக்கத்திற்கு செல்ல ADDED : அக் 28, 2026 07:11 PM அ நிறம் | அளவு கீழடி: தமிழக தொல்லியல் துறை கமிஷனராக சங்கர் செப்டம்பரில் நியமிக்கப்பட்டார். இதனையடுத்து கீழடி தொல் பொருள் மற்றும் திறந்த வெளி அருங்காட்சியகம், 11ம் கட்ட அகழாய்வு நடைபெறும் இடங்கள் ஆகியவற்றை ஆய்வு செய்தார். அருங்காட்சியகத்தில் கூடுதல… | O3: full-text | P3: gnews | Q3: 2026-10-29
A4: 3 | B4: 2026-10-28 | C4: 2026 | D4: பாண்டியர் கால கல்வெட்டு புதுக்கோட்டையில் கண்டெடுப்பு | E4: கல்வெட்டு | F4: Inscription / Epigraphy | G4: கல்வெட்டு | I4: dinamalar.com | J4: India | K4: Tamil | L4: https://www.dinamalar.com/news/tamil-nadu-district-news-pudukottai/pandyan-period-inscription-discovered-in-pudukkottai/4360672 | N4: உள்ளடக்கத்திற்கு செல்ல பாண்டியர் கால கல்வெட்டு புதுக்கோட்டையில் கண்டெடுப்பு UPDATED : அக் 27, 2026 07:10 PM ADDED : அக் 27, 2026 07:00 PM புதுக்கோட்டை: புதுக்கோட்டை மாவட்டம், பொதுஒக்கூர் என்ற ஊரில், வரலாற்று ஆய்வாளர் காளிதாஸ் குழுவினர், கள ஆய்வு மேற்கொண்டனர். அப்போது, பிள்ளையார் கோவில் திடலுக்கு அரு… | O4: full-text | P4: gnews | Q4: 2026-10-28
A5: 4 | B5: 2026-10-28 | C5: 2026 | D5: பாண்டியர் கால கல்வெட்டு புதுக்கோட்டையில் கண்டெடுப்பு | E5: கல்வெட்டு | F5: Inscription / Epigraphy | G5: கல்வெட்டு | H5: Kerala | I5: temple.dinamalar.com | J5: India | K5: Tamil | L5: https://temple.dinamalar.com/news_detail.php?id=165979 | N5: | | | | முதல் பக்கம் » இன்றைய செய்திகள் | | | பாண்டியர் கால கல்வெட்டு புதுக்கோட்டையில் கண்டெடுப்பு பதிவு செய்த நாள் 28 அக் 2026 11:10 புதுக்கோட்டை: புதுக்கோட்டை மாவட்டம், பொதுஒக்கூர் என்ற ஊரில், வரலாற்று ஆய்வாளர் காளிதாஸ் குழுவினர், கள ஆய்வு மேற்கொண்டனர். அப்போது, பிள்ளையார் கோவில் திடலுக்கு அருகே க… | O5: full-text | P5: gnews | Q5: 2026-10-29
A6: 5 | B6: 2026-10-27 | C6: 2026 | D6: 10ம் நுாற்றாண்டு கல்வெட்டு அகத்தீஸ்வரர் கோவிலில் கண்டுபிடிப்பு | E6: கல்வெட்டு, தொல்லியல் | F6: Inscription / Epigraphy, Archaeology / Excavation | G6: கல்வெட்டு, கல்வெட்டுகள், தொல்லியல் | I6: dinamalar.com | J6: India | K6: Tamil | L6: https://www.dinamalar.com/news/tamil-nadu-district-news-kancheepuram/10th-century-inscription-discovered-in-agadheshwara-temple/4359447 | N6: உள்ளடக்கத்திற்கு செல்ல 10ம் நுாற்றாண்டு கல்வெட்டு அகத்தீஸ்வரர் கோவிலில் கண்டுபிடிப்பு ADDED : அக் 26, 2026 04:26 PM வாலாஜாபாத்: வல்லப்பாக்கம் அகத்தீஸ்வரர் கோவிலில், 10ம் நுாற்றாண்டைச் சேர்ந்த கல்வெட்டு நேற்று (அக்.,25) கண்டுபிடிக்கபட்டு உள்ளது. இதுகுறித்து, வாலாஜாபாத் வட்டார வரலாற்று ஆய்வு மைய தலைவர… | O6: full-text | P6: gnews | Q6: 2026-10-27
A7: 6 | B7: 2026-10-27 | C7: 2026 | D7: தமிழ் ஆசிரியர்கள் பறக்கலாம்!: நம்பிக்கை அளிக்கிறார் பேரூர் ஆதினம் | E7: கல்வெட்டு, தொல்லியல் | F7: Inscription / Epigraphy, Archaeology / Excavation | G7: கல்வெட்டு, தொல்பொருள் | H7: Sri Lanka, Malaysia | I7: dinamalar.com | J7: India | K7: Tamil | L7: https://www.dinamalar.com/news_detail.asp?id=2268888 | N7: உள்ளடக்கத்திற்கு செல்ல தமிழ் ஆசிரியர்கள் 'பறக்கலாம்!': நம்பிக்கை அளிக்கிறார் பேரூர் ஆதினம் UPDATED : மே 04, 2019 02:00 AM ADDED : மே 04, 2019 01:13 AM 'தமிழ் படிச்சு என்னங்க ஆகப்போகுது...பேசாம பி.காம் சேர்த்து விட்டுருங்க...பேங்குலயாவது வேலை கிடைக்கும்'- இப்படி பெற்றோர்களை தவறாக வழிநடத்தும் கல்வியாள… | O7: full-text | P7: gdelt | Q7: 2026-10-27
A8: 7 | B8: 2026-10-26 | C8: 2026 | D8: 13th Century Hero Stone Helps Understand Medieval History | E8: கல்வெட்டு, நடுகல், தொல்லியல் | F8: Inscription / Epigraphy, Hero stone / Memorial stone, Archaeology / Excavation | G8: inscription, inscriptions, inscribed, hero stone, hero stones, hero-stone, archaeological | H8: Tamil Nadu | I8: deccanchronicle.com | J8: India | K8: English/Other | L8: https://www.deccanchronicle.com/amp/southern-states/tamil-nadu/13th-century-hero-stone-helps-understand-medieval-history-1998923 | N8: 13th Century Hero Stone Helps Understand Medieval History In view of the relative rarity of inscriptions from the period of Vira Vishwanatha in Tamil Nadu, this discovery represents a significant documentary source for further research into the region’s medieval political history COIMBATORE: On the … | O8: full-text | P8: gnews | Q8: 2026-10-27
A9: 8 | B9: 2026-10-26 | C9: 2026 | D9: 13th Century Hero Stone Helps Understand Medieval History | E9: கல்வெட்டு, நடுகல், தொல்லியல் | F9: Inscription / Epigraphy, Hero stone / Memorial stone, Archaeology / Excavation | G9: inscription, inscriptions, inscribed, hero stone, hero stones, hero-stone, archaeological | H9: Tamil Nadu | I9: deccanchronicle.com | J9: India | K9: English/Other | L9: https://www.deccanchronicle.com/southern-states/tamil-nadu/13th-century-hero-stone-helps-understand-medieval-history-1998923 | N9: 13th Century Hero Stone Helps Understand Medieval History In view of the relative rarity of inscriptions from the period of Vira Vishwanatha in Tamil Nadu, this discovery represents a significant documentary source for further research into the region’s medieval political history COIMBATORE: On the … | O9: full-text | P9: gnews | Q9: 2026-10-27
A10: 9 | B10: 2026-10-26 | C10: 2026 | D10: 6th-Century Dharmapuri Hero Stone Sheds Light on Ancient Tamil Nadu | E10: கல்வெட்டு, நடுகல் | F10: Inscription / Epigraphy, Hero stone / Memorial stone | G10: inscriptions, hero stone, hero-stone | H10: Tamil Nadu | I10: deccanchronicle.com | J10: India | K10: English/Other | L10: https://www.deccanchronicle.com/through-the-lens/6th-century-dharmapuri-hero-stone-sheds-light-on-ancient-tamil-nadu-1998926 | N10: 6th-Century Dharmapuri Hero Stone Sheds Light on Ancient Tamil Nadu The newly-documented ‘hero stone inscriptions’ in Dharmapuri belt sheds light on the history of ancient Tamil Nadu as researchers from the Yaakkai Heritage Trust, based in Coimbatore, documented two hero stone inscriptions during fi… | O10: full-text | P10: gnews | Q10: 2026-10-27
A11: 10 | B11: 2026-10-26 | C11: 2026 | D11: Ancient terracotta lamp unearthed in Tamil Nadus Vembakottai | E11: தொல்லியல் | F11: Archaeology / Excavation | G11: archaeology, vembakottai | H11: Tamil Nadu | I11: news.webindia123.com | J11: Unknown | K11: English/Other | L11: https://news.webindia123.com/news/Articles/India/20220504/3937813.html | N11: Monday, October 26, 2026 News | | | Ancient terracotta lamp unearthed in Tamil Nadu's Vembakottai Chennai \| Wednesday, 2022 3:45:09 AM IST | | Excavations at Vembakottai in Virudhunagar district of Tamil Nadu have unearthed an ancient terracotta lamp, which according to archaeologists is an intrins… | O11: full-text | P11: gdelt | Q11: 2026-10-26
A12: 11 | B12: 2026-10-26 | C12: 2026 | D12: Dharmapuri Hero Stones Shed Light on Tamil Nadu’s History | E12: கல்வெட்டு, நடுகல், தொல்லியல் | F12: Inscription / Epigraphy, Hero stone / Memorial stone, Archaeology / Excavation | G12: inscription, inscriptions, epigraphist, vatteluttu, hero stone, hero stones, hero-stone, archaeological | H12: Tamil Nadu | I12: deccanchronicle.com | J12: India | K12: English/Other | L12: https://www.deccanchronicle.com/amp/southern-states/tamil-nadu/dharmapuri-hero-stones-shed-light-on-tamil-nadus-history-1998919 | N12: Dharmapuri Hero Stones Shed Light on Tamil Nadu’s History The newly-documented ‘hero stone inscriptions’ in Dharmapuri belt sheds light on the history of ancient Tamil Nadu as researchers from the Yaakkai Heritage Trust, based in Coimbatore, documented two hero stone inscriptions during field survey… | O12: full-text | P12: gnews | Q12: 2026-10-27
A13: 12 | B13: 2026-10-26 | C13: 2026 | D13: Dharmapuri Hero Stones Shed Light on Tamil Nadu’s History | E13: கல்வெட்டு, நடுகல், தொல்லியல் | F13: Inscription / Epigraphy, Hero stone / Memorial stone, Archaeology / Excavation | G13: inscription, inscriptions, epigraphist, vatteluttu, hero stone, hero stones, hero-stone, archaeological | H13: Tamil Nadu | I13: deccanchronicle.com | J13: India | K13: English/Other | L13: https://www.deccanchronicle.com/southern-states/tamil-nadu/dharmapuri-hero-stones-shed-light-on-tamil-nadus-history-1998919 | N13: Dharmapuri Hero Stones Shed Light on Tamil Nadu’s History The newly-documented ‘hero stone inscriptions’ in Dharmapuri belt sheds light on the history of ancient Tamil Nadu as researchers from the Yaakkai Heritage Trust, based in Coimbatore, documented two hero stone inscriptions during field survey… | O13: full-text | P13: gnews | Q13: 2026-10-27
A14: 13 | B14: 2026-10-26 | C14: 2026 | D14: நாயுடன் போருக்குச் சென்ற வீரன்... செஞ்சி அருகே 500 ஆண்டுகள் பழமையான நடுகல் கண்டுபிடிப்பு | E14: நடுகல் | F14: Hero stone / Memorial stone | G14: நடுகல் | I14: tamil.news18.com | J14: India | K14: Tamil | L14: https://tamil.news18.com/tamil-nadu/16th-century-hero-stone-discovered-near-gingee-in-villupuram-depicting-warrior-with-a-dog-pja-pdp-local18-2239455.html?utm_source=District%20Widget&utm_medium=Desktop&utm_campaign=tamil | N14: நாயுடன் போருக்குச் சென்ற வீரன்... செஞ்சி அருகே 500 ஆண்டுகள் பழமையான நடுகல் கண்டுபிடிப்பு - Reported by:Pooja S - Published by:pradeepa m Last Updated: இந்த நடுகல் கி.பி. 16-ஆம் நூற்றாண்டைச் சேர்ந்ததாகக் கருதப்படுகிறது. பிற்கால விஜயநகரப் பேரரசின் இறுதிக் காலத்துக்கும் தொடக்ககால நாயக்கர் ஆட்சிக் காலத்… | O14: full-text | P14: gnews | Q14: 2026-10-27
A15: 14 | B15: 2026-10-26 | C15: 2026 | D15: நாயுடன் போருக்குச் சென்ற வீரன்... செஞ்சி அருகே 500 ஆண்டுகள் பழமையான நடுகல் கண்டுபிடிப்பு | E15: நடுகல் | F15: Hero stone / Memorial stone | G15: நடுகல் | I15: tamil.news18.com | J15: India | K15: Tamil | L15: https://tamil.news18.com/tamil-nadu/16th-century-hero-stone-discovered-near-gingee-in-villupuram-depicting-warrior-with-a-dog-pja-pdp-local18-2239455.html | N15: நாயுடன் போருக்குச் சென்ற வீரன்... செஞ்சி அருகே 500 ஆண்டுகள் பழமையான நடுகல் கண்டுபிடிப்பு - Reported by:Pooja S - Published by:pradeepa m Last Updated: இந்த நடுகல் கி.பி. 16-ஆம் நூற்றாண்டைச் சேர்ந்ததாகக் கருதப்படுகிறது. பிற்கால விஜயநகரப் பேரரசின் இறுதிக் காலத்துக்கும் தொடக்ககால நாயக்கர் ஆட்சிக் காலத்… | O15: full-text | P15: gnews | Q15: 2026-10-27
A16: 15 | B16: 2026-10-25 | C16: 2026 | D16: ASI refutes Kanimozhi's claim over lack of facilities at Adichanallur heritage site | E16: தொல்லியல் | F16: Archaeology / Excavation | G16: archaeological, adichanallur | H16: Tamil Nadu | I16: aninews.in | J16: India | K16: English/Other | L16: https://www.aninews.in/news/national/general-news/asi-refutes-kanimozhis-claim-over-lack-of-facilities-at-adichanallur-heritage-site20210724135934/ | N16: New Delhi [India], July 24 (ANI): The Archaeological Survey of India (ASI) on Friday refuted DMK MP Kanimozhi's claim that there are no amenities like boundary walls, drinking water, toilets and solar lights around the Adichanallur heritage site in Tamil Nadu. "We Archaeological Survey of India is w… | O16: full-text | P16: gdelt | Q16: 2026-10-25
A17: 16 | B17: 2026-10-25 | C17: 2026 | D17: Assam: Thousands participate in Yoga Utsav in Sivasagar | E17: தொல்லியல் | F17: Archaeology / Excavation | G17: archaeological, adichanallur | H17: Tamil Nadu | I17: news.webindia123.com | J17: Unknown | K17: English/Other | L17: https://news.webindia123.com/news/Articles/India/20220502/3937227.html | N17: Sunday, October 25, 2026 News | | | Assam: Thousands participate in 'Yoga Utsav' in Sivasagar General News \| May 2, 2022 3:53:32 PM IST | | Sivasagar (Assam) [India], May 2: The Ayush Ministry with active support from the Assam government on Monday organised a Yoga Utsav at the iconic holy site of … | O17: full-text | P17: gdelt | Q17: 2026-10-25
A18: 17 | B18: 2026-10-25 | C18: 2026 | D18: Budget 2020: Govt allocates Rs 2,500 cr for development of tourism sector | E18: தொல்லியல் | F18: Archaeology / Excavation | G18: archaeology, archeological, adichanallur | H18: Tamil Nadu | I18: aninews.in | J18: India | K18: English/Other | L18: https://www.aninews.in/news/national/general-news/budget-2020-govt-allocates-rs-2500-cr-for-development-of-tourism-sector20200201205416/ | N18: New Delhi [India], Feb 1 (ANI): To make India an attractive destination for both international and domestic tourists, Finance Minister Nirmala Sitharaman on Saturday proposed to allocate Rs 2,500 crores in the Budget for FY2020-21 for the tourism sector. Besides tourism, Sitharaman also proposed to … | O18: full-text | P18: gdelt | Q18: 2026-10-25
A19: 18 | B19: 2026-10-25 | C19: 2026 | D19: FM Sitharaman proposes Rs 2,500 crore for tourism in 2020-21, eight new museums | E19: தொல்லியல் | F19: Archaeology / Excavation | G19: archeological, adichanallur | H19: Tamil Nadu | I19: aninews.in | J19: India | K19: English/Other | L19: https://www.aninews.in/news/national/general-news/fm-sitharaman-proposes-rs-2500-crore-for-tourism-in-2020-21-eight-new-museums20200201150419/ | N19: New Delhi [India], Feb 1 (ANI): Finance Minister Nirmala Sithraman on Saturday proposed to allocate Rs 2,500 crore in 2020-21 for the tourism sector and construction of eight new museums, which includes building infrastructure around 5 iconic sites. "To make India an attractive destination for both … | O19: full-text | P19: gdelt | Q19: 2026-10-25
A20: 19 | B20: 2026-10-25 | C20: 2026 | D20: Ministry of Ayush to celebrate Yoga Utsav to mark 50 days countdown to International Day of Yoga 2022 | E20: தொல்லியல் | F20: Archaeology / Excavation | G20: archaeological, adichanallur | H20: Tamil Nadu | I20: news.webindia123.com | J20: Unknown | K20: English/Other | L20: https://news.webindia123.com/news/Articles/Business/20220501/3937022.html | N20: Sunday, October 25, 2026 News | | | Ministry of Ayush to celebrate Yoga Utsav to mark 50 days countdown to International Day of Yoga 2022 New Delhi \| May 1, 2022 10:24:01 PM IST | | The Ministry of Ayush in collaboration with state Government of Assam is organizing a grand event at Rang Ghar Ground… | O20: full-text | P20: gdelt | Q20: 2026-10-25
A21: 20 | B21: 2026-10-25 | C21: 2026 | D21: NTK proposes new Tamil Nadu government emblem featuring Thiruvalluvar at election manifesto release program | E21: தொல்லியல் | F21: Archaeology / Excavation | G21: keeladi, adichanallur | H21: Tamil Nadu | I21: aninews.in | J21: India | K21: English/Other | L21: https://aninews.in/news/national/general-news/ntk-proposes-new-tamil-nadu-government-emblem-featuring-thiruvalluvar-at-election-manifesto-release-program20260319132156/ | N21: Chennai (Tamil Nadu) [India], March 19 (ANI): The Naam Tamilar Katchi (NTK) has proposed the new Tamil Nadu government emblem if the party comes to power in the state at the NTK Election Manifesto release program on Thursday in Chennai. According to the party, the redesigned emblem would prominently… | O21: full-text | P21: gdelt | Q21: 2026-10-25
A22: 21 | B22: 2026-10-25 | C22: 2026 | D22: Tamil Nadu floods: 35 deaths reported, focus now on restoring basic services, says chief secretary | E22: தொல்லியல் | F22: Archaeology / Excavation | G22: excavation site, adichanallur | H22: Tamil Nadu | I22: news.webindia123.com | J22: Unknown | K22: English/Other | L22: https://news.webindia123.com/news/Articles/India/20231223/4151975.html | N22: Sunday, October 25, 2026 News | | | Tamil Nadu floods: 35 deaths reported, focus now on restoring basic services, says chief secretary Thoothukudi (Tamil Nadu) \| December 23, 2023 10:21:28 PM IST | | Tamil Nadu Chief Secretary Shiv Das Meena said on Saturday that the rescue operation in the flood-a… | O22: full-text | P22: gdelt | Q22: 2026-10-25
A23: 22 | B23: 2026-10-25 | C23: 2026 | D23: Tamil Nadu: AIADMK, NDA allies hold massive protest against DMK in Dindigul | E23: தொல்லியல் | F23: Archaeology / Excavation | G23: archaeological, keezhadi, adichanallur | H23: Tamil Nadu | I23: aninews.in | J23: India | K23: English/Other | L23: https://aninews.in/news/national/politics/tamil-nadu-aiadmk-nda-allies-hold-massive-protest-against-dmk-in-dindigul20260318041556/ | N23: Dindigul (Tamil Nadu) [India], March 18 (ANI): The All India Anna Dravida Munnetra Kazhagam (AIADMK) and its National Democratic Alliance (NDA) partners staged a joint protest at the Dindigul Clock Tower area to condemn the policies of the state government led by Dravida Munnetra Kazhagam (DMK). AIA… | O23: full-text | P23: gdelt | Q23: 2026-10-25
A24: 23 | B24: 2026-10-25 | C24: 2026 | D24: Tamil Nadu: Political landscape heats up as Opposition protests against DMK ahead of polls | E24: தொல்லியல் | F24: Archaeology / Excavation | G24: archaeological, keezhadi, adichanallur | H24: Tamil Nadu | I24: aninews.in | J24: India | K24: English/Other | L24: https://aninews.in/news/national/politics/tamil-nadu-political-landscape-heats-up-as-opposition-protests-against-dmk-ahead-of-polls20260317180639/ | N24: Tiruppur (Tamil Nadu) [India], March 17 (ANI): The political temperature in Tamil Nadu heightened as opposition parties staged a large-scale protest in Tiruppur, targeting the ruling Dravida Munnetra Kazhagam (DMK) government while also highlighting central government support for local farmers. The … | O24: full-text | P24: gdelt | Q24: 2026-10-25
A25: 24 | B25: 2026-10-25 | C25: 2026 | D25: சிதிலமடைந்த அன்னதான மடத்தில் பழங்கால கல்வெட்டு கண்டெடுப்பு | E25: கல்வெட்டு, தொல்லியல் | F25: Inscription / Epigraphy, Archaeology / Excavation | G25: கல்வெட்டு, தொல்லியல் | I25: dailythanthi.com | J25: India | K25: Tamil | L25: https://www.dailythanthi.com/news/tamilnadu/ancient-inscription-discovered-in-ruined-annadhana-mutt | N25: தமிழக செய்திகள் சிதிலமடைந்த அன்னதான மடத்தில் பழங்கால கல்வெட்டு கண்டெடுப்பு 17 தூண்களுடன் கட்டப்பட்ட இந்த மடத்தில் தனியாக ஒரு விளக்குத்தூணும் உள்ளது. தென்காசி, வாசுதேவநல்லூர் அருகே தொல்லியல் ஆய்வில் சேதமடைந்த மடத்தில் கல்வெட்டு, பழங்கால சிற்பங்கள் கண்டுபிடிக்கப்பட்டுள்ளன. தென்பொதிகை ஆவணக்காப்பகத்தை ச… | O25: full-text | P25: gnews | Q25: 2026-10-26
